Workbook

Sheet Source Ledger
A1: Yanou & Partners IT Services - Fixed Asset Ledger
A2: Accounting extract | As of 2026-08-09
A4: Ledger Asset ID | B4: Asset Tag | C4: Serial Number | D4: Capitalized | E4: Acquisition Cost | F4: Accumulated Depreciation | G4: Net Book Value | H4: Ledger Status | I4: As-of Date
A5: FA-000001 | B5: MD-00001 | C5: MD-LA-050001 | D5: No | E5: 1895 | F5: 1895 | G5: =E5-F5 | H5: Active | I5: 46243.5
A6: FA-000002 | B6: MD-00002 | C6: MD-MO-050002 | D6: No | E6: 610 | F6: 296.94 | G6: =E6-F6 | H6: Active | I6: 46243.5
A7: FA-000003 | B7: MD-00003 | C7: MD-MO-050003 | D7: No | E7: 1085 | F7: 487.17 | G7: =E7-F7 | H7: Active | I7: 46243.5
A8: FA-000004 | B8: MD-00004 | C8: MD-NE-050004 | D8: Yes | E8: 6380 | F8: 5439.38 | G8: =E8-F8 | H8: Active | I8: 46243.5
A9: FA-000005 | B9: MD-00005 | C9: MD-LA-050005 | D9: No | E9: 2075 | F9: 2075 | G9: =E9-F9 | H9: Active | I9: 46243.5
A10: FA-000006 | B10: MD-00006 | C10: MD-MO-050006 | D10: No | E10: 790 | F10: 330.06 | G10: =E10-F10 | H10: Active | I10: 46243.5
A11: FA-000007 | B11: MD-00007 | C11: MD-MO-050007 | D11: No | E11: 950 | F11: 317.32 | G11: =E11-F11 | H11: Active | I11: 46243.5
A12: FA-000008 | B12: MD-00008 | C12: MD-NE-050008 | D12: Yes | E12: 6245 | F12: 4889.99 | G12: =E12-F12 | H12: Active | I12: 46243.5
A13: FA-000009 | B13: MD-00009 | C13: MD-LA-050009 | D13: No | E13: 1940 | F13: 1830.67 | G13: =E13-F13 | H13: Active | I13: 46243.5
A14: FA-000010 | B14: MD-00010 | C14: MD-MO-050010 | D14: No | E14: 655 | F14: 228.11 | G14: =E14-F14 | H14: Active | I14: 46243.5
A15: FA-000011 | B15: MD-00011 | C15: MD-MO-050011 | D15: No | E15: 1130 | F15: 247.5 | G15: =E15-F15 | H15: Active | I15: 46243.5
A16: FA-000012 | B16: MD-00012 | C16: MD-NE-050012 | D16: Yes | E16: 6425 | F16: 5871.77 | G16: =E16-F16 | H16: Active | I16: 46243.5
... A20: FA-000016 | B20: MD-00016 | C20: MD-NE-050016 | D20: Yes | E20: 6290 | F20: 5321.31 | G20: =E20-F20 | H20: Active | I20: 46243.5
A21: FA-000017 | B21: MD-00017 | C21: MD-LA-050017 | D21: No | E21: 2070 | F21: 2160 | G21: 0 | H21: Active | I21: 46243.5
A22: FA-000018 | B22: MD-00018 | C22: MD-MO-050018 | D22: No | E22: 700 | F22: 287.86 | G22: =E22-F22 | H22: Active | I22: 46243.5
A23: FA-000019 | B23: MD-00019 | C23: MD-MO-050019 | D23: No | E23: 1175 | F23: 379.6 | G23: =E23-F23 | H23: Active | I23: 46243.5
A24: FA-000020 | B24: MD-00020 | C24: MD-NE-050020 | D24: Yes | E24: 6470 | F24: 5023.66 | G24: =E24-F24 | H24: Active | I24: 46243.5
A25: FA-000021 | B25: MD-00021 | C25: MD-LA-050021 | D25: No | E25: 1850 | F25: 1725.48 | G25: =E25-F25 | H25: Active | I25: 46243.5
A26: FA-000022 | B26: MD-00022 | C26: MD-MO-050022 | D26: No | E26: 565 | F26: 193.05 | G26: =E26-F26 | H26: Active | I26: 46243.5
A27: FA-000023 | B27: MD-00023 | C27: MD-MO-050023 | D27: No | E27: 1040 | F27: 216.4 | G27: =E27-F27 | H27: Active | I27: 46243.5
A28: FA-000024 | B28: MD-00024 | C28: MD-NE-050024 | D28: Yes | E28: 6335 | F28: 5831.15 | G28: =E28-F28 | H28: Active | I28: 46243.5
A29: FA-000025 | B29: MD-00025 | C29: MD-LA-050021 | D29: No | E29: 2030 | F29: 2030 | G29: =E29-F29 | H29: Active | I29: 46243.5
A30: FA-000026 | B30: MD-00026 | C30: MD-MO-050026 | D30: No | E30: 745 | F30: 362.66 | G30: =E30-F30 | H30: Active | I30: 46243.5
A31: FA-000027 | B31: MD-00027 | C31: MD-MO-050027 | D31: No | E31: 1220 | F31: 547.79 | G31: =E31-F31 | H31: Active | I31: 46243.5
A32: FA-000028 | B32: MD-00028 | C32: MD-NE-050028 | D32: Yes | E32: 6200 | F32: 5285.91 | G32: =E32-F32 | H32: Active | I32: 46243.5
A33: FA-000029 | B33: MD-00029 | C33: MD-LA-050029 | D33: No | E33: 1895 | F33: 1895 | G33: =E33-F33 | H33: Active | I33: 46243.5
... A54: FA-000050 | B54: MD-00050 | C54: MD-MO-050050 | D54: No | E54: 565 | F54: 275.04 | G54: =E54-F54 | H54: Active | I54: 46243.5
A55: FA-000051 | B55: MD-00051 | C55: MD-MO-050051 | D55: No | E55: 1250 | F55: 641.97 | G55: 573.03 | H55: Active | I55: 46243.5
A56: FA-000052 | B56: MD-00052 | C56: MD-NE-050052 | D56: Yes | E56: 6335 | F56: 5401.01 | G56: =E56-F56 | H56: Active | I56: 46243.5
A57: FA-000053 | B57: MD-00053 | C57: MD-LA-050053 | D57: No | E57: 2030 | F57: 2030 | G57: =E57-F57 | H57: Active | I57: 46243.5
A58: FA-000054 | B58: MD-00054 | C58: MD-MO-050054 | D58: No | E58: 745 | F58: 311.26 | G58: =E58-F58 | H58: Active | I58: 46243.5
A59: FA-000055 | B59: MD-00055 | C59: MD-MO-050055 | D59: No | E59: 1220 | F59: 407.5 | G59: =E59-F59 | H59: Active | I59: 46243.5
A60: FA-000056 | B60: MD-00056 | C60: MD-NE-050056 | D60: Yes | E60: 6200 | F60: 4854.76 | G60: =E60-F60 | H60: Active | I60: 46243.5
A61: FA-000057 | B61: MD-00057 | C61: MD-LA-050057 | D61: No | E61: 1895 | F61: 1788.21 | G61: =E61-F61 | H61: Active | I61: 46243.5
A62: FA-000058 | B62: MD-00058 | C62: MD-MO-050058 | D62: No | E62: 610 | F62: 212.44 | G62: =E62-F62 | H62: Active | I62: 46243.5
A63: FA-000059 | B63: MD-00059 | C63: MD-MO-050059 | D63: No | E63: 1085 | F63: 237.65 | G63: =E63-F63 | H63: Active | I63: 46243.5
A64: FA-000060 | B64: MD-00060 | C64: MD-NE-050060 | D64: Yes | E64: 6380 | F64: 5830.65 | G64: =E64-F64 | H64: Active | I64: 46243.5
A65: FA-000061 | B65: MD-00061 | C65: MD-LA-050061 | D65: No | E65: 2075 | F65: 2075 | G65: =E65-F65 | H65: Active | I65: 46243.5
A66: FA-000062 | B66: MD-00062 | C66: MD-MO-050062 | D66: No | E66: 790 | F66: 379.37 | G66: =E66-F66 | H66: Active | I66: 46243.5
A67: FA-000063 | B67: MD-00063 | C67: MD-MO-050063 | D67: No | E67: 950 | F67: 416.15 | G67: =E67-F67 | H67: Active | I67: 46243.5
... A71: FA-000067 | B71: MD-00067 | C71: MD-MO-050067 | D71: No | E71: 1130 | F71: 365.07 | G71: =E71-F71 | H71: Active | I71: 46243.5
A72: FA-000068 | B72: MD-00068 | C72: MD-NE-050068 | D72: Yes | E72: 6480 | F72: 5163.72 | G72: 1436.28 | H72: Active | I72: 46243.5
A73: FA-000069 | B73: MD-00069 | C73: MD-LA-050069 | D73: No | E73: 2120 | F73: 1977.31 | G73: =E73-F73 | H73: Active | I73: 46243.5
A74: FA-000070 | B74: MD-00070 | C74: MD-MO-050070 | D74: No | E74: 520 | F74: 177.68 | G74: =E74-F74 | H74: Active | I74: 46243.5
A75: FA-000071 | B75: MD-00071 | C75: MD-MO-050071 | D75: No | E75: 995 | F75: 207.04 | G75: =E75-F75 | H75: Active | I75: 46243.5
A76: FA-000072 | B76: MD-00072 | C76: MD-NE-050072 | D76: Yes | E76: 6290 | F76: 5789.73 | G76: =E76-F76 | H76: Active | I76: 46243.5
A77: FA-000073 | B77: MD-00073 | C77: MD-LA-050073 | D77: No | E77: 1985 | F77: 1985 | G77: =E77-F77 | H77: Active | I77: 46243.5
A78: FA-000074 | B78: MD-00074 | C78: MD-MO-050074 | D78: No | E78: 700 | F78: 340.75 | G78: =E78-F78 | H78: Active | I78: 46243.5
A79: FA-000075 | B79: MD-00075 | C79: MD-MO-050075 | D79: No | E79: 1175 | F79: 527.58 | G79: =E79-F79 | H79: Active | I79: 46243.5
A80: FA-000076 | B80: MD-00076 | C80: MD-NE-050076 | D80: Yes | E80: 6470 | F80: 5516.11 | G80: =E80-F80 | H80: Active | I80: 46243.5
A81: FA-000077 | B81: MD-00077 | C81: MD-LA-050077 | D81: No | E81: 1850 | F81: 1850 | G81: =E81-F81 | H81: Active | I81: 46243.5
A82: FA-000078 | B82: MD-00078 | C82: MD-MO-050078 | D82: No | E82: 565 | F82: 236.05 | G82: =E82-F82 | H82: Active | I82: 46243.5
A83: FA-000079 | B83: MD-00079 | C83: MD-MO-050079 | D83: No | E83: 1040 | F83: 347.38 | G83: =E83-F83 | H83: Active | I83: 46243.5
A84: FA-000080 | B84: MD-00080 | C84: MD-NE-050080 | D84: Yes | E84: 6335 | F84: 4960.47 | G84: =E84-F84 | H84: Active | I84: 46243.5
... A88: FA-000084 | B88: MD-00084 | C88: MD-NE-050084 | D88: Yes | E88: 6200 | F88: 5666.15 | G88: =E88-F88 | H88: Active | I88: 46243.5
A89: FA-000085 | B89: MD-00085 | C89: MD-LA-050085 | D89: No | E89: 2090 | F89: 2070 | G89: 0 | H89: Active | I89: 46243.5
A90: FA-000086 | B90: MD-00086 | C90: MD-MO-050086 | D90: No | E90: 610 | F90: 292.93 | G90: =E90-F90 | H90: Active | I90: 46243.5
A91: FA-000087 | B91: MD-00087 | C91: MD-MO-050087 | D91: No | E91: 1085 | F91: 475.29 | G91: =E91-F91 | H91: Active | I91: 46243.5
A92: FA-000088 | B92: MD-00088 | C92: MD-NE-050088 | D92: Yes | E92: 6380 | F92: 5397.45 | G92: =E92-F92 | H92: Active | I92: 46243.5
A93: FA-000089 | B93: MD-00089 | C93: MD-LA-050089 | D93: No | E93: 2075 | F93: 2075 | G93: =E93-F93 | H93: Active | I93: 46243.5
A94: FA-000090 | B94: MD-00090 | C94: MD-MO-050090 | D94: No | E94: 790 | F94: 324.87 | G94: =E94-F94 | H94: Active | I94: 46243.5
A95: FA-000091 | B95: MD-00091 | C95: MD-MO-050091 | D95: No | E95: 950 | F95: 306.91 | G95: =E95-F95 | H95: Active | I95: 46243.5
A96: FA-000092 | B96: MD-00092 | C96: MD-NE-050088 | D96: Yes | E96: 6245 | F96: 4848.96 | G96: =E96-F96 | H96: Active | I96: 46243.5
A97: FA-000093 | B97: MD-00093 | C97: MD-LA-050093 | D97: No | E97: 1940 | F97: 1809.43 | G97: =E97-F97 | H97: Active | I97: 46243.5
A98: FA-000094 | B98: MD-00094 | C98: MD-MO-050094 | D98: No | E98: 655 | F98: 223.8 | G98: =E98-F98 | H98: Active | I98: 46243.5
A99: FA-000095 | B99: MD-00095 | C99: MD-MO-050095 | D99: No | E99: 1130 | F99: 235.13 | G99: =E99-F99 | H99: Active | I99: 46243.5
A100: FA-000096 | B100: MD-00096 | C100: MD-NE-050096 | D100: Yes | E100: 6425 | F100: 5913.99 | G100: =E100-F100 | H100: Active | I100: 46243.5
A101: FA-000097 | B101: MD-00097 | C101: MD-LA-050097 | D101: No | E101: 2120 | F101: 2120 | G101: =E101-F101 | H101: Active | I101: 46243.5
... A105: FA-000101 | B105: MD-00101 | C105: MD-LA-050101 | D105: No | E105: 1985 | F105: 1985 | G105: =E105-F105 | H105: Active | I105: 46243.5
A106: FA-000102 | B106: MD-00102 | C106: MD-MO-050102 | D106: No | E106: 820 | F106: 467.46 | G106: 407.54 | H106: Active | I106: 46243.5
A107: FA-000103 | B107: MD-00103 | C107: MD-MO-050103 | D107: No | E107: 1175 | F107: 392.47 | G107: =E107-F107 | H107: Active | I107: 46243.5
A108: FA-000104 | B108: MD-00104 | C108: MD-NE-050104 | D108: Yes | E108: 6470 | F108: 5066.17 | G108: =E108-F108 | H108: Active | I108: 46243.5
A109: FA-000105 | B109: MD-00105 | C109: MD-LA-050105 | D109: No | E109: 1850 | F109: 1745.74 | G109: =E109-F109 | H109: Active | I109: 46243.5
A110: FA-000106 | B110: MD-00106 | C110: MD-MO-050106 | D110: No | E110: 565 | F110: 196.76 | G110: =E110-F110 | H110: Active | I110: 46243.5
A111: FA-000107 | B111: MD-00107 | C111: MD-MO-050107 | D111: No | E111: 1040 | F111: 227.79 | G111: =E111-F111 | H111: Active | I111: 46243.5
A112: FA-000108 | B112: MD-00108 | C112: MD-NE-050108 | D112: Yes | E112: 6335 | F112: 5789.52 | G112: =E112-F112 | H112: Active | I112: 46243.5
A113: FA-000109 | B113: MD-00109 | C113: MD-LA-050109 | D113: No | E113: 2030 | F113: 2030 | G113: =E113-F113 | H113: Active | I113: 46243.5
A114: FA-000110 | B114: MD-00110 | C114: MD-MO-050110 | D114: No | E114: 745 | F114: 357.76 | G114: =E114-F114 | H114: Active | I114: 46243.5
A115: FA-000111 | B115: MD-00111 | C115: MD-MO-050111 | D115: No | E115: 1220 | F115: 1220 | G115: =E115-F115 | H115: Disposed | I115: 46243.5
A116: FA-000112 | B116: MD-00112 | C116: MD-NE-050112 | D116: Yes | E116: 6200 | F116: 6200 | G116: =E116-F116 | H116: Disposed | I116: 46243.5
A117: FA-000113 | B117: MD-00113 | C117: MD-LA-050113 | D117: No | E117: 1895 | F117: 1895 | G117: =E117-F117 | H117: Disposed | I117: 46243.5
A118: FA-000114 | B118: MD-00114 | C118: MD-MO-050114 | D118: No | E118: 610 | F118: 610 | G118: =E118-F118 | H118: Disposed | I118: 46243.5
... A122: FA-000118 | B122: MD-00118 | C122: MD-MO-050118 | D122: No | E122: 790 | F122: 790 | G122: =E122-F122 | H122: Disposed | I122: 46243.5
A123: FA-000119 | B123: MD-00119 | C123: MD-MO-050119 | D123: No | E123: 1115 | F123: 1125 | G123: 0 | H123: Disposed | I123: 46243.5
A124: FA-000120 | B124: MD-00120 | C124: MD-NE-050120 | D124: Yes | E124: 6245 | F124: 6245 | G124: =E124-F124 | H124: Disposed | I124: 46243.5
A125: FA-000121 | B125: MD-00121 | C125: MD-LA-050121 | D125: No | E125: 1940 | F125: 1940 | G125: =E125-F125 | H125: Active | I125: 46243.5
A126: FA-000122 | B126: MD-00122 | C126: MD-MO-050122 | D126: No | E126: 655 | F126: 318.85 | G126: =E126-F126 | H126: Active | I126: 46243.5
A127: FA-000123 | B127: MD-00123 | C127: MD-MO-050123 | D127: No | E127: 1130 | F127: 507.38 | G127: =E127-F127 | H127: Active | I127: 46243.5
A128: FA-000124 | B128: MD-00124 | C128: MD-NE-050124 | D128: Yes | E128: 6425 | F128: 5477.74 | G128: =E128-F128 | H128: Active | I128: 46243.5
A129: FA-000125 | B129: MD-00125 | C129: MD-LA-050125 | D129: No | E129: 2120 | F129: 2120 | G129: =E129-F129 | H129: Active | I129: 46243.5
A130: FA-000126 | B130: MD-00126 | C130: MD-MO-050126 | D130: No | E130: 520 | F130: 217.25 | G130: =E130-F130 | H130: Active | I130: 46243.5
A131: FA-000127 | B131: MD-00127 | C131: MD-MO-050127 | D131: No | E131: 995 | F131: 332.35 | G131: =E131-F131 | H131: Active | I131: 46243.5
A132: FA-000128 | B132: MD-00128 | C132: MD-NE-050128 | D132: Yes | E132: 6290 | F132: 4925.23 | G132: =E132-F132 | H132: Active | I132: 46243.5
A133: FA-000129 | B133: MD-00129 | C133: MD-LA-050129 | D133: No | E133: 1985 | F133: 1873.14 | G133: =E133-F133 | H133: Active | I133: 46243.5

Sheet Source Inventory
A1: Source Inventory (from it_asset_inventory.xlsx)
A2: Operational snapshot used by Corrected Register lookups.
A4: Asset Tag | B4: Serial Number | C4: Category | D4: Model | E4: Assigned Employee | F4: Location | G4: Lifecycle Status | H4: Acquisition Cost
A5: MD-00001 | B5: MD-LA-050001 | C5: Laptop | D5: HP EliteBook 840 G10 | E5: E0001 | F5: Chicago | G5: In Use | H5: 1895
A6: MD-00002 | B6: MD-MO-050002 | C6: Laptop | D6: Microsoft Surface Laptop 5 | E6: E0002 | F6: Dallas | G6: In Use | H6: 610
A7: MD-00003 | B7: MD-MO-050003 | C7: Laptop | D7: Lenovo ThinkPad X1 Carbon | E7: E0003 | F7: Denver | G7: In Use | H7: 1085
A8: MD-00004 | B8: MD-NE-050004 | C8: Laptop | D8: Lenovo ThinkPad T14 | E8: E0004 | F8: New York | G8: In Use | H8: 6380
A9: MD-00005 | B9: MD-LA-050005 | C9: Laptop | D9: MacBook Pro 14 | E9: E0005 | F9: Seattle | G9: In Use | H9: 2075
A10: MD-00006 | B10: MD-MO-050006 | C10: Laptop | D10: Dell Latitude 7440 | E10: E0006 | F10: Atlanta | G10: In Use | H10: 790
A11: MD-00007 | B11: MD-MO-050007 | C11: Laptop | D11: HP EliteBook 840 G10 | E11: E0007 | F11: Chicago | G11: In Use | H11: 950
A12: MD-00008 | B12: MD-NE-050008 | C12: Monitor | D12: Samsung ViewFinity S8 | E12: E0008 | F12: Dallas | G12: In Use | H12: 6245
A13: MD-00009 | B13: MD-LA-050009 | C13: Monitor | D13: BenQ PD2705U | E13: E0009 | F13: Denver | G13: In Use | H13: 1940
A14: MD-00010 | B14: MD-MO-050010 | C14: Monitor | D14: Dell U2723QE | E14: E0010 | F14: New York | G14: In Use | H14: 655
A15: MD-00011 | B15: MD-MO-050011 | C15: Monitor | D15: LG UltraFine 27MD5KL | E15: E0011 | F15: Seattle | G15: In Use | H15: 1130
A16: MD-00012 | B16: MD-NE-050012 | C16: Monitor | D16: Samsung ViewFinity S8 | E16: E0012 | F16: Atlanta | G16: In Use | H16: 6425
... A49: MD-00045 | B49: MD-LA-050045 | C49: Mobile Device | D49: Samsung Galaxy S23 FE | E49: E0045 | F49: Denver - Closed | G49: In Use | H49: 1985
A50: MD-00046 | B50: MD-MO-050046 | C50: Mobile Device | D50: iPhone 14 | F50: Chicago - Closed | G50: Available | H50: 700
A51: MD-00047 | B51: MD-MO-050047 | C51: Mobile Device | D51: Samsung Galaxy S24 | F51: Denver - Closed | G51: Available | H51: 1175
A52: MD-00048 | B52: MD-NE-050048 | C52: Mobile Device | D52: iPhone 15 | F52: Chicago - Closed | G52: Available | H52: 6470
A53: MD-00049 | B53: MD-LA-050049 | C53: Mobile Device | D53: Google Pixel 8 | F53: Denver - Closed | G53: Available | H53: 1850
A54: MD-00050 | B54: MD-MO-050050 | C54: Mobile Device | D54: iPhone 14 | F54: Chicago - Closed | G54: Available | H54: 565
A55: MD-00051 | B55: MD-MO-050051 | C55: Mobile Device | D55: Samsung Galaxy S24 | F55: Denver - Closed | G55: Available | H55: 1040
A56: MD-00052 | B56: MD-NE-050052 | C56: Mobile Device | D56: iPhone 15 | F56: Chicago - Closed | G56: Available | H56: 6335
A57: MD-00053 | B57: MD-LA-050053 | C57: Mobile Device | D57: Google Pixel 8 | F57: Denver - Closed | G57: Available | H57: 2030
A58: MD-00054 | B58: MD-MO-050054 | C58: Mobile Device | D58: Samsung Galaxy S23 FE | F58: Chicago - Closed | G58: Available | H58: 745
A59: MD-00055 | B59: MD-MO-050055 | C59: Mobile Device | D59: iPhone 14 | F59: Denver - Closed | G59: Available | H59: 1220
A60: MD-00056 | B60: MD-NE-050056 | C60: Mobile Device | D60: Samsung Galaxy S24 | F60: Chicago - Closed | G60: Available | H60: 6200
A61: MD-00057 | B61: MD-LA-050057 | C61: Mobile Device | D61: iPhone 15 | F61: Denver - Closed | G61: Available | H61: 1895
A62: MD-00058 | B62: MD-MO-050058 | C62: Mobile Device | D62: Google Pixel 8 | E62: E0071 | F62: Chicago - Closed | G62: Assigned | H62: 610
A63: MD-00059 | B63: MD-MO-050059 | C63: Mobile Device | D63: Samsung Galaxy S23 FE | E63: E0072 | F63: Denver - Closed | G63: Assigned | H63: 1085
A64: MD-00060 | B64: MD-NE-050060 | C64: Mobile Device | D64: Samsung Galaxy S24 | E64: E0073 | F64: Chicago - Closed | G64: Assigned | H64: 6380
A65: MD-00061 | B65: MD-LA-050061 | C65: Mobile Device | D65: iPhone 15 | E65: E0074 | F65: Denver - Closed | G65: Assigned | H65: 2075
A66: MD-00062 | B66: MD-MO-050062 | C66: Mobile Device | D66: Google Pixel 8 | E66: E0075 | F66: Chicago - Closed | G66: Assigned | H66: 790
A67: MD-00063 | B67: MD-MO-050063 | C67: Mobile Device | D67: Samsung Galaxy S23 FE | E67: E0076 | F67: Denver - Closed | G67: Assigned | H67: 950
A68: MD-00064 | B68: MD-NE-050064 | C68: Mobile Device | D68: iPhone 14 | E68: E0077 | F68: Chicago - Closed | G68: Assigned | H68: 6245
A69: MD-00065 | B69: MD-LA-050065 | C69: Mobile Device | D69: Samsung Galaxy S24 | E69: E0078 | F69: Denver - Closed | G69: Assigned | H69: 1940
A70: MD-00066 | B70: MD-MO-050066 | C70: Mobile Device | D70: iPhone 15 | E70: E0079 | F70: Chicago - Closed | G70: Assigned | H70: 655
A71: MD-00067 | B71: MD-MO-050067 | C71: Mobile Device | D71: Google Pixel 8 | E71: E0080 | F71: Denver - Closed | G71: Assigned | H71: 1130
A72: MD-00068 | B72: MD-NE-050068 | C72: Mobile Device | D72: Samsung Galaxy S23 FE | E72: E0081 | F72: Chicago - Closed | G72: Assigned | H72: 6425
A73: MD-00069 | B73: MD-LA-050069 | C73: Mobile Device | D73: iPhone 14 | E73: E0082 | F73: Denver - Closed | G73: Assigned | H73: 2120
... A124: MD-00120 | B124: MD-NE-050120 | C124: Laptop | D124: MacBook Pro 14 | E124: E0083 | F124: Chicago - Closed | G124: Assigned | H124: 6245
A125: MD-00121 | B125: MD-LA-050121 | C125: Laptop | D125: Dell Latitude 7440 | F125: Denver - Closed | G125: Assigned | H125: 1940
A126: MD-00122 | B126: MD-MO-050122 | C126: Laptop | D126: HP EliteBook 840 G10 | F126: Chicago - Closed | G126: Assigned | H126: 655
A127: MD-00123 | B127: MD-MO-050123 | C127: Laptop | D127: Microsoft Surface Laptop 5 | F127: Denver - Closed | G127: Assigned | H127: 1130
A128: MD-00124 | B128: MD-NE-050124 | C128: Laptop | D128: Lenovo ThinkPad X1 Carbon | F128: Chicago - Closed | G128: Assigned | H128: 6425
A129: MD-00125 | B129: MD-LA-050125 | C129: Laptop | D129: Lenovo ThinkPad T14 | F129: Denver - Closed | G129: Assigned | H129: 2120
A130: MD-00126 | B130: MD-MO-050126 | C130: Laptop | D130: MacBook Pro 14 | F130: Chicago - Closed | G130: Assigned | H130: 520
A131: MD-00127 | B131: MD-MO-050127 | C131: Laptop | D131: Dell Latitude 7440 | E131: E0061 | F131: Denver | G131: In Use | H131: 995
A132: MD-00128 | B132: MD-NE-050128 | C132: Laptop | D132: HP EliteBook 840 G10 | E132: E0062 | F132: New York | G132: In Use | H132: 6290
A133: MD-00129 | B133: MD-LA-050129 | C133: Laptop | D133: Microsoft Surface Laptop 5 | E133: E0063 | F133: Seattle | G133: In Use | H133: 1985
A134: MD-00130 | B134: MD-MO-050130 | C134: Laptop | D134: Lenovo ThinkPad T14 | E134: E0064 | F134: Atlanta | G134: In Use | H134: 700
A135: MD-00131 | B135: MD-MO-050131 | C135: Laptop | D135: MacBook Pro 14 | E135: E0065 | F135: Chicago | G135: In Use | H135: 1175
A136: MD-00132 | B136: MD-NE-050132 | C136: Laptop | D136: Dell Latitude 7440 | E136: E0066 | F136: Dallas | G136: In Use | H136: 6470

Sheet Dashboard
A1: Yanou & Partners IT Services - IT Asset Reconciliation Dashboard
A2: Prepared for IT Operations Manager, Finance Controller, HR Operations Lead, and Internal Audit | As of 2026-08-09 | Policy figure and dock image used as leads only
A4: KPI | B4: Value
A5: Assets reviewed | B5: 132
A6: Corrected register acquisition cost | B6: 332115
A7: Remaining book value (ledger NBV where present) | B7: 61526.6
A8: Open exceptions | B8: 163
A9: Certification blockers (Critical impact) | B9: 43
A10: Assets Missing / Cannot Locate | B10: 12
A11: Overdue returns (label ≠ proof) | B11: 12
A12: Verified disposed with certificate | B12: 8
A13: Custody chains documented | B13: 65
A14: Multimodal image leads cited | B14: ITAM_control_matrix.png; receiving_exception_scan_1ZMD00000082.png
A17: Asset Counts and Book Value by Verified Status | E17: By Device Category
A18: Verified Status | B18: Asset Count | C18: Book Value | E18: Category | F18: Asset Count | G18: Book Value
A19: Available | B19: 25 | C19: 12961 | E19: Laptop | F19: 40 | G19: 13030.88
A20: Disposed | B20: 8 | C20: 0 | E20: Mobile Device | F20: 36 | G20: 18983.58
A21: In Transit - Exception | B21: 2 | C21: 1019.4 | E21: Monitor | F21: 28 | G21: 15372.27
A22: In Use | B22: 51 | C22: 25477.76 | E22: Network Asset | F22: 28 | G22: 14139.87
A23: Missing | B23: 12 | C23: 6214.38
A24: Pending Redeployment | B24: 10 | C24: 4851.08
A25: Retired/Pending Disposal | B25: 12 | C25: 4811.33
A26: Return Overdue | B26: 12 | C26: 6191.65
A30: By Verified Location | E30: Open Exceptions by Type
A31: Verified Location | B31: Asset Count | C31: Book Value | E31: Type | F31: Count | G31: Financial Exposure
A32: Chicago | B32: 16 | C32: 5184.18 | E32: Cannot Locate | F32: 12 | G32: 6214.38
A33: Atlanta | B33: 15 | C33: 6267.29 | E33: Closed Location Assignment | F33: 61 | G33: 29063.84
A34: Dallas | B34: 15 | C34: 11070.95 | E34: Duplicate Serial Number | F34: 4 | G34: 2503.11
A35: Seattle | B35: 15 | C35: 5149.95 | E35: Former Employee Assignment | F35: 43 | G35: 22627.56
A36: Denver | B36: 14 | C36: 5551.75 | E36: Inventory-to-Ledger Difference | F36: 8 | G36: 7275
A37: New York | B37: 14 | C37: 10526 | E37: Missing Disposal Evidence | F37: 12 | G37: 4811.33
A38: Unknown | B38: 12 | C38: 6214.38 | E38: Overdue Return | F38: 12 | G38: 6191.65
A39: Remote - Former Employee | B39: 10 | C39: 4878.51 | E39: Shipment Mismatch | F39: 4 | G39: 2332.54
A40: Disposed | B40: 8 | C40: 0 | E40: Unapproved Transfer | F40: 5 | G40: 2869.32
A41: Atlanta Warehouse | B41: 7 | C41: 4351.05 | E41: Below Capitalization Threshold | F41: 2 | G41: 0
A42: Carrier Network / Unverified | B42: 4 | C42: 2332.54
A43: Disposed (certificate missing) | B43: 2 | C43: 0
A45: Key finding - Duplicate serial identities (both pairs)
A46: Duplicate Serial | B46: Asset Tags Sharing This Serial | C46: Exception IDs
A47: MD-LA-050021 | B47: MD-00021 and MD-00025 | C47: EX-0002; EX-0004
A48: MD-NE-050088 | B48: MD-00088 and MD-00092 | C48: EX-0102; EX-0111
A49: Flags duplicate serial MD-LA-050021 across MD-00021 and MD-00025, and duplicate serial MD-NE-050088 across MD-00088 and MD-00092.

Sheet Corrected Register
A1: Corrected Asset Register
A2: Every reviewed asset with verified custodian, location, status, evidence (including multimodal leads where applicable), cost, book value, and confidence. As of 2026-08-09.
A4: Asset Tag | B4: Serial Number | C4: Category | D4: Model | E4: Register Custodian | F4: Register Location | G4: Register Status | H4: Verified Custodian | I4: Verified Location | J4: Verified Status | K4: Evidence Source | L4: Last Verified Date | M4: Acquisition Cost | N4: Remaining Book Value | O4: Ledger Asset ID | P4: Capitalized | Q4: Confidence | R4: Exception IDs | S4: Escalation Required | T4: Ledger Acquisition Cost | U4: Ledger Status | V4: FA Net Book Value | W4: Ledger vs Register Cost Diff | X4: Book Value Present
A5: MD-00001 | B5: =IFERROR(XLOOKUP(A5,'Source Inventory'!$A$5:$A$200,'Source Inventory'!$B$5:$B$200),"") | C5: =IFERROR(XLOOKUP(A5,'Source Inventory'!$A$5:$A$200,'Source Inventory'!$C$5:$C$200),"") | D5: =IFERROR(XLOOKUP(A5,'Source Inventory'!$A$5:$A$200,'Source Inventory'!$D$5:$D$200),"") | E5: =IFERROR(XLOOKUP(A5,'Source Inventory'!$A$5:$A$200,'Source Inventory'!$E$5:$E$200),"") | F5: =IFERROR(XLOOKUP(A5,'Source Inventory'!$A$5:$A$200,'Source Inventory'!$F$5:$F$200),"") | G5: =IFERROR(XLOOKUP(A5,'Source Inventory'!$A$5:$A$200,'Source Inventory'!$G$5:$G$200),"") | H5: E0001 | I5: Chicago | J5: In Use | K5: Files reviewed for MD-00001: HP EliteBook 840 G10, basis $1895, operating site Chicago, status In Use. Source Ledger FA-000001; net book value $0. equipment_transfer_log TR-00001 posted Jan 21, 2026; inbound 2026-01-21 approval APR-00001. hr_employee_status lists Priya Shah (E0001) as Active. hardware_purchase_orders.csv ties MD-00001 to PO-2022-0001. | L5: 2026-08-05 | M5: =IFERROR(XLOOKUP(A5,'Source Inventory'!$A$5:$A$200,'Source Inventory'!$H$5:$H$200),"") | N5: 0 | O5: =IFERROR(XLOOKUP(A5,'Source Ledger'!$B$5:$B$200,'Source Ledger'!$A$5:$A$200),"") | P5: =IFERROR(XLOOKUP(A5,'Source Ledger'!$B$5:$B$200,'Source Ledger'!$D$5:$D$200),"") | Q5: High | S5: =IF(OR(R5="",R5=0),"No","Yes") | T5: =IFERROR(XLOOKUP(A5,'Source Ledger'!$B$5:$B$200,'Source Ledger'!$E$5:$E$200),"") | U5: =IFERROR(XLOOKUP(A5,'Source Ledger'!$B$5:$B$200,'Source Ledger'!$H$5:$H$200),"") | V5: =IFERROR(XLOOKUP(A5,'Source Ledger'!$B$5:$B$200,'Source Ledger'!$G$5:$G$200),"") | W5: =IF(OR(M5="",T5=""),"",T5-M5) | X5: =IF(V5="","No","Yes")
A6: MD-00002 | B6: =IFERROR(XLOOKUP(A6,'Source Inventory'!$A$5:$A$200,'Source Inventory'!$B$5:$B$200),"") | C6: =IFERROR(XLOOKUP(A6,'Source Inventory'!$A$5:$A$200,'Source Inventory'!$C$5:$C$200),"") | D6: =IFERROR(XLOOKUP(A6,'Source Inventory'!$A$5:$A$200,'Source Inventory'!$D$5:$D$200),"") | E6: =IFERROR(XLOOKUP(A6,'Source Inventory'!$A$5:$A$200,'Source Inventory'!$E$5:$E$200),"") | F6: =IFERROR(XLOOKUP(A6,'Source Inventory'!$A$5:$A$200,'Source Inventory'!$F$5:$F$200),"") | G6: =IFERROR(XLOOKUP(A6,'Source Inventory'!$A$5:$A$200,'Source Inventory'!$G$5:$G$200),"") | H6: E0002 | I6: Dallas | J6: In Use | K6: Cross-checked MD-00002 (MD-MO-050002, Microsoft Surface Laptop 5) against HR, transfers, and ledger extracts. Source Ledger FA-000002; net book value $313.06. equipment_transfer_log TR-00002 posted Feb 23, 2026; inbound 2026-02-25 approval APR-00002. hr_employee_status lists Marcus Ellison (E0002) as Active. capital PO PO-2022-0001 supports the cost basis. | L6: 2026-08-05 | M6: =IFERROR(XLOOKUP(A6,'Source Inventory'!$A$5:$A$200,'Source Inventory'!$H$5:$H$200),"") | N6: 313.06 | O6: =IFERROR(XLOOKUP(A6,'Source Ledger'!$B$5:$B$200,'Source Ledger'!$A$5:$A$200),"") | P6: =IFERROR(XLOOKUP(A6,'Source Ledger'!$B$5:$B$200,'Source Ledger'!$D$5:$D$200),"") | Q6: High | S6: =IF(OR(R6="",R6=0),"No","Yes") | T6: =IFERROR(XLOOKUP(A6,'Source Ledger'!$B$5:$B$200,'Source Ledger'!$E$5:$E$200),"") | U6: =IFERROR(XLOOKUP(A6,'Source Ledger'!$B$5:$B$200,'Source Ledger'!$H$5:$H$200),"") | V6: =IFERROR(XLOOKUP(A6,'Source Ledger'!$B$5:$B$200,'Source Ledger'!$G$5:$G$200),"") | W6: =IF(OR(M6="",T6=""),"",T6-M6) | X6: =IF(V6="","No","Yes")
A7: MD-00003 | B7: =IFERROR(XLOOKUP(A7,'Source Inventory'!$A$5:$A$200,'Source Inventory'!$B$5:$B$200),"") | C7: =IFERROR(XLOOKUP(A7,'Source Inventory'!$A$5:$A$200,'Source Inventory'!$C$5:$C$200),"") | D7: =IFERROR(XLOOKUP(A7,'Source Inventory'!$A$5:$A$200,'Source Inventory'!$D$5:$D$200),"") | E7: =IFERROR(XLOOKUP(A7,'Source Inventory'!$A$5:$A$200,'Source Inventory'!$E$5:$E$200),"") | F7: =IFERROR(XLOOKUP(A7,'Source Inventory'!$A$5:$A$200,'Source Inventory'!$F$5:$F$200),"") | G7: =IFERROR(XLOOKUP(A7,'Source Inventory'!$A$5:$A$200,'Source Inventory'!$G$5:$G$200),"") | H7: E0003 | I7: Denver | J7: In Use | K7: Cross-checked MD-00003 (MD-MO-050003, Lenovo ThinkPad X1 Carbon) against HR, transfers, and ledger extracts. Source Ledger FA-000003; net book value $597.83. equipment_transfer_log TR-00003 posted Mar 31, 2026; inbound 2026-04-03 approval APR-00003. hr_employee_status lists Elena Kovacs (E0003) as Active. hardware_purchase_orders.csv ties MD-00003 to PO-2022-0001. | L7: 2026-08-05 | M7: =IFERROR(XLOOKUP(A7,'Source Inventory'!$A$5:$A$200,'Source Inventory'!$H$5:$H$200),"") | N7: 597.83 | O7: =IFERROR(XLOOKUP(A7,'Source Ledger'!$B$5:$B$200,'Source Ledger'!$A$5:$A$200),"") | P7: =IFERROR(XLOOKUP(A7,'Source Ledger'!$B$5:$B$200,'Source Ledger'!$D$5:$D$200),"") | Q7: High | S7: =IF(OR(R7="",R7=0),"No","Yes") | T7: =IFERROR(XLOOKUP(A7,'Source Ledger'!$B$5:$B$200,'Source Ledger'!$E$5:$E$200),"") | U7: =IFERROR(XLOOKUP(A7,'Source Ledger'!$B$5:$B$200,'Source Ledger'!$H$5:$H$200),"") | V7: =IFERROR(XLOOKUP(A7,'Source Ledger'!$B$5:$B$200,'Source Ledger'!$G$5:$G$200),"") | W7: =IF(OR(M7="",T7=""),"",T7-M7) | X7: =IF(V7="","No","Yes")
A8: MD-00004 | B8: =IFERROR(XLOOKUP(A8,'Source Inventory'!$A$5:$A$200,'Source Inventory'!$B$5:$B$200),"") | C8: =IFERROR(XLOOKUP(A8,'Source Inventory'!$A$5:$A$200,'Source Inventory'!$C$5:$C$200),"") | D8: =IFERROR(XLOOKUP(A8,'Source Inventory'!$A$5:$A$200,'Source Inventory'!$D$5:$D$200),"") | E8: =IFERROR(XLOOKUP(A8,'Source Inventory'!$A$5:$A$200,'Source Inventory'!$E$5:$E$200),"") | F8: =IFERROR(XLOOKUP(A8,'Source Inventory'!$A$5:$A$200,'Source Inventory'!$F$5:$F$200),"") | G8: =IFERROR(XLOOKUP(A8,'Source Inventory'!$A$5:$A$200,'Source Inventory'!$G$5:$G$200),"") | H8: E0004 | I8: New York | J8: In Use | K8: Cross-checked MD-00004 (MD-NE-050004, Lenovo ThinkPad T14) against HR, transfers, and ledger extracts. Source Ledger FA-000004; net book value $940.62. equipment_transfer_log TR-00004 posted May 01, 2026; inbound 2026-05-01 approval APR-00004. hr_employee_status lists James Whitaker (E0004) as Active. hardware_purchase_orders.csv ties MD-00004 to PO-2023-0002. | L8: 2026-08-05 | M8: =IFERROR(XLOOKUP(A8,'Source Inventory'!$A$5:$A$200,'Source Inventory'!$H$5:$H$200),"") | N8: 940.62 | O8: =IFERROR(XLOOKUP(A8,'Source Ledger'!$B$5:$B$200,'Source Ledger'!$A$5:$A$200),"") | P8: =IFERROR(XLOOKUP(A8,'Source Ledger'!$B$5:$B$200,'Source Ledger'!$D$5:$D$200),"") | Q8: High | S8: =IF(OR(R8="",R8=0),"No","Yes") | T8: =IFERROR(XLOOKUP(A8,'Source Ledger'!$B$5:$B$200,'Source Ledger'!$E$5:$E$200),"") | U8: =IFERROR(XLOOKUP(A8,'Source Ledger'!$B$5:$B$200,'Source Ledger'!$H$5:$H$200),"") | V8: =IFERROR(XLOOKUP(A8,'Source Ledger'!$B$5:$B$200,'Source Ledger'!$G$5:$G$200),"") | W8: =IF(OR(M8="",T8=""),"",T8-M8) | X8: =IF(V8="","No","Yes")
A9: MD-00005 | B9: =IFERROR(XLOOKUP(A9,'Source Inventory'!$A$5:$A$200,'Source Inventory'!$B$5:$B$200),"") | C9: =IFERROR(XLOOKUP(A9,'Source Inventory'!$A$5:$A$200,'Source Inventory'!$C$5:$C$200),"") | D9: =IFERROR(XLOOKUP(A9,'Source Inventory'!$A$5:$A$200,'Source Inventory'!$D$5:$D$200),"") | E9: =IFERROR(XLOOKUP(A9,'Source Inventory'!$A$5:$A$200,'Source Inventory'!$E$5:$E$200),"") | F9: =IFERROR(XLOOKUP(A9,'Source Inventory'!$A$5:$A$200,'Source Inventory'!$F$5:$F$200),"") | G9: =IFERROR(XLOOKUP(A9,'Source Inventory'!$A$5:$A$200,'Source Inventory'!$G$5:$G$200),"") | H9: E0005 | I9: Seattle | J9: In Use | K9: Reconciliation packet cites MD-00005 with acquisition $2075 and custody In Use at Seattle. Source Ledger FA-000005; net book value $0. capital PO PO-2023-0002 supports the cost basis. equipment_transfer_log TR-00005 posted Jun 05, 2026; inbound 2026-06-08 approval APR-00005. hr_employee_status lists Aisha Rahman (E0005) as Active. | L9: 2026-08-05 | M9: =IFERROR(XLOOKUP(A9,'Source Inventory'!$A$5:$A$200,'Source Inventory'!$H$5:$H$200),"") | N9: 0 | O9: =IFERROR(XLOOKUP(A9,'Source Ledger'!$B$5:$B$200,'Source Ledger'!$A$5:$A$200),"") | P9: =IFERROR(XLOOKUP(A9,'Source Ledger'!$B$5:$B$200,'Source Ledger'!$D$5:$D$200),"") | Q9: High | S9: =IF(OR(R9="",R9=0),"No","Yes") | T9: =IFERROR(XLOOKUP(A9,'Source Ledger'!$B$5:$B$200,'Source Ledger'!$E$5:$E$200),"") | U9: =IFERROR(XLOOKUP(A9,'Source Ledger'!$B$5:$B$200,'Source Ledger'!$H$5:$H$200),"") | V9: =IFERROR(XLOOKUP(A9,'Source Ledger'!$B$5:$B$200,'Source Ledger'!$G$5:$G$200),"") | W9: =IF(OR(M9="",T9=""),"",T9-M9) | X9: =IF(V9="","No","Yes")
A10: MD-00006 | B10: =IFERROR(XLOOKUP(A10,'Source Inventory'!$A$5:$A$200,'Source Inventory'!$B$5:$B$200),"") | C10: =IFERROR(XLOOKUP(A10,'Source Inventory'!$A$5:$A$200,'Source Inventory'!$C$5:$C$200),"") | D10: =IFERROR(XLOOKUP(A10,'Source Inventory'!$A$5:$A$200,'Source Inventory'!$D$5:$D$200),"") | E10: =IFERROR(XLOOKUP(A10,'Source Inventory'!$A$5:$A$200,'Source Inventory'!$E$5:$E$200),"") | F10: =IFERROR(XLOOKUP(A10,'Source Inventory'!$A$5:$A$200,'Source Inventory'!$F$5:$F$200),"") | G10: =IFERROR(XLOOKUP(A10,'Source Inventory'!$A$5:$A$200,'Source Inventory'!$G$5:$G$200),"") | H10: E0006 | I10: Atlanta | J10: In Use | K10: Cross-checked MD-00006 (MD-MO-050006, Dell Latitude 7440) against HR, transfers, and ledger extracts. Source Ledger FA-000006; net book value $459.94. equipment_transfer_log TR-00006 posted Jan 10, 2026; inbound 2026-01-12 approval APR-00006. hr_employee_status lists Colin Bergstrom (E0006) as Active. order PO-2023-0002 appears in the purchasing extract. | L10: 2026-08-05 | M10: =IFERROR(XLOOKUP(A10,'Source Inventory'!$A$5:$A$200,'Source Inventory'!$H$5:$H$200),"") | N10: 459.94 | O10: =IFERROR(XLOOKUP(A10,'Source Ledger'!$B$5:$B$200,'Source Ledger'!$A$5:$A$200),"") | P10: =IFERROR(XLOOKUP(A10,'Source Ledger'!$B$5:$B$200,'Source Ledger'!$D$5:$D$200),"") | Q10: High | S10: =IF(OR(R10="",R10=0),"No","Yes") | T10: =IFERROR(XLOOKUP(A10,'Source Ledger'!$B$5:$B$200,'Source Ledger'!$E$5:$E$200),"") | U10: =IFERROR(XLOOKUP(A10,'Source Ledger'!$B$5:$B$200,'Source Ledger'!$H$5:$H$200),"") | V10: =IFERROR(XLOOKUP(A10,'Source Ledger'!$B$5:$B$200,'Source Ledger'!$G$5:$G$200),"") | W10: =IF(OR(M10="",T10=""),"",T10-M10) | X10: =IF(V10="","No","Yes")
A11: MD-00007 | B11: =IFERROR(XLOOKUP(A11,'Source Inventory'!$A$5:$A$200,'Source Inventory'!$B$5:$B$200),"") | C11: =IFERROR(XLOOKUP(A11,'Source Inventory'!$A$5:$A$200,'Source Inventory'!$C$5:$C$200),"") | D11: =IFERROR(XLOOKUP(A11,'Source Inventory'!$A$5:$A$200,'Source Inventory'!$D$5:$D$200),"") | E11: =IFERROR(XLOOKUP(A11,'Source Inventory'!$A$5:$A$200,'Source Inventory'!$E$5:$E$200),"") | F11: =IFERROR(XLOOKUP(A11,'Source Inventory'!$A$5:$A$200,'Source Inventory'!$F$5:$F$200),"") | G11: =IFERROR(XLOOKUP(A11,'Source Inventory'!$A$5:$A$200,'Source Inventory'!$G$5:$G$200),"") | H11: E0007 | I11: Chicago | J11: In Use | K11: Cross-checked MD-00007 (MD-MO-050007, HP EliteBook 840 G10) against HR, transfers, and ledger extracts. Source Ledger FA-000007; net book value $632.68. equipment_transfer_log TR-00007 posted Feb 11, 2026; inbound 2026-02-17 approval APR-00007. hr_employee_status lists Sofia Alvarez (E0007) as Active. PO-2023-0002 is the cited purchase order. | L11: 2026-08-05 | M11: =IFERROR(XLOOKUP(A11,'Source Inventory'!$A$5:$A$200,'Source Inventory'!$H$5:$H$200),"") | N11: 632.68 | O11: =IFERROR(XLOOKUP(A11,'Source Ledger'!$B$5:$B$200,'Source Ledger'!$A$5:$A$200),"") | P11: =IFERROR(XLOOKUP(A11,'Source Ledger'!$B$5:$B$200,'Source Ledger'!$D$5:$D$200),"") | Q11: High | S11: =IF(OR(R11="",R11=0),"No","Yes") | T11: =IFERROR(XLOOKUP(A11,'Source Ledger'!$B$5:$B$200,'Source Ledger'!$E$5:$E$200),"") | U11: =IFERROR(XLOOKUP(A11,'Source Ledger'!$B$5:$B$200,'Source Ledger'!$H$5:$H$200),"") | V11: =IFERROR(XLOOKUP(A11,'Source Ledger'!$B$5:$B$200,'Source Ledger'!$G$5:$G$200),"") | W11: =IF(OR(M11="",T11=""),"",T11-M11) | X11: =IF(V11="","No","Yes")
A12: MD-00008 | B12: =IFERROR(XLOOKUP(A12,'Source Inventory'!$A$5:$A$200,'Source Inventory'!$B$5:$B$200),"") | C12: =IFERROR(XLOOKUP(A12,'Source Inventory'!$A$5:$A$200,'Source Inventory'!$C$5:$C$200),"") | D12: =IFERROR(XLOOKUP(A12,'Source Inventory'!$A$5:$A$200,'Source Inventory'!$D$5:$D$200),"") | E12: =IFERROR(XLOOKUP(A12,'Source Inventory'!$A$5:$A$200,'Source Inventory'!$E$5:$E$200),"") | F12: =IFERROR(XLOOKUP(A12,'Source Inventory'!$A$5:$A$200,'Source Inventory'!$F$5:$F$200),"") | G12: =IFERROR(XLOOKUP(A12,'Source Inventory'!$A$5:$A$200,'Source Inventory'!$G$5:$G$200),"") | H12: E0008 | I12: Dallas | J12: In Use | K12: Cross-checked MD-00008 (MD-NE-050008, Samsung ViewFinity S8) against HR, transfers, and ledger extracts. Source Ledger FA-000008; net book value $1355.01. equipment_transfer_log TR-00008 posted Mar 16, 2026; inbound 2026-03-19 approval APR-00008. hr_employee_status lists Derek Nguyen (E0008) as Active. acquisition recorded on PO-2023-0002. | L12: 2026-08-05 | M12: =IFERROR(XLOOKUP(A12,'Source Inventory'!$A$5:$A$200,'Source Inventory'!$H$5:$H$200),"") | N12: 1355.01 | O12: =IFERROR(XLOOKUP(A12,'Source Ledger'!$B$5:$B$200,'Source Ledger'!$A$5:$A$200),"") | P12: =IFERROR(XLOOKUP(A12,'Source Ledger'!$B$5:$B$200,'Source Ledger'!$D$5:$D$200),"") | Q12: High | S12: =IF(OR(R12="",R12=0),"No","Yes") | T12: =IFERROR(XLOOKUP(A12,'Source Ledger'!$B$5:$B$200,'Source Ledger'!$E$5:$E$200),"") | U12: =IFERROR(XLOOKUP(A12,'Source Ledger'!$B$5:$B$200,'Source Ledger'!$H$5:$H$200),"") | V12: =IFERROR(XLOOKUP(A12,'Source Ledger'!$B$5:$B$200,'Source Ledger'!$G$5:$G$200),"") | W12: =IF(OR(M12="",T12=""),"",T12-M12) | X12: =IF(V12="","No","Yes")
A13: MD-00009 | B13: =IFERROR(XLOOKUP(A13,'Source Inventory'!$A$5:$A$200,'Source Inventory'!$B$5:$B$200),"") | C13: =IFERROR(XLOOKUP(A13,'Source Inventory'!$A$5:$A$200,'Source Inventory'!$C$5:$C$200),"") | D13: =IFERROR(XLOOKUP(A13,'Source Inventory'!$A$5:$A$200,'Source Inventory'!$D$5:$D$200),"") | E13: =IFERROR(XLOOKUP(A13,'Source Inventory'!$A$5:$A$200,'Source Inventory'!$E$5:$E$200),"") | F13: =IFERROR(XLOOKUP(A13,'Source Inventory'!$A$5:$A$200,'Source Inventory'!$F$5:$F$200),"") | G13: =IFERROR(XLOOKUP(A13,'Source Inventory'!$A$5:$A$200,'Source Inventory'!$G$5:$G$200),"") | H13: E0009 | I13: Denver | J13: In Use | K13: Working conclusion for MD-00009 (MD-LA-050009): In Use at Denver; cost $1940. equipment_transfer_log TR-00009 posted Apr 20, 2026; inbound 2026-04-21 approval APR-00009. hr_employee_status lists Hannah Cole (E0009) as Active. PO-2024-0003 is the cited purchase order. Source Ledger FA-000009; net book value $109.33. | L13: 2026-08-05 | M13: =IFERROR(XLOOKUP(A13,'Source Inventory'!$A$5:$A$200,'Source Inventory'!$H$5:$H$200),"") | N13: 109.33 | O13: =IFERROR(XLOOKUP(A13,'Source Ledger'!$B$5:$B$200,'Source Ledger'!$A$5:$A$200),"") | P13: =IFERROR(XLOOKUP(A13,'Source Ledger'!$B$5:$B$200,'Source Ledger'!$D$5:$D$200),"") | Q13: High | S13: =IF(OR(R13="",R13=0),"No","Yes") | T13: =IFERROR(XLOOKUP(A13,'Source Ledger'!$B$5:$B$200,'Source Ledger'!$E$5:$E$200),"") | U13: =IFERROR(XLOOKUP(A13,'Source Ledger'!$B$5:$B$200,'Source Ledger'!$H$5:$H$200),"") | V13: =IFERROR(XLOOKUP(A13,'Source Ledger'!$B$5:$B$200,'Source Ledger'!$G$5:$G$200),"") | W13: =IF(OR(M13="",T13=""),"",T13-M13) | X13: =IF(V13="","No","Yes")
A14: MD-00010 | B14: =IFERROR(XLOOKUP(A14,'Source Inventory'!$A$5:$A$200,'Source Inventory'!$B$5:$B$200),"") | C14: =IFERROR(XLOOKUP(A14,'Source Inventory'!$A$5:$A$200,'Source Inventory'!$C$5:$C$200),"") | D14: =IFERROR(XLOOKUP(A14,'Source Inventory'!$A$5:$A$200,'Source Inventory'!$D$5:$D$200),"") | E14: =IFERROR(XLOOKUP(A14,'Source Inventory'!$A$5:$A$200,'Source Inventory'!$E$5:$E$200),"") | F14: =IFERROR(XLOOKUP(A14,'Source Inventory'!$A$5:$A$200,'Source Inventory'!$F$5:$F$200),"") | G14: =IFERROR(XLOOKUP(A14,'Source Inventory'!$A$5:$A$200,'Source Inventory'!$G$5:$G$200),"") | H14: E0010 | I14: New York | J14: In Use | K14: Working conclusion for MD-00010 (MD-MO-050010): In Use at New York; cost $655. equipment_transfer_log TR-00010 posted May 22, 2026; inbound 2026-05-28 approval APR-00010. Source Ledger FA-000010; net book value $426.89. PO PO-2024-0003 documents the buy for MD-00010. hr_employee_status lists Owen Patel (E0010) as Active. | L14: 2026-08-05 | M14: =IFERROR(XLOOKUP(A14,'Source Inventory'!$A$5:$A$200,'Source Inventory'!$H$5:$H$200),"") | N14: 426.89 | O14: =IFERROR(XLOOKUP(A14,'Source Ledger'!$B$5:$B$200,'Source Ledger'!$A$5:$A$200),"") | P14: =IFERROR(XLOOKUP(A14,'Source Ledger'!$B$5:$B$200,'Source Ledger'!$D$5:$D$200),"") | Q14: High | S14: =IF(OR(R14="",R14=0),"No","Yes") | T14: =IFERROR(XLOOKUP(A14,'Source Ledger'!$B$5:$B$200,'Source Ledger'!$E$5:$E$200),"") | U14: =IFERROR(XLOOKUP(A14,'Source Ledger'!$B$5:$B$200,'Source Ledger'!$H$5:$H$200),"") | V14: =IFERROR(XLOOKUP(A14,'Source Ledger'!$B$5:$B$200,'Source Ledger'!$G$5:$G$200),"") | W14: =IF(OR(M14="",T14=""),"",T14-M14) | X14: =IF(V14="","No","Yes")
A15: MD-00011 | B15: =IFERROR(XLOOKUP(A15,'Source Inventory'!$A$5:$A$200,'Source Inventory'!$B$5:$B$200),"") | C15: =IFERROR(XLOOKUP(A15,'Source Inventory'!$A$5:$A$200,'Source Inventory'!$C$5:$C$200),"") | D15: =IFERROR(XLOOKUP(A15,'Source Inventory'!$A$5:$A$200,'Source Inventory'!$D$5:$D$200),"") | E15: =IFERROR(XLOOKUP(A15,'Source Inventory'!$A$5:$A$200,'Source Inventory'!$E$5:$E$200),"") | F15: =IFERROR(XLOOKUP(A15,'Source Inventory'!$A$5:$A$200,'Source Inventory'!$F$5:$F$200),"") | G15: =IFERROR(XLOOKUP(A15,'Source Inventory'!$A$5:$A$200,'Source Inventory'!$G$5:$G$200),"") | H15: E0011 | I15: Seattle | J15: In Use | K15: Working conclusion for MD-00011 (MD-MO-050011): In Use at Seattle; cost $1130. equipment_transfer_log TR-00011 posted Jun 26, 2026; inbound 2026-06-28 approval APR-00011. Source Ledger FA-000011; net book value $882.5. capital PO PO-2024-0003 supports the cost basis. hr_employee_status lists Maya Fontaine (E0011) as Active. | L15: 2026-08-05 | M15: =IFERROR(XLOOKUP(A15,'Source Inventory'!$A$5:$A$200,'Source Inventory'!$H$5:$H$200),"") | N15: 882.5 | O15: =IFERROR(XLOOKUP(A15,'Source Ledger'!$B$5:$B$200,'Source Ledger'!$A$5:$A$200),"") | P15: =IFERROR(XLOOKUP(A15,'Source Ledger'!$B$5:$B$200,'Source Ledger'!$D$5:$D$200),"") | Q15: High | S15: =IF(OR(R15="",R15=0),"No","Yes") | T15: =IFERROR(XLOOKUP(A15,'Source Ledger'!$B$5:$B$200,'Source Ledger'!$E$5:$E$200),"") | U15: =IFERROR(XLOOKUP(A15,'Source Ledger'!$B$5:$B$200,'Source Ledger'!$H$5:$H$200),"") | V15: =IFERROR(XLOOKUP(A15,'Source Ledger'!$B$5:$B$200,'Source Ledger'!$G$5:$G$200),"") | W15: =IF(OR(M15="",T15=""),"",T15-M15) | X15: =IF(V15="","No","Yes")
A16: MD-00012 | B16: =IFERROR(XLOOKUP(A16,'Source Inventory'!$A$5:$A$200,'Source Inventory'!$B$5:$B$200),"") | C16: =IFERROR(XLOOKUP(A16,'Source Inventory'!$A$5:$A$200,'Source Inventory'!$C$5:$C$200),"") | D16: =IFERROR(XLOOKUP(A16,'Source Inventory'!$A$5:$A$200,'Source Inventory'!$D$5:$D$200),"") | E16: =IFERROR(XLOOKUP(A16,'Source Inventory'!$A$5:$A$200,'Source Inventory'!$E$5:$E$200),"") | F16: =IFERROR(XLOOKUP(A16,'Source Inventory'!$A$5:$A$200,'Source Inventory'!$F$5:$F$200),"") | G16: =IFERROR(XLOOKUP(A16,'Source Inventory'!$A$5:$A$200,'Source Inventory'!$G$5:$G$200),"") | H16: E0012 | I16: Atlanta | J16: In Use | K16: Working conclusion for MD-00012 (MD-NE-050012): In Use at Atlanta; cost $6425. equipment_transfer_log TR-00012 posted Jan 30, 2026; inbound 2026-01-31 approval APR-00012. Source Ledger FA-000012; net book value $553.23. buy path for MD-00012 references PO-2024-0003. hr_employee_status lists Ryan Okonkwo (E0012) as Active. | L16: 2026-08-05 | M16: =IFERROR(XLOOKUP(A16,'Source Inventory'!$A$5:$A$200,'Source Inventory'!$H$5:$H$200),"") | N16: 553.23 | O16: =IFERROR(XLOOKUP(A16,'Source Ledger'!$B$5:$B$200,'Source Ledger'!$A$5:$A$200),"") | P16: =IFERROR(XLOOKUP(A16,'Source Ledger'!$B$5:$B$200,'Source Ledger'!$D$5:$D$200),"") | Q16: High | S16: =IF(OR(R16="",R16=0),"No","Yes") | T16: =IFERROR(XLOOKUP(A16,'Source Ledger'!$B$5:$B$200,'Source Ledger'!$E$5:$E$200),"") | U16: =IFERROR(XLOOKUP(A16,'Source Ledger'!$B$5:$B$200,'Source Ledger'!$H$5:$H$200),"") | V16: =IFERROR(XLOOKUP(A16,'Source Ledger'!$B$5:$B$200,'Source Ledger'!$G$5:$G$200),"") | W16: =IF(OR(M16="",T16=""),"",T16-M16) | X16: =IF(V16="","No","Yes")
... A20: MD-00016 | B20: =IFERROR(XLOOKUP(A20,'Source Inventory'!$A$5:$A$200,'Source Inventory'!$B$5:$B$200),"") | C20: =IFERROR(XLOOKUP(A20,'Source Inventory'!$A$5:$A$200,'Source Inventory'!$C$5:$C$200),"") | D20: =IFERROR(XLOOKUP(A20,'Source Inventory'!$A$5:$A$200,'Source Inventory'!$D$5:$D$200),"") | E20: =IFERROR(XLOOKUP(A20,'Source Inventory'!$A$5:$A$200,'Source Inventory'!$E$5:$E$200),"") | F20: =IFERROR(XLOOKUP(A20,'Source Inventory'!$A$5:$A$200,'Source Inventory'!$F$5:$F$200),"") | G20: =IFERROR(XLOOKUP(A20,'Source Inventory'!$A$5:$A$200,'Source Inventory'!$G$5:$G$200),"") | H20: E0016 | I20: New York | J20: In Use | K20: Asset MD-00016 — LG UltraFine 27MD5KL — reconciled to In Use in New York on $6290 acquisition. hr_employee_status lists Patrick Gallagher (E0016) as Active. Source Ledger FA-000016; net book value $968.69. PO-2024-0003 is the cited purchase order. equipment_transfer_log TR-00016 posted May 13, 2026; inbound 2026-05-17 approval APR-00016. | L20: 2026-08-05 | M20: =IFERROR(XLOOKUP(A20,'Source Inventory'!$A$5:$A$200,'Source Inventory'!$H$5:$H$200),"") | N20: 968.69 | O20: =IFERROR(XLOOKUP(A20,'Source Ledger'!$B$5:$B$200,'Source Ledger'!$A$5:$A$200),"") | P20: =IFERROR(XLOOKUP(A20,'Source Ledger'!$B$5:$B$200,'Source Ledger'!$D$5:$D$200),"") | Q20: High | S20: =IF(OR(R20="",R20=0),"No","Yes") | T20: =IFERROR(XLOOKUP(A20,'Source Ledger'!$B$5:$B$200,'Source Ledger'!$E$5:$E$200),"") | U20: =IFERROR(XLOOKUP(A20,'Source Ledger'!$B$5:$B$200,'Source Ledger'!$H$5:$H$200),"") | V20: =IFERROR(XLOOKUP(A20,'Source Ledger'!$B$5:$B$200,'Source Ledger'!$G$5:$G$200),"") | W20: =IF(OR(M20="",T20=""),"",T20-M20) | X20: =IF(V20="","No","Yes")
A21: MD-00017 | B21: =IFERROR(XLOOKUP(A21,'Source Inventory'!$A$5:$A$200,'Source Inventory'!$B$5:$B$200),"") | C21: =IFERROR(XLOOKUP(A21,'Source Inventory'!$A$5:$A$200,'Source Inventory'!$C$5:$C$200),"") | D21: =IFERROR(XLOOKUP(A21,'Source Inventory'!$A$5:$A$200,'Source Inventory'!$D$5:$D$200),"") | E21: =IFERROR(XLOOKUP(A21,'Source Inventory'!$A$5:$A$200,'Source Inventory'!$E$5:$E$200),"") | F21: =IFERROR(XLOOKUP(A21,'Source Inventory'!$A$5:$A$200,'Source Inventory'!$F$5:$F$200),"") | G21: =IFERROR(XLOOKUP(A21,'Source Inventory'!$A$5:$A$200,'Source Inventory'!$G$5:$G$200),"") | H21: E0017 | I21: Seattle | J21: In Use | K21: Asset MD-00017 — Samsung ViewFinity S8 — reconciled to In Use in Seattle on $1985 acquisition. hr_employee_status lists Irene Cho (E0017) as Active. Source Ledger FA-000017; net book value $0. order PO-2025-0004 appears in the purchasing extract. equipment_transfer_log TR-00017 posted Jun 17, 2026; inbound 2026-06-19 approval APR-00017. | L21: 2026-08-05 | M21: =IFERROR(XLOOKUP(A21,'Source Inventory'!$A$5:$A$200,'Source Inventory'!$H$5:$H$200),"") | N21: 0 | O21: =IFERROR(XLOOKUP(A21,'Source Ledger'!$B$5:$B$200,'Source Ledger'!$A$5:$A$200),"") | P21: =IFERROR(XLOOKUP(A21,'Source Ledger'!$B$5:$B$200,'Source Ledger'!$D$5:$D$200),"") | Q21: High | R21: EX-0001 | S21: =IF(OR(R21="",R21=0),"No","Yes") | T21: =IFERROR(XLOOKUP(A21,'Source Ledger'!$B$5:$B$200,'Source Ledger'!$E$5:$E$200),"") | U21: =IFERROR(XLOOKUP(A21,'Source Ledger'!$B$5:$B$200,'Source Ledger'!$H$5:$H$200),"") | V21: =IFERROR(XLOOKUP(A21,'Source Ledger'!$B$5:$B$200,'Source Ledger'!$G$5:$G$200),"") | W21: =IF(OR(M21="",T21=""),"",T21-M21) | X21: =IF(V21="","No","Yes")
A22: MD-00018 | B22: =IFERROR(XLOOKUP(A22,'Source Inventory'!$A$5:$A$200,'Source Inventory'!$B$5:$B$200),"") | C22: =IFERROR(XLOOKUP(A22,'Source Inventory'!$A$5:$A$200,'Source Inventory'!$C$5:$C$200),"") | D22: =IFERROR(XLOOKUP(A22,'Source Inventory'!$A$5:$A$200,'Source Inventory'!$D$5:$D$200),"") | E22: =IFERROR(XLOOKUP(A22,'Source Inventory'!$A$5:$A$200,'Source Inventory'!$E$5:$E$200),"") | F22: =IFERROR(XLOOKUP(A22,'Source Inventory'!$A$5:$A$200,'Source Inventory'!$F$5:$F$200),"") | G22: =IFERROR(XLOOKUP(A22,'Source Inventory'!$A$5:$A$200,'Source Inventory'!$G$5:$G$200),"") | H22: E0018 | I22: Atlanta | J22: In Use | K22: Asset MD-00018 — BenQ PD2705U — reconciled to In Use in Atlanta on $700 acquisition. hr_employee_status lists Theo Barnett (E0018) as Active. Source Ledger FA-000018; net book value $412.14. PO-2025-0004 is the cited purchase order. equipment_transfer_log TR-00018 posted Jan 22, 2026; inbound 2026-01-23 approval APR-00018. | L22: 2026-08-05 | M22: =IFERROR(XLOOKUP(A22,'Source Inventory'!$A$5:$A$200,'Source Inventory'!$H$5:$H$200),"") | N22: 412.14 | O22: =IFERROR(XLOOKUP(A22,'Source Ledger'!$B$5:$B$200,'Source Ledger'!$A$5:$A$200),"") | P22: =IFERROR(XLOOKUP(A22,'Source Ledger'!$B$5:$B$200,'Source Ledger'!$D$5:$D$200),"") | Q22: High | S22: =IF(OR(R22="",R22=0),"No","Yes") | T22: =IFERROR(XLOOKUP(A22,'Source Ledger'!$B$5:$B$200,'Source Ledger'!$E$5:$E$200),"") | U22: =IFERROR(XLOOKUP(A22,'Source Ledger'!$B$5:$B$200,'Source Ledger'!$H$5:$H$200),"") | V22: =IFERROR(XLOOKUP(A22,'Source Ledger'!$B$5:$B$200,'Source Ledger'!$G$5:$G$200),"") | W22: =IF(OR(M22="",T22=""),"",T22-M22) | X22: =IF(V22="","No","Yes")
A23: MD-00019 | B23: =IFERROR(XLOOKUP(A23,'Source Inventory'!$A$5:$A$200,'Source Inventory'!$B$5:$B$200),"") | C23: =IFERROR(XLOOKUP(A23,'Source Inventory'!$A$5:$A$200,'Source Inventory'!$C$5:$C$200),"") | D23: =IFERROR(XLOOKUP(A23,'Source Inventory'!$A$5:$A$200,'Source Inventory'!$D$5:$D$200),"") | E23: =IFERROR(XLOOKUP(A23,'Source Inventory'!$A$5:$A$200,'Source Inventory'!$E$5:$E$200),"") | F23: =IFERROR(XLOOKUP(A23,'Source Inventory'!$A$5:$A$200,'Source Inventory'!$F$5:$F$200),"") | G23: =IFERROR(XLOOKUP(A23,'Source Inventory'!$A$5:$A$200,'Source Inventory'!$G$5:$G$200),"") | H23: E0019 | I23: Chicago | J23: In Use | K23: Asset MD-00019 — Dell P2422H — reconciled to In Use in Chicago on $1175 acquisition. hr_employee_status lists Jasmine Reed (E0019) as Active. Source Ledger FA-000019; net book value $795.4. acquisition recorded on PO-2025-0004. equipment_transfer_log TR-00019 posted Feb 23, 2026; inbound 2026-02-26 approval APR-00019. | L23: 2026-08-05 | M23: =IFERROR(XLOOKUP(A23,'Source Inventory'!$A$5:$A$200,'Source Inventory'!$H$5:$H$200),"") | N23: 795.4 | O23: =IFERROR(XLOOKUP(A23,'Source Ledger'!$B$5:$B$200,'Source Ledger'!$A$5:$A$200),"") | P23: =IFERROR(XLOOKUP(A23,'Source Ledger'!$B$5:$B$200,'Source Ledger'!$D$5:$D$200),"") | Q23: High | S23: =IF(OR(R23="",R23=0),"No","Yes") | T23: =IFERROR(XLOOKUP(A23,'Source Ledger'!$B$5:$B$200,'Source Ledger'!$E$5:$E$200),"") | U23: =IFERROR(XLOOKUP(A23,'Source Ledger'!$B$5:$B$200,'Source Ledger'!$H$5:$H$200),"") | V23: =IFERROR(XLOOKUP(A23,'Source Ledger'!$B$5:$B$200,'Source Ledger'!$G$5:$G$200),"") | W23: =IF(OR(M23="",T23=""),"",T23-M23) | X23: =IF(V23="","No","Yes")
A24: MD-00020 | B24: =IFERROR(XLOOKUP(A24,'Source Inventory'!$A$5:$A$200,'Source Inventory'!$B$5:$B$200),"") | C24: =IFERROR(XLOOKUP(A24,'Source Inventory'!$A$5:$A$200,'Source Inventory'!$C$5:$C$200),"") | D24: =IFERROR(XLOOKUP(A24,'Source Inventory'!$A$5:$A$200,'Source Inventory'!$D$5:$D$200),"") | E24: =IFERROR(XLOOKUP(A24,'Source Inventory'!$A$5:$A$200,'Source Inventory'!$E$5:$E$200),"") | F24: =IFERROR(XLOOKUP(A24,'Source Inventory'!$A$5:$A$200,'Source Inventory'!$F$5:$F$200),"") | G24: =IFERROR(XLOOKUP(A24,'Source Inventory'!$A$5:$A$200,'Source Inventory'!$G$5:$G$200),"") | H24: E0020 | I24: Dallas | J24: In Use | K24: Asset MD-00020 — LG UltraFine 27MD5KL — reconciled to In Use in Dallas on $6470 acquisition. hr_employee_status lists Luis Navarro (E0020) as Active. equipment_transfer_log TR-00020 posted Mar 28, 2026; inbound 2026-03-30 approval APR-00020. Source Ledger FA-000020; net book value $1446.34. capital PO PO-2025-0004 supports the cost basis. | L24: 2026-08-05 | M24: =IFERROR(XLOOKUP(A24,'Source Inventory'!$A$5:$A$200,'Source Inventory'!$H$5:$H$200),"") | N24: 1446.34 | O24: =IFERROR(XLOOKUP(A24,'Source Ledger'!$B$5:$B$200,'Source Ledger'!$A$5:$A$200),"") | P24: =IFERROR(XLOOKUP(A24,'Source Ledger'!$B$5:$B$200,'Source Ledger'!$D$5:$D$200),"") | Q24: High | S24: =IF(OR(R24="",R24=0),"No","Yes") | T24: =IFERROR(XLOOKUP(A24,'Source Ledger'!$B$5:$B$200,'Source Ledger'!$E$5:$E$200),"") | U24: =IFERROR(XLOOKUP(A24,'Source Ledger'!$B$5:$B$200,'Source Ledger'!$H$5:$H$200),"") | V24: =IFERROR(XLOOKUP(A24,'Source Ledger'!$B$5:$B$200,'Source Ledger'!$G$5:$G$200),"") | W24: =IF(OR(M24="",T24=""),"",T24-M24) | X24: =IF(V24="","No","Yes")
A25: MD-00021 | B25: =IFERROR(XLOOKUP(A25,'Source Inventory'!$A$5:$A$200,'Source Inventory'!$B$5:$B$200),"") | C25: =IFERROR(XLOOKUP(A25,'Source Inventory'!$A$5:$A$200,'Source Inventory'!$C$5:$C$200),"") | D25: =IFERROR(XLOOKUP(A25,'Source Inventory'!$A$5:$A$200,'Source Inventory'!$D$5:$D$200),"") | E25: =IFERROR(XLOOKUP(A25,'Source Inventory'!$A$5:$A$200,'Source Inventory'!$E$5:$E$200),"") | F25: =IFERROR(XLOOKUP(A25,'Source Inventory'!$A$5:$A$200,'Source Inventory'!$F$5:$F$200),"") | G25: =IFERROR(XLOOKUP(A25,'Source Inventory'!$A$5:$A$200,'Source Inventory'!$G$5:$G$200),"") | H25: E0021 | I25: Denver | J25: In Use | K25: Asset MD-00021 — Samsung ViewFinity S8 — reconciled to In Use in Denver on $1850 acquisition. duplicate serial MD-LA-050021 flagged on the register. equipment_transfer_log TR-00021 posted May 02, 2026; inbound 2026-05-03 approval APR-00021. Source Ledger FA-000021; net book value $124.52. buy path for MD-00021 references PO-2022-0005. hr_employee_status lists Grace Lindholm (E0021) as Active. | L25: 2026-08-05 | M25: =IFERROR(XLOOKUP(A25,'Source Inventory'!$A$5:$A$200,'Source Inventory'!$H$5:$H$200),"") | N25: 124.52 | O25: =IFERROR(XLOOKUP(A25,'Source Ledger'!$B$5:$B$200,'Source Ledger'!$A$5:$A$200),"") | P25: =IFERROR(XLOOKUP(A25,'Source Ledger'!$B$5:$B$200,'Source Ledger'!$D$5:$D$200),"") | Q25: Medium | R25: EX-0002 | S25: =IF(OR(R25="",R25=0),"No","Yes") | T25: =IFERROR(XLOOKUP(A25,'Source Ledger'!$B$5:$B$200,'Source Ledger'!$E$5:$E$200),"") | U25: =IFERROR(XLOOKUP(A25,'Source Ledger'!$B$5:$B$200,'Source Ledger'!$H$5:$H$200),"") | V25: =IFERROR(XLOOKUP(A25,'Source Ledger'!$B$5:$B$200,'Source Ledger'!$G$5:$G$200),"") | W25: =IF(OR(M25="",T25=""),"",T25-M25) | X25: =IF(V25="","No","Yes")
A26: MD-00022 | B26: =IFERROR(XLOOKUP(A26,'Source Inventory'!$A$5:$A$200,'Source Inventory'!$B$5:$B$200),"") | C26: =IFERROR(XLOOKUP(A26,'Source Inventory'!$A$5:$A$200,'Source Inventory'!$C$5:$C$200),"") | D26: =IFERROR(XLOOKUP(A26,'Source Inventory'!$A$5:$A$200,'Source Inventory'!$D$5:$D$200),"") | E26: =IFERROR(XLOOKUP(A26,'Source Inventory'!$A$5:$A$200,'Source Inventory'!$E$5:$E$200),"") | F26: =IFERROR(XLOOKUP(A26,'Source Inventory'!$A$5:$A$200,'Source Inventory'!$F$5:$F$200),"") | G26: =IFERROR(XLOOKUP(A26,'Source Inventory'!$A$5:$A$200,'Source Inventory'!$G$5:$G$200),"") | H26: E0022 | I26: New York | J26: In Use | K26: Working conclusion for MD-00022 (MD-MO-050022): In Use at New York; cost $565. hardware_purchase_orders.csv ties MD-00022 to PO-2022-0005. hr_employee_status lists Andre Baptiste (E0022) as Active. equipment_transfer_log TR-00022 posted Jun 03, 2026; inbound 2026-06-05 approval APR-00022. Source Ledger FA-000022; net book value $371.95. | L26: 2026-08-05 | M26: =IFERROR(XLOOKUP(A26,'Source Inventory'!$A$5:$A$200,'Source Inventory'!$H$5:$H$200),"") | N26: 371.95 | O26: =IFERROR(XLOOKUP(A26,'Source Ledger'!$B$5:$B$200,'Source Ledger'!$A$5:$A$200),"") | P26: =IFERROR(XLOOKUP(A26,'Source Ledger'!$B$5:$B$200,'Source Ledger'!$D$5:$D$200),"") | Q26: High | S26: =IF(OR(R26="",R26=0),"No","Yes") | T26: =IFERROR(XLOOKUP(A26,'Source Ledger'!$B$5:$B$200,'Source Ledger'!$E$5:$E$200),"") | U26: =IFERROR(XLOOKUP(A26,'Source Ledger'!$B$5:$B$200,'Source Ledger'!$H$5:$H$200),"") | V26: =IFERROR(XLOOKUP(A26,'Source Ledger'!$B$5:$B$200,'Source Ledger'!$G$5:$G$200),"") | W26: =IF(OR(M26="",T26=""),"",T26-M26) | X26: =IF(V26="","No","Yes")
A27: MD-00023 | B27: =IFERROR(XLOOKUP(A27,'Source Inventory'!$A$5:$A$200,'Source Inventory'!$B$5:$B$200),"") | C27: =IFERROR(XLOOKUP(A27,'Source Inventory'!$A$5:$A$200,'Source Inventory'!$C$5:$C$200),"") | D27: =IFERROR(XLOOKUP(A27,'Source Inventory'!$A$5:$A$200,'Source Inventory'!$D$5:$D$200),"") | E27: =IFERROR(XLOOKUP(A27,'Source Inventory'!$A$5:$A$200,'Source Inventory'!$E$5:$E$200),"") | F27: =IFERROR(XLOOKUP(A27,'Source Inventory'!$A$5:$A$200,'Source Inventory'!$F$5:$F$200),"") | G27: =IFERROR(XLOOKUP(A27,'Source Inventory'!$A$5:$A$200,'Source Inventory'!$G$5:$G$200),"") | H27: E0023 | I27: Seattle | J27: In Use | K27: Working conclusion for MD-00023 (MD-MO-050023): In Use at Seattle; cost $1040. PO PO-2022-0005 documents the buy for MD-00023. hr_employee_status lists Nina Kowalski (E0023) as Active. equipment_transfer_log TR-00023 posted Jul 08, 2026; inbound 2026-07-09 approval APR-00023. Source Ledger FA-000023; net book value $823.6. | L27: 2026-08-05 | M27: =IFERROR(XLOOKUP(A27,'Source Inventory'!$A$5:$A$200,'Source Inventory'!$H$5:$H$200),"") | N27: 823.6 | O27: =IFERROR(XLOOKUP(A27,'Source Ledger'!$B$5:$B$200,'Source Ledger'!$A$5:$A$200),"") | P27: =IFERROR(XLOOKUP(A27,'Source Ledger'!$B$5:$B$200,'Source Ledger'!$D$5:$D$200),"") | Q27: High | S27: =IF(OR(R27="",R27=0),"No","Yes") | T27: =IFERROR(XLOOKUP(A27,'Source Ledger'!$B$5:$B$200,'Source Ledger'!$E$5:$E$200),"") | U27: =IFERROR(XLOOKUP(A27,'Source Ledger'!$B$5:$B$200,'Source Ledger'!$H$5:$H$200),"") | V27: =IFERROR(XLOOKUP(A27,'Source Ledger'!$B$5:$B$200,'Source Ledger'!$G$5:$G$200),"") | W27: =IF(OR(M27="",T27=""),"",T27-M27) | X27: =IF(V27="","No","Yes")
A28: MD-00024 | B28: =IFERROR(XLOOKUP(A28,'Source Inventory'!$A$5:$A$200,'Source Inventory'!$B$5:$B$200),"") | C28: =IFERROR(XLOOKUP(A28,'Source Inventory'!$A$5:$A$200,'Source Inventory'!$C$5:$C$200),"") | D28: =IFERROR(XLOOKUP(A28,'Source Inventory'!$A$5:$A$200,'Source Inventory'!$D$5:$D$200),"") | E28: =IFERROR(XLOOKUP(A28,'Source Inventory'!$A$5:$A$200,'Source Inventory'!$E$5:$E$200),"") | F28: =IFERROR(XLOOKUP(A28,'Source Inventory'!$A$5:$A$200,'Source Inventory'!$F$5:$F$200),"") | G28: =IFERROR(XLOOKUP(A28,'Source Inventory'!$A$5:$A$200,'Source Inventory'!$G$5:$G$200),"") | H28: E0024 | I28: Atlanta | J28: In Use | K28: Working conclusion for MD-00024 (MD-NE-050024): In Use at Atlanta; cost $6335. capital PO PO-2022-0005 supports the cost basis. hr_employee_status lists Chris Daley (E0024) as Active. equipment_transfer_log TR-00024 posted Jan 18, 2026; inbound 2026-01-21 approval APR-00024. Source Ledger FA-000024; net book value $503.85. | L28: 2026-08-05 | M28: =IFERROR(XLOOKUP(A28,'Source Inventory'!$A$5:$A$200,'Source Inventory'!$H$5:$H$200),"") | N28: 503.85 | O28: =IFERROR(XLOOKUP(A28,'Source Ledger'!$B$5:$B$200,'Source Ledger'!$A$5:$A$200),"") | P28: =IFERROR(XLOOKUP(A28,'Source Ledger'!$B$5:$B$200,'Source Ledger'!$D$5:$D$200),"") | Q28: High | S28: =IF(OR(R28="",R28=0),"No","Yes") | T28: =IFERROR(XLOOKUP(A28,'Source Ledger'!$B$5:$B$200,'Source Ledger'!$E$5:$E$200),"") | U28: =IFERROR(XLOOKUP(A28,'Source Ledger'!$B$5:$B$200,'Source Ledger'!$H$5:$H$200),"") | V28: =IFERROR(XLOOKUP(A28,'Source Ledger'!$B$5:$B$200,'Source Ledger'!$G$5:$G$200),"") | W28: =IF(OR(M28="",T28=""),"",T28-M28) | X28: =IF(V28="","No","Yes")
A29: MD-00025 | B29: =IFERROR(XLOOKUP(A29,'Source Inventory'!$A$5:$A$200,'Source Inventory'!$B$5:$B$200),"") | C29: =IFERROR(XLOOKUP(A29,'Source Inventory'!$A$5:$A$200,'Source Inventory'!$C$5:$C$200),"") | D29: =IFERROR(XLOOKUP(A29,'Source Inventory'!$A$5:$A$200,'Source Inventory'!$D$5:$D$200),"") | E29: =IFERROR(XLOOKUP(A29,'Source Inventory'!$A$5:$A$200,'Source Inventory'!$E$5:$E$200),"") | F29: =IFERROR(XLOOKUP(A29,'Source Inventory'!$A$5:$A$200,'Source Inventory'!$F$5:$F$200),"") | G29: =IFERROR(XLOOKUP(A29,'Source Inventory'!$A$5:$A$200,'Source Inventory'!$G$5:$G$200),"") | H29: E0025 | I29: Chicago | J29: In Use | K29: Working conclusion for MD-00025 (MD-LA-050021): In Use at Chicago; cost $2030. buy path for MD-00025 references PO-2022-0005. hr_employee_status lists Fatima Hussein (E0025) as Active. duplicate serial MD-LA-050021 flagged on the register. Source Ledger FA-000025; net book value $0. equipment_transfer_log TR-00025 posted Jan 21, 2026; inbound 2026-01-22 approval APR-00025. | L29: 2026-08-05 | M29: =IFERROR(XLOOKUP(A29,'Source Inventory'!$A$5:$A$200,'Source Inventory'!$H$5:$H$200),"") | N29: 0 | O29: =IFERROR(XLOOKUP(A29,'Source Ledger'!$B$5:$B$200,'Source Ledger'!$A$5:$A$200),"") | P29: =IFERROR(XLOOKUP(A29,'Source Ledger'!$B$5:$B$200,'Source Ledger'!$D$5:$D$200),"") | Q29: Medium | R29: EX-0003, EX-0004 | S29: =IF(OR(R29="",R29=0),"No","Yes") | T29: =IFERROR(XLOOKUP(A29,'Source Ledger'!$B$5:$B$200,'Source Ledger'!$E$5:$E$200),"") | U29: =IFERROR(XLOOKUP(A29,'Source Ledger'!$B$5:$B$200,'Source Ledger'!$H$5:$H$200),"") | V29: =IFERROR(XLOOKUP(A29,'Source Ledger'!$B$5:$B$200,'Source Ledger'!$G$5:$G$200),"") | W29: =IF(OR(M29="",T29=""),"",T29-M29) | X29: =IF(V29="","No","Yes")
A30: MD-00026 | B30: =IFERROR(XLOOKUP(A30,'Source Inventory'!$A$5:$A$200,'Source Inventory'!$B$5:$B$200),"") | C30: =IFERROR(XLOOKUP(A30,'Source Inventory'!$A$5:$A$200,'Source Inventory'!$C$5:$C$200),"") | D30: =IFERROR(XLOOKUP(A30,'Source Inventory'!$A$5:$A$200,'Source Inventory'!$D$5:$D$200),"") | E30: =IFERROR(XLOOKUP(A30,'Source Inventory'!$A$5:$A$200,'Source Inventory'!$E$5:$E$200),"") | F30: =IFERROR(XLOOKUP(A30,'Source Inventory'!$A$5:$A$200,'Source Inventory'!$F$5:$F$200),"") | G30: =IFERROR(XLOOKUP(A30,'Source Inventory'!$A$5:$A$200,'Source Inventory'!$G$5:$G$200),"") | H30: E0026 | I30: Dallas | J30: In Use | K30: Working conclusion for MD-00026 (MD-MO-050026): In Use at Dallas; cost $745. acquisition recorded on PO-2022-0005. hr_employee_status lists Brendan Walsh (E0026) as Active. equipment_transfer_log TR-00026 posted Feb 23, 2026; inbound 2026-02-27 approval APR-00026. Source Ledger FA-000026; net book value $382.34. | L30: 2026-08-05 | M30: =IFERROR(XLOOKUP(A30,'Source Inventory'!$A$5:$A$200,'Source Inventory'!$H$5:$H$200),"") | N30: 382.34 | O30: =IFERROR(XLOOKUP(A30,'Source Ledger'!$B$5:$B$200,'Source Ledger'!$A$5:$A$200),"") | P30: =IFERROR(XLOOKUP(A30,'Source Ledger'!$B$5:$B$200,'Source Ledger'!$D$5:$D$200),"") | Q30: High | R30: EX-0005 | S30: =IF(OR(R30="",R30=0),"No","Yes") | T30: =IFERROR(XLOOKUP(A30,'Source Ledger'!$B$5:$B$200,'Source Ledger'!$E$5:$E$200),"") | U30: =IFERROR(XLOOKUP(A30,'Source Ledger'!$B$5:$B$200,'Source Ledger'!$H$5:$H$200),"") | V30: =IFERROR(XLOOKUP(A30,'Source Ledger'!$B$5:$B$200,'Source Ledger'!$G$5:$G$200),"") | W30: =IF(OR(M30="",T30=""),"",T30-M30) | X30: =IF(V30="","No","Yes")
A31: MD-00027 | B31: =IFERROR(XLOOKUP(A31,'Source Inventory'!$A$5:$A$200,'Source Inventory'!$B$5:$B$200),"") | C31: =IFERROR(XLOOKUP(A31,'Source Inventory'!$A$5:$A$200,'Source Inventory'!$C$5:$C$200),"") | D31: =IFERROR(XLOOKUP(A31,'Source Inventory'!$A$5:$A$200,'Source Inventory'!$D$5:$D$200),"") | E31: =IFERROR(XLOOKUP(A31,'Source Inventory'!$A$5:$A$200,'Source Inventory'!$E$5:$E$200),"") | F31: =IFERROR(XLOOKUP(A31,'Source Inventory'!$A$5:$A$200,'Source Inventory'!$F$5:$F$200),"") | G31: =IFERROR(XLOOKUP(A31,'Source Inventory'!$A$5:$A$200,'Source Inventory'!$G$5:$G$200),"") | H31: E0027 | I31: Denver | J31: In Use | K31: Asset MD-00027 — BenQ PD2705U — reconciled to In Use in Denver on $1220 acquisition. hr_employee_status lists Yuki Tanaka (E0027) as Active. equipment_transfer_log TR-00027 posted Mar 31, 2026; inbound 2026-04-06 approval APR-00027. Source Ledger FA-000027; net book value $672.21. purchasing file shows PO-2022-0005 for this unit. | L31: 2026-08-05 | M31: =IFERROR(XLOOKUP(A31,'Source Inventory'!$A$5:$A$200,'Source Inventory'!$H$5:$H$200),"") | N31: 672.21 | O31: =IFERROR(XLOOKUP(A31,'Source Ledger'!$B$5:$B$200,'Source Ledger'!$A$5:$A$200),"") | P31: =IFERROR(XLOOKUP(A31,'Source Ledger'!$B$5:$B$200,'Source Ledger'!$D$5:$D$200),"") | Q31: High | R31: EX-0006 | S31: =IF(OR(R31="",R31=0),"No","Yes") | T31: =IFERROR(XLOOKUP(A31,'Source Ledger'!$B$5:$B$200,'Source Ledger'!$E$5:$E$200),"") | U31: =IFERROR(XLOOKUP(A31,'Source Ledger'!$B$5:$B$200,'Source Ledger'!$H$5:$H$200),"") | V31: =IFERROR(XLOOKUP(A31,'Source Ledger'!$B$5:$B$200,'Source Ledger'!$G$5:$G$200),"") | W31: =IF(OR(M31="",T31=""),"",T31-M31) | X31: =IF(V31="","No","Yes")
A32: MD-00028 | B32: =IFERROR(XLOOKUP(A32,'Source Inventory'!$A$5:$A$200,'Source Inventory'!$B$5:$B$200),"") | C32: =IFERROR(XLOOKUP(A32,'Source Inventory'!$A$5:$A$200,'Source Inventory'!$C$5:$C$200),"") | D32: =IFERROR(XLOOKUP(A32,'Source Inventory'!$A$5:$A$200,'Source Inventory'!$D$5:$D$200),"") | E32: =IFERROR(XLOOKUP(A32,'Source Inventory'!$A$5:$A$200,'Source Inventory'!$E$5:$E$200),"") | F32: =IFERROR(XLOOKUP(A32,'Source Inventory'!$A$5:$A$200,'Source Inventory'!$F$5:$F$200),"") | G32: =IFERROR(XLOOKUP(A32,'Source Inventory'!$A$5:$A$200,'Source Inventory'!$G$5:$G$200),"") | H32: E0028 | I32: New York | J32: In Use | K32: Asset MD-00028 — Dell P2422H — reconciled to In Use in New York on $6200 acquisition. hr_employee_status lists Megan Copeland (E0028) as Active. equipment_transfer_log TR-00028 posted May 01, 2026; inbound 2026-05-02 approval APR-00028. Source Ledger FA-000028; net book value $914.09. acquisition recorded on PO-2023-0006. | L32: 2026-08-05 | M32: =IFERROR(XLOOKUP(A32,'Source Inventory'!$A$5:$A$200,'Source Inventory'!$H$5:$H$200),"") | N32: 914.09 | O32: =IFERROR(XLOOKUP(A32,'Source Ledger'!$B$5:$B$200,'Source Ledger'!$A$5:$A$200),"") | P32: =IFERROR(XLOOKUP(A32,'Source Ledger'!$B$5:$B$200,'Source Ledger'!$D$5:$D$200),"") | Q32: High | R32: EX-0007 | S32: =IF(OR(R32="",R32=0),"No","Yes") | T32: =IFERROR(XLOOKUP(A32,'Source Ledger'!$B$5:$B$200,'Source Ledger'!$E$5:$E$200),"") | U32: =IFERROR(XLOOKUP(A32,'Source Ledger'!$B$5:$B$200,'Source Ledger'!$H$5:$H$200),"") | V32: =IFERROR(XLOOKUP(A32,'Source Ledger'!$B$5:$B$200,'Source Ledger'!$G$5:$G$200),"") | W32: =IF(OR(M32="",T32=""),"",T32-M32) | X32: =IF(V32="","No","Yes")
A33: MD-00029 | B33: =IFERROR(XLOOKUP(A33,'Source Inventory'!$A$5:$A$200,'Source Inventory'!$B$5:$B$200),"") | C33: =IFERROR(XLOOKUP(A33,'Source Inventory'!$A$5:$A$200,'Source Inventory'!$C$5:$C$200),"") | D33: =IFERROR(XLOOKUP(A33,'Source Inventory'!$A$5:$A$200,'Source Inventory'!$D$5:$D$200),"") | E33: =IFERROR(XLOOKUP(A33,'Source Inventory'!$A$5:$A$200,'Source Inventory'!$E$5:$E$200),"") | F33: =IFERROR(XLOOKUP(A33,'Source Inventory'!$A$5:$A$200,'Source Inventory'!$F$5:$F$200),"") | G33: =IFERROR(XLOOKUP(A33,'Source Inventory'!$A$5:$A$200,'Source Inventory'!$G$5:$G$200),"") | H33: E0029 | I33: Seattle | J33: In Use | K33: Asset MD-00029 — Dell U2723QE — reconciled to In Use in Seattle on $1895 acquisition. hr_employee_status lists Omar Haddad (E0029) as Active. equipment_transfer_log TR-00029 posted Jun 05, 2026; inbound 2026-06-11 approval APR-00029. Source Ledger FA-000029; net book value $0. purchasing file shows PO-2023-0006 for this unit. | L33: 2026-08-05 | M33: =IFERROR(XLOOKUP(A33,'Source Inventory'!$A$5:$A$200,'Source Inventory'!$H$5:$H$200),"") | N33: 0 | O33: =IFERROR(XLOOKUP(A33,'Source Ledger'!$B$5:$B$200,'Source Ledger'!$A$5:$A$200),"") | P33: =IFERROR(XLOOKUP(A33,'Source Ledger'!$B$5:$B$200,'Source Ledger'!$D$5:$D$200),"") | Q33: High | R33: EX-0008 | S33: =IF(OR(R33="",R33=0),"No","Yes") | T33: =IFERROR(XLOOKUP(A33,'Source Ledger'!$B$5:$B$200,'Source Ledger'!$E$5:$E$200),"") | U33: =IFERROR(XLOOKUP(A33,'Source Ledger'!$B$5:$B$200,'Source Ledger'!$H$5:$H$200),"") | V33: =IFERROR(XLOOKUP(A33,'Source Ledger'!$B$5:$B$200,'Source Ledger'!$G$5:$G$200),"") | W33: =IF(OR(M33="",T33=""),"",T33-M33) | X33: =IF(V33="","No","Yes")
A34: MD-00030 | B34: =IFERROR(XLOOKUP(A34,'Source Inventory'!$A$5:$A$200,'Source Inventory'!$B$5:$B$200),"") | C34: =IFERROR(XLOOKUP(A34,'Source Inventory'!$A$5:$A$200,'Source Inventory'!$C$5:$C$200),"") | D34: =IFERROR(XLOOKUP(A34,'Source Inventory'!$A$5:$A$200,'Source Inventory'!$D$5:$D$200),"") | E34: =IFERROR(XLOOKUP(A34,'Source Inventory'!$A$5:$A$200,'Source Inventory'!$E$5:$E$200),"") | F34: =IFERROR(XLOOKUP(A34,'Source Inventory'!$A$5:$A$200,'Source Inventory'!$F$5:$F$200),"") | G34: =IFERROR(XLOOKUP(A34,'Source Inventory'!$A$5:$A$200,'Source Inventory'!$G$5:$G$200),"") | H34: E0030 | I34: Atlanta | J34: In Use | K34: Files reviewed for MD-00030: Samsung ViewFinity S8, basis $610, operating site Atlanta, status In Use. equipment_transfer_log TR-00030 posted Jan 10, 2026; inbound 2026-01-13 approval APR-00030. buy path for MD-00030 references PO-2023-0006. Source Ledger FA-000030; net book value $355.14. hr_employee_status lists Stephanie Ruiz (E0030) as Active. | L34: 2026-08-05 | M34: =IFERROR(XLOOKUP(A34,'Source Inventory'!$A$5:$A$200,'Source Inventory'!$H$5:$H$200),"") | N34: 355.14 | O34: =IFERROR(XLOOKUP(A34,'Source Ledger'!$B$5:$B$200,'Source Ledger'!$A$5:$A$200),"") | P34: =IFERROR(XLOOKUP(A34,'Source Ledger'!$B$5:$B$200,'Source Ledger'!$D$5:$D$200),"") | Q34: High | R34: EX-0009 | S34: =IF(OR(R34="",R34=0),"No","Yes") | T34: =IFERROR(XLOOKUP(A34,'Source Ledger'!$B$5:$B$200,'Source Ledger'!$E$5:$E$200),"") | U34: =IFERROR(XLOOKUP(A34,'Source Ledger'!$B$5:$B$200,'Source Ledger'!$H$5:$H$200),"") | V34: =IFERROR(XLOOKUP(A34,'Source Ledger'!$B$5:$B$200,'Source Ledger'!$G$5:$G$200),"") | W34: =IF(OR(M34="",T34=""),"",T34-M34) | X34: =IF(V34="","No","Yes")
A35: MD-00031 | B35: =IFERROR(XLOOKUP(A35,'Source Inventory'!$A$5:$A$200,'Source Inventory'!$B$5:$B$200),"") | C35: =IFERROR(XLOOKUP(A35,'Source Inventory'!$A$5:$A$200,'Source Inventory'!$C$5:$C$200),"") | D35: =IFERROR(XLOOKUP(A35,'Source Inventory'!$A$5:$A$200,'Source Inventory'!$D$5:$D$200),"") | E35: =IFERROR(XLOOKUP(A35,'Source Inventory'!$A$5:$A$200,'Source Inventory'!$E$5:$E$200),"") | F35: =IFERROR(XLOOKUP(A35,'Source Inventory'!$A$5:$A$200,'Source Inventory'!$F$5:$F$200),"") | G35: =IFERROR(XLOOKUP(A35,'Source Inventory'!$A$5:$A$200,'Source Inventory'!$G$5:$G$200),"") | H35: E0031 | I35: Chicago | J35: In Use | K35: Files reviewed for MD-00031: BenQ PD2705U, basis $1085, operating site Chicago, status In Use. equipment_transfer_log TR-00031 posted Feb 11, 2026; inbound 2026-02-11 approval APR-00031. hardware_purchase_orders.csv ties MD-00031 to PO-2023-0006. Source Ledger FA-000031; net book value $722.59. hr_employee_status lists Keith Moreau (E0031) as Active. | L35: 2026-08-05 | M35: =IFERROR(XLOOKUP(A35,'Source Inventory'!$A$5:$A$200,'Source Inventory'!$H$5:$H$200),"") | N35: 722.59 | O35: =IFERROR(XLOOKUP(A35,'Source Ledger'!$B$5:$B$200,'Source Ledger'!$A$5:$A$200),"") | P35: =IFERROR(XLOOKUP(A35,'Source Ledger'!$B$5:$B$200,'Source Ledger'!$D$5:$D$200),"") | Q35: High | R35: EX-0010 | S35: =IF(OR(R35="",R35=0),"No","Yes") | T35: =IFERROR(XLOOKUP(A35,'Source Ledger'!$B$5:$B$200,'Source Ledger'!$E$5:$E$200),"") | U35: =IFERROR(XLOOKUP(A35,'Source Ledger'!$B$5:$B$200,'Source Ledger'!$H$5:$H$200),"") | V35: =IFERROR(XLOOKUP(A35,'Source Ledger'!$B$5:$B$200,'Source Ledger'!$G$5:$G$200),"") | W35: =IF(OR(M35="",T35=""),"",T35-M35) | X35: =IF(V35="","No","Yes")
A36: MD-00032 | B36: =IFERROR(XLOOKUP(A36,'Source Inventory'!$A$5:$A$200,'Source Inventory'!$B$5:$B$200),"") | C36: =IFERROR(XLOOKUP(A36,'Source Inventory'!$A$5:$A$200,'Source Inventory'!$C$5:$C$200),"") | D36: =IFERROR(XLOOKUP(A36,'Source Inventory'!$A$5:$A$200,'Source Inventory'!$D$5:$D$200),"") | E36: =IFERROR(XLOOKUP(A36,'Source Inventory'!$A$5:$A$200,'Source Inventory'!$E$5:$E$200),"") | F36: =IFERROR(XLOOKUP(A36,'Source Inventory'!$A$5:$A$200,'Source Inventory'!$F$5:$F$200),"") | G36: =IFERROR(XLOOKUP(A36,'Source Inventory'!$A$5:$A$200,'Source Inventory'!$G$5:$G$200),"") | H36: E0032 | I36: Dallas | J36: In Use | K36: Asset MD-00032 — Dell P2422H — reconciled to In Use in Dallas on $6380 acquisition. Source Ledger FA-000032; net book value $1384.3. PO PO-2023-0006 documents the buy for MD-00032. hr_employee_status lists Diana Voss (E0032) as Active. equipment_transfer_log TR-00032 posted Mar 16, 2026; inbound 2026-03-22 approval APR-00032. | L36: 2026-08-05 | M36: =IFERROR(XLOOKUP(A36,'Source Inventory'!$A$5:$A$200,'Source Inventory'!$H$5:$H$200),"") | N36: 1384.3 | O36: =IFERROR(XLOOKUP(A36,'Source Ledger'!$B$5:$B$200,'Source Ledger'!$A$5:$A$200),"") | P36: =IFERROR(XLOOKUP(A36,'Source Ledger'!$B$5:$B$200,'Source Ledger'!$D$5:$D$200),"") | Q36: High | R36: EX-0011 | S36: =IF(OR(R36="",R36=0),"No","Yes") | T36: =IFERROR(XLOOKUP(A36,'Source Ledger'!$B$5:$B$200,'Source Ledger'!$E$5:$E$200),"") | U36: =IFERROR(XLOOKUP(A36,'Source Ledger'!$B$5:$B$200,'Source Ledger'!$H$5:$H$200),"") | V36: =IFERROR(XLOOKUP(A36,'Source Ledger'!$B$5:$B$200,'Source Ledger'!$G$5:$G$200),"") | W36: =IF(OR(M36="",T36=""),"",T36-M36) | X36: =IF(V36="","No","Yes")
A37: MD-00033 | B37: =IFERROR(XLOOKUP(A37,'Source Inventory'!$A$5:$A$200,'Source Inventory'!$B$5:$B$200),"") | C37: =IFERROR(XLOOKUP(A37,'Source Inventory'!$A$5:$A$200,'Source Inventory'!$C$5:$C$200),"") | D37: =IFERROR(XLOOKUP(A37,'Source Inventory'!$A$5:$A$200,'Source Inventory'!$D$5:$D$200),"") | E37: =IFERROR(XLOOKUP(A37,'Source Inventory'!$A$5:$A$200,'Source Inventory'!$E$5:$E$200),"") | F37: =IFERROR(XLOOKUP(A37,'Source Inventory'!$A$5:$A$200,'Source Inventory'!$F$5:$F$200),"") | G37: =IFERROR(XLOOKUP(A37,'Source Inventory'!$A$5:$A$200,'Source Inventory'!$G$5:$G$200),"") | H37: E0033 | I37: Denver | J37: In Use | K37: Asset MD-00033 — Dell U2723QE — reconciled to In Use in Denver on $2075 acquisition. Source Ledger FA-000033; net book value $116.93. capital PO PO-2023-0006 supports the cost basis. hr_employee_status lists Jordan Blake (E0033) as Active. equipment_transfer_log TR-00033 posted Apr 20, 2026; inbound 2026-04-22 approval APR-00033. | L37: 2026-08-05 | M37: =IFERROR(XLOOKUP(A37,'Source Inventory'!$A$5:$A$200,'Source Inventory'!$H$5:$H$200),"") | N37: 116.93 | O37: =IFERROR(XLOOKUP(A37,'Source Ledger'!$B$5:$B$200,'Source Ledger'!$A$5:$A$200),"") | P37: =IFERROR(XLOOKUP(A37,'Source Ledger'!$B$5:$B$200,'Source Ledger'!$D$5:$D$200),"") | Q37: High | R37: EX-0012 | S37: =IF(OR(R37="",R37=0),"No","Yes") | T37: =IFERROR(XLOOKUP(A37,'Source Ledger'!$B$5:$B$200,'Source Ledger'!$E$5:$E$200),"") | U37: =IFERROR(XLOOKUP(A37,'Source Ledger'!$B$5:$B$200,'Source Ledger'!$H$5:$H$200),"") | V37: =IFERROR(XLOOKUP(A37,'Source Ledger'!$B$5:$B$200,'Source Ledger'!$G$5:$G$200),"") | W37: =IF(OR(M37="",T37=""),"",T37-M37) | X37: =IF(V37="","No","Yes")
A38: MD-00034 | B38: =IFERROR(XLOOKUP(A38,'Source Inventory'!$A$5:$A$200,'Source Inventory'!$B$5:$B$200),"") | C38: =IFERROR(XLOOKUP(A38,'Source Inventory'!$A$5:$A$200,'Source Inventory'!$C$5:$C$200),"") | D38: =IFERROR(XLOOKUP(A38,'Source Inventory'!$A$5:$A$200,'Source Inventory'!$D$5:$D$200),"") | E38: =IFERROR(XLOOKUP(A38,'Source Inventory'!$A$5:$A$200,'Source Inventory'!$E$5:$E$200),"") | F38: =IFERROR(XLOOKUP(A38,'Source Inventory'!$A$5:$A$200,'Source Inventory'!$F$5:$F$200),"") | G38: =IFERROR(XLOOKUP(A38,'Source Inventory'!$A$5:$A$200,'Source Inventory'!$G$5:$G$200),"") | H38: E0034 | I38: New York | J38: In Use | K38: Working conclusion for MD-00034 (MD-MO-050034): In Use at New York; cost $790. equipment_transfer_log TR-00034 posted May 22, 2026; inbound 2026-05-22 approval APR-00034. PO PO-2024-0007 documents the buy for MD-00034. Source Ledger FA-000034; net book value $479.88. hr_employee_status lists Amelia Grant (E0034) as Active. | L38: 2026-08-05 | M38: =IFERROR(XLOOKUP(A38,'Source Inventory'!$A$5:$A$200,'Source Inventory'!$H$5:$H$200),"") | N38: 479.88 | O38: =IFERROR(XLOOKUP(A38,'Source Ledger'!$B$5:$B$200,'Source Ledger'!$A$5:$A$200),"") | P38: =IFERROR(XLOOKUP(A38,'Source Ledger'!$B$5:$B$200,'Source Ledger'!$D$5:$D$200),"") | Q38: High | R38: EX-0013, EX-0014 | S38: =IF(OR(R38="",R38=0),"No","Yes") | T38: =IFERROR(XLOOKUP(A38,'Source Ledger'!$B$5:$B$200,'Source Ledger'!$E$5:$E$200),"") | U38: =IFERROR(XLOOKUP(A38,'Source Ledger'!$B$5:$B$200,'Source Ledger'!$H$5:$H$200),"") | V38: =IFERROR(XLOOKUP(A38,'Source Ledger'!$B$5:$B$200,'Source Ledger'!$G$5:$G$200),"") | W38: =IF(OR(M38="",T38=""),"",T38-M38) | X38: =IF(V38="","No","Yes")
A39: MD-00035 | B39: =IFERROR(XLOOKUP(A39,'Source Inventory'!$A$5:$A$200,'Source Inventory'!$B$5:$B$200),"") | C39: =IFERROR(XLOOKUP(A39,'Source Inventory'!$A$5:$A$200,'Source Inventory'!$C$5:$C$200),"") | D39: =IFERROR(XLOOKUP(A39,'Source Inventory'!$A$5:$A$200,'Source Inventory'!$D$5:$D$200),"") | E39: =IFERROR(XLOOKUP(A39,'Source Inventory'!$A$5:$A$200,'Source Inventory'!$E$5:$E$200),"") | F39: =IFERROR(XLOOKUP(A39,'Source Inventory'!$A$5:$A$200,'Source Inventory'!$F$5:$F$200),"") | G39: =IFERROR(XLOOKUP(A39,'Source Inventory'!$A$5:$A$200,'Source Inventory'!$G$5:$G$200),"") | H39: E0035 | I39: Seattle | J39: In Use | K39: Asset MD-00035 — Samsung ViewFinity S8 — reconciled to In Use in Seattle on $950 acquisition. hr_employee_status lists Rafael Mendes (E0035) as Active. Source Ledger FA-000035; net book value $741.92. equipment_transfer_log TR-00035 posted Jun 26, 2026; inbound 2026-06-30 approval APR-00035. capital PO PO-2024-0007 supports the cost basis. | L39: 2026-08-05 | M39: =IFERROR(XLOOKUP(A39,'Source Inventory'!$A$5:$A$200,'Source Inventory'!$H$5:$H$200),"") | N39: 741.92 | O39: =IFERROR(XLOOKUP(A39,'Source Ledger'!$B$5:$B$200,'Source Ledger'!$A$5:$A$200),"") | P39: =IFERROR(XLOOKUP(A39,'Source Ledger'!$B$5:$B$200,'Source Ledger'!$D$5:$D$200),"") | Q39: High | R39: EX-0015 | S39: =IF(OR(R39="",R39=0),"No","Yes") | T39: =IFERROR(XLOOKUP(A39,'Source Ledger'!$B$5:$B$200,'Source Ledger'!$E$5:$E$200),"") | U39: =IFERROR(XLOOKUP(A39,'Source Ledger'!$B$5:$B$200,'Source Ledger'!$H$5:$H$200),"") | V39: =IFERROR(XLOOKUP(A39,'Source Ledger'!$B$5:$B$200,'Source Ledger'!$G$5:$G$200),"") | W39: =IF(OR(M39="",T39=""),"",T39-M39) | X39: =IF(V39="","No","Yes")
A40: MD-00036 | B40: =IFERROR(XLOOKUP(A40,'Source Inventory'!$A$5:$A$200,'Source Inventory'!$B$5:$B$200),"") | C40: =IFERROR(XLOOKUP(A40,'Source Inventory'!$A$5:$A$200,'Source Inventory'!$C$5:$C$200),"") | D40: =IFERROR(XLOOKUP(A40,'Source Inventory'!$A$5:$A$200,'Source Inventory'!$D$5:$D$200),"") | E40: =IFERROR(XLOOKUP(A40,'Source Inventory'!$A$5:$A$200,'Source Inventory'!$E$5:$E$200),"") | F40: =IFERROR(XLOOKUP(A40,'Source Inventory'!$A$5:$A$200,'Source Inventory'!$F$5:$F$200),"") | G40: =IFERROR(XLOOKUP(A40,'Source Inventory'!$A$5:$A$200,'Source Inventory'!$G$5:$G$200),"") | H40: E0036 | I40: Atlanta | J40: In Use | K40: Asset MD-00036 — Samsung Galaxy S23 FE — reconciled to In Use in Atlanta on $6245 acquisition. hr_employee_status lists Kate Sorenson (E0036) as Active. Source Ledger FA-000036; net book value $537.73. equipment_transfer_log TR-00036 posted Jan 30, 2026; inbound 2026-02-01 approval APR-00036. purchasing file shows PO-2025-0008 for this unit. | L40: 2026-08-05 | M40: =IFERROR(XLOOKUP(A40,'Source Inventory'!$A$5:$A$200,'Source Inventory'!$H$5:$H$200),"") | N40: 537.73 | O40: =IFERROR(XLOOKUP(A40,'Source Ledger'!$B$5:$B$200,'Source Ledger'!$A$5:$A$200),"") | P40: =IFERROR(XLOOKUP(A40,'Source Ledger'!$B$5:$B$200,'Source Ledger'!$D$5:$D$200),"") | Q40: High | R40: EX-0016 | S40: =IF(OR(R40="",R40=0),"No","Yes") | T40: =IFERROR(XLOOKUP(A40,'Source Ledger'!$B$5:$B$200,'Source Ledger'!$E$5:$E$200),"") | U40: =IFERROR(XLOOKUP(A40,'Source Ledger'!$B$5:$B$200,'Source Ledger'!$H$5:$H$200),"") | V40: =IFERROR(XLOOKUP(A40,'Source Ledger'!$B$5:$B$200,'Source Ledger'!$G$5:$G$200),"") | W40: =IF(OR(M40="",T40=""),"",T40-M40) | X40: =IF(V40="","No","Yes")
... A114: MD-00110 | B114: =IFERROR(XLOOKUP(A114,'Source Inventory'!$A$5:$A$200,'Source Inventory'!$B$5:$B$200),"") | C114: =IFERROR(XLOOKUP(A114,'Source Inventory'!$A$5:$A$200,'Source Inventory'!$C$5:$C$200),"") | D114: =IFERROR(XLOOKUP(A114,'Source Inventory'!$A$5:$A$200,'Source Inventory'!$D$5:$D$200),"") | E114: =IFERROR(XLOOKUP(A114,'Source Inventory'!$A$5:$A$200,'Source Inventory'!$E$5:$E$200),"") | F114: =IFERROR(XLOOKUP(A114,'Source Inventory'!$A$5:$A$200,'Source Inventory'!$F$5:$F$200),"") | G114: =IFERROR(XLOOKUP(A114,'Source Inventory'!$A$5:$A$200,'Source Inventory'!$G$5:$G$200),"") | H114: Regional IT | I114: Dallas | J114: Retired/Pending Disposal | K114: Asset MD-00110 — Dell Latitude 7440 — reconciled to Retired/Pending Disposal in Dallas on $745 acquisition. equipment_transfer_log TR-00110 posted Mar 07, 2026; inbound 2026-03-08 approval APR-00110. Source Ledger FA-000110; net book value $387.24. buy path for MD-00110 references PO-2022-0021. offboarding ticket RET-00110 referenced. | L114: 2026-05-31 | M114: =IFERROR(XLOOKUP(A114,'Source Inventory'!$A$5:$A$200,'Source Inventory'!$H$5:$H$200),"") | N114: 387.24 | O114: =IFERROR(XLOOKUP(A114,'Source Ledger'!$B$5:$B$200,'Source Ledger'!$A$5:$A$200),"") | P114: =IFERROR(XLOOKUP(A114,'Source Ledger'!$B$5:$B$200,'Source Ledger'!$D$5:$D$200),"") | Q114: Medium | R114: EX-0147, EX-0148 | S114: =IF(OR(R114="",R114=0),"No","Yes") | T114: =IFERROR(XLOOKUP(A114,'Source Ledger'!$B$5:$B$200,'Source Ledger'!$E$5:$E$200),"") | U114: =IFERROR(XLOOKUP(A114,'Source Ledger'!$B$5:$B$200,'Source Ledger'!$H$5:$H$200),"") | V114: =IFERROR(XLOOKUP(A114,'Source Ledger'!$B$5:$B$200,'Source Ledger'!$G$5:$G$200),"") | W114: =IF(OR(M114="",T114=""),"",T114-M114) | X114: =IF(V114="","No","Yes")
A115: MD-00111 | B115: =IFERROR(XLOOKUP(A115,'Source Inventory'!$A$5:$A$200,'Source Inventory'!$B$5:$B$200),"") | C115: =IFERROR(XLOOKUP(A115,'Source Inventory'!$A$5:$A$200,'Source Inventory'!$C$5:$C$200),"") | D115: =IFERROR(XLOOKUP(A115,'Source Inventory'!$A$5:$A$200,'Source Inventory'!$D$5:$D$200),"") | E115: =IFERROR(XLOOKUP(A115,'Source Inventory'!$A$5:$A$200,'Source Inventory'!$E$5:$E$200),"") | F115: =IFERROR(XLOOKUP(A115,'Source Inventory'!$A$5:$A$200,'Source Inventory'!$F$5:$F$200),"") | G115: =IFERROR(XLOOKUP(A115,'Source Inventory'!$A$5:$A$200,'Source Inventory'!$G$5:$G$200),"") | H115: Certified Recycler | I115: Disposed | J115: Disposed | K115: Working conclusion for MD-00111 (MD-MO-050111): Disposed at Disposed; cost $1220. Source Ledger FA-000111; net book value $0. PO PO-2022-0021 documents the buy for MD-00111. equipment_transfer_log TR-00111 posted Apr 12, 2026; inbound 2026-04-13 approval APR-00111. | L115: 2026-07-20 | M115: =IFERROR(XLOOKUP(A115,'Source Inventory'!$A$5:$A$200,'Source Inventory'!$H$5:$H$200),"") | N115: 0 | O115: =IFERROR(XLOOKUP(A115,'Source Ledger'!$B$5:$B$200,'Source Ledger'!$A$5:$A$200),"") | P115: =IFERROR(XLOOKUP(A115,'Source Ledger'!$B$5:$B$200,'Source Ledger'!$D$5:$D$200),"") | Q115: High | S115: =IF(OR(R115="",R115=0),"No","Yes") | T115: =IFERROR(XLOOKUP(A115,'Source Ledger'!$B$5:$B$200,'Source Ledger'!$E$5:$E$200),"") | U115: =IFERROR(XLOOKUP(A115,'Source Ledger'!$B$5:$B$200,'Source Ledger'!$H$5:$H$200),"") | V115: =IFERROR(XLOOKUP(A115,'Source Ledger'!$B$5:$B$200,'Source Ledger'!$G$5:$G$200),"") | W115: =IF(OR(M115="",T115=""),"",T115-M115) | X115: =IF(V115="","No","Yes")
A116: MD-00112 | B116: =IFERROR(XLOOKUP(A116,'Source Inventory'!$A$5:$A$200,'Source Inventory'!$B$5:$B$200),"") | C116: =IFERROR(XLOOKUP(A116,'Source Inventory'!$A$5:$A$200,'Source Inventory'!$C$5:$C$200),"") | D116: =IFERROR(XLOOKUP(A116,'Source Inventory'!$A$5:$A$200,'Source Inventory'!$D$5:$D$200),"") | E116: =IFERROR(XLOOKUP(A116,'Source Inventory'!$A$5:$A$200,'Source Inventory'!$E$5:$E$200),"") | F116: =IFERROR(XLOOKUP(A116,'Source Inventory'!$A$5:$A$200,'Source Inventory'!$F$5:$F$200),"") | G116: =IFERROR(XLOOKUP(A116,'Source Inventory'!$A$5:$A$200,'Source Inventory'!$G$5:$G$200),"") | H116: Certified Recycler | I116: Disposed | J116: Disposed | K116: Asset MD-00112 — Microsoft Surface Laptop 5 — reconciled to Disposed in Disposed on $6200 acquisition. equipment_transfer_log TR-00112 posted May 13, 2026; inbound 2026-05-15 approval APR-00112. Source Ledger FA-000112; net book value $0. acquisition recorded on PO-2024-0024. | L116: 2026-07-20 | M116: =IFERROR(XLOOKUP(A116,'Source Inventory'!$A$5:$A$200,'Source Inventory'!$H$5:$H$200),"") | N116: 0 | O116: =IFERROR(XLOOKUP(A116,'Source Ledger'!$B$5:$B$200,'Source Ledger'!$A$5:$A$200),"") | P116: =IFERROR(XLOOKUP(A116,'Source Ledger'!$B$5:$B$200,'Source Ledger'!$D$5:$D$200),"") | Q116: High | S116: =IF(OR(R116="",R116=0),"No","Yes") | T116: =IFERROR(XLOOKUP(A116,'Source Ledger'!$B$5:$B$200,'Source Ledger'!$E$5:$E$200),"") | U116: =IFERROR(XLOOKUP(A116,'Source Ledger'!$B$5:$B$200,'Source Ledger'!$H$5:$H$200),"") | V116: =IFERROR(XLOOKUP(A116,'Source Ledger'!$B$5:$B$200,'Source Ledger'!$G$5:$G$200),"") | W116: =IF(OR(M116="",T116=""),"",T116-M116) | X116: =IF(V116="","No","Yes")
A117: MD-00113 | B117: =IFERROR(XLOOKUP(A117,'Source Inventory'!$A$5:$A$200,'Source Inventory'!$B$5:$B$200),"") | C117: =IFERROR(XLOOKUP(A117,'Source Inventory'!$A$5:$A$200,'Source Inventory'!$C$5:$C$200),"") | D117: =IFERROR(XLOOKUP(A117,'Source Inventory'!$A$5:$A$200,'Source Inventory'!$D$5:$D$200),"") | E117: =IFERROR(XLOOKUP(A117,'Source Inventory'!$A$5:$A$200,'Source Inventory'!$E$5:$E$200),"") | F117: =IFERROR(XLOOKUP(A117,'Source Inventory'!$A$5:$A$200,'Source Inventory'!$F$5:$F$200),"") | G117: =IFERROR(XLOOKUP(A117,'Source Inventory'!$A$5:$A$200,'Source Inventory'!$G$5:$G$200),"") | H117: Certified Recycler | I117: Disposed | J117: Disposed | K117: Files reviewed for MD-00113: Lenovo ThinkPad X1 Carbon, basis $1895, operating site Disposed, status Disposed. Source Ledger FA-000113; net book value $0. order PO-2024-0024 appears in the purchasing extract. equipment_transfer_log TR-00113 posted Jun 17, 2026; inbound 2026-06-18 approval APR-00113. | L117: 2026-07-20 | M117: =IFERROR(XLOOKUP(A117,'Source Inventory'!$A$5:$A$200,'Source Inventory'!$H$5:$H$200),"") | N117: 0 | O117: =IFERROR(XLOOKUP(A117,'Source Ledger'!$B$5:$B$200,'Source Ledger'!$A$5:$A$200),"") | P117: =IFERROR(XLOOKUP(A117,'Source Ledger'!$B$5:$B$200,'Source Ledger'!$D$5:$D$200),"") | Q117: High | S117: =IF(OR(R117="",R117=0),"No","Yes") | T117: =IFERROR(XLOOKUP(A117,'Source Ledger'!$B$5:$B$200,'Source Ledger'!$E$5:$E$200),"") | U117: =IFERROR(XLOOKUP(A117,'Source Ledger'!$B$5:$B$200,'Source Ledger'!$H$5:$H$200),"") | V117: =IFERROR(XLOOKUP(A117,'Source Ledger'!$B$5:$B$200,'Source Ledger'!$G$5:$G$200),"") | W117: =IF(OR(M117="",T117=""),"",T117-M117) | X117: =IF(V117="","No","Yes")
A118: MD-00114 | B118: =IFERROR(XLOOKUP(A118,'Source Inventory'!$A$5:$A$200,'Source Inventory'!$B$5:$B$200),"") | C118: =IFERROR(XLOOKUP(A118,'Source Inventory'!$A$5:$A$200,'Source Inventory'!$C$5:$C$200),"") | D118: =IFERROR(XLOOKUP(A118,'Source Inventory'!$A$5:$A$200,'Source Inventory'!$D$5:$D$200),"") | E118: =IFERROR(XLOOKUP(A118,'Source Inventory'!$A$5:$A$200,'Source Inventory'!$E$5:$E$200),"") | F118: =IFERROR(XLOOKUP(A118,'Source Inventory'!$A$5:$A$200,'Source Inventory'!$F$5:$F$200),"") | G118: =IFERROR(XLOOKUP(A118,'Source Inventory'!$A$5:$A$200,'Source Inventory'!$G$5:$G$200),"") | H118: Certified Recycler | I118: Disposed (certificate missing) | J118: Retired/Pending Disposal | K118: Files reviewed for MD-00114: Lenovo ThinkPad T14, basis $610, operating site Disposed (certificate missing), status Retired/Pending Disposal. Source Ledger FA-000114; net book value $0. acquisition recorded on PO-2024-0024. offboarding ticket RET-00114 referenced. equipment_transfer_log TR-00114 posted Jan 22, 2026; inbound 2026-01-22 approval APR-00114. no verified disposal certificate located. | L118: 2026-01-20 | M118: =IFERROR(XLOOKUP(A118,'Source Inventory'!$A$5:$A$200,'Source Inventory'!$H$5:$H$200),"") | N118: 0 | O118: =IFERROR(XLOOKUP(A118,'Source Ledger'!$B$5:$B$200,'Source Ledger'!$A$5:$A$200),"") | P118: =IFERROR(XLOOKUP(A118,'Source Ledger'!$B$5:$B$200,'Source Ledger'!$D$5:$D$200),"") | Q118: Low | R118: EX-0149, EX-0150 | S118: =IF(OR(R118="",R118=0),"No","Yes") | T118: =IFERROR(XLOOKUP(A118,'Source Ledger'!$B$5:$B$200,'Source Ledger'!$E$5:$E$200),"") | U118: =IFERROR(XLOOKUP(A118,'Source Ledger'!$B$5:$B$200,'Source Ledger'!$H$5:$H$200),"") | V118: =IFERROR(XLOOKUP(A118,'Source Ledger'!$B$5:$B$200,'Source Ledger'!$G$5:$G$200),"") | W118: =IF(OR(M118="",T118=""),"",T118-M118) | X118: =IF(V118="","No","Yes")
A119: MD-00115 | B119: =IFERROR(XLOOKUP(A119,'Source Inventory'!$A$5:$A$200,'Source Inventory'!$B$5:$B$200),"") | C119: =IFERROR(XLOOKUP(A119,'Source Inventory'!$A$5:$A$200,'Source Inventory'!$C$5:$C$200),"") | D119: =IFERROR(XLOOKUP(A119,'Source Inventory'!$A$5:$A$200,'Source Inventory'!$D$5:$D$200),"") | E119: =IFERROR(XLOOKUP(A119,'Source Inventory'!$A$5:$A$200,'Source Inventory'!$E$5:$E$200),"") | F119: =IFERROR(XLOOKUP(A119,'Source Inventory'!$A$5:$A$200,'Source Inventory'!$F$5:$F$200),"") | G119: =IFERROR(XLOOKUP(A119,'Source Inventory'!$A$5:$A$200,'Source Inventory'!$G$5:$G$200),"") | H119: Certified Recycler | I119: Disposed | J119: Disposed | K119: Files reviewed for MD-00115: MacBook Pro 14, basis $1085, operating site Disposed, status Disposed. Source Ledger FA-000115; net book value $0. order PO-2024-0024 appears in the purchasing extract. equipment_transfer_log TR-00115 posted Feb 23, 2026; inbound 2026-02-25 approval APR-00115. | L119: 2026-07-20 | M119: =IFERROR(XLOOKUP(A119,'Source Inventory'!$A$5:$A$200,'Source Inventory'!$H$5:$H$200),"") | N119: 0 | O119: =IFERROR(XLOOKUP(A119,'Source Ledger'!$B$5:$B$200,'Source Ledger'!$A$5:$A$200),"") | P119: =IFERROR(XLOOKUP(A119,'Source Ledger'!$B$5:$B$200,'Source Ledger'!$D$5:$D$200),"") | Q119: High | S119: =IF(OR(R119="",R119=0),"No","Yes") | T119: =IFERROR(XLOOKUP(A119,'Source Ledger'!$B$5:$B$200,'Source Ledger'!$E$5:$E$200),"") | U119: =IFERROR(XLOOKUP(A119,'Source Ledger'!$B$5:$B$200,'Source Ledger'!$H$5:$H$200),"") | V119: =IFERROR(XLOOKUP(A119,'Source Ledger'!$B$5:$B$200,'Source Ledger'!$G$5:$G$200),"") | W119: =IF(OR(M119="",T119=""),"",T119-M119) | X119: =IF(V119="","No","Yes")
A120: MD-00116 | B120: =IFERROR(XLOOKUP(A120,'Source Inventory'!$A$5:$A$200,'Source Inventory'!$B$5:$B$200),"") | C120: =IFERROR(XLOOKUP(A120,'Source Inventory'!$A$5:$A$200,'Source Inventory'!$C$5:$C$200),"") | D120: =IFERROR(XLOOKUP(A120,'Source Inventory'!$A$5:$A$200,'Source Inventory'!$D$5:$D$200),"") | E120: =IFERROR(XLOOKUP(A120,'Source Inventory'!$A$5:$A$200,'Source Inventory'!$E$5:$E$200),"") | F120: =IFERROR(XLOOKUP(A120,'Source Inventory'!$A$5:$A$200,'Source Inventory'!$F$5:$F$200),"") | G120: =IFERROR(XLOOKUP(A120,'Source Inventory'!$A$5:$A$200,'Source Inventory'!$G$5:$G$200),"") | H120: Certified Recycler | I120: Disposed | J120: Disposed | K120: Asset MD-00116 — Dell Latitude 7440 — reconciled to Disposed in Disposed on $6380 acquisition. equipment_transfer_log TR-00116 posted Mar 28, 2026; inbound 2026-03-29 approval APR-00116. PO PO-2024-0024 documents the buy for MD-00116. Source Ledger FA-000116; net book value $0. | L120: 2026-07-20 | M120: =IFERROR(XLOOKUP(A120,'Source Inventory'!$A$5:$A$200,'Source Inventory'!$H$5:$H$200),"") | N120: 0 | O120: =IFERROR(XLOOKUP(A120,'Source Ledger'!$B$5:$B$200,'Source Ledger'!$A$5:$A$200),"") | P120: =IFERROR(XLOOKUP(A120,'Source Ledger'!$B$5:$B$200,'Source Ledger'!$D$5:$D$200),"") | Q120: High | S120: =IF(OR(R120="",R120=0),"No","Yes") | T120: =IFERROR(XLOOKUP(A120,'Source Ledger'!$B$5:$B$200,'Source Ledger'!$E$5:$E$200),"") | U120: =IFERROR(XLOOKUP(A120,'Source Ledger'!$B$5:$B$200,'Source Ledger'!$H$5:$H$200),"") | V120: =IFERROR(XLOOKUP(A120,'Source Ledger'!$B$5:$B$200,'Source Ledger'!$G$5:$G$200),"") | W120: =IF(OR(M120="",T120=""),"",T120-M120) | X120: =IF(V120="","No","Yes")
A121: MD-00117 | B121: =IFERROR(XLOOKUP(A121,'Source Inventory'!$A$5:$A$200,'Source Inventory'!$B$5:$B$200),"") | C121: =IFERROR(XLOOKUP(A121,'Source Inventory'!$A$5:$A$200,'Source Inventory'!$C$5:$C$200),"") | D121: =IFERROR(XLOOKUP(A121,'Source Inventory'!$A$5:$A$200,'Source Inventory'!$D$5:$D$200),"") | E121: =IFERROR(XLOOKUP(A121,'Source Inventory'!$A$5:$A$200,'Source Inventory'!$E$5:$E$200),"") | F121: =IFERROR(XLOOKUP(A121,'Source Inventory'!$A$5:$A$200,'Source Inventory'!$F$5:$F$200),"") | G121: =IFERROR(XLOOKUP(A121,'Source Inventory'!$A$5:$A$200,'Source Inventory'!$G$5:$G$200),"") | H121: Certified Recycler | I121: Disposed | J121: Disposed | K121: Files reviewed for MD-00117: HP EliteBook 840 G10, basis $2075, operating site Disposed, status Disposed. Source Ledger FA-000117; net book value $0. buy path for MD-00117 references PO-2024-0024. equipment_transfer_log TR-00117 posted May 02, 2026; inbound 2026-05-02 approval APR-00117. | L121: 2026-07-20 | M121: =IFERROR(XLOOKUP(A121,'Source Inventory'!$A$5:$A$200,'Source Inventory'!$H$5:$H$200),"") | N121: 0 | O121: =IFERROR(XLOOKUP(A121,'Source Ledger'!$B$5:$B$200,'Source Ledger'!$A$5:$A$200),"") | P121: =IFERROR(XLOOKUP(A121,'Source Ledger'!$B$5:$B$200,'Source Ledger'!$D$5:$D$200),"") | Q121: High | S121: =IF(OR(R121="",R121=0),"No","Yes") | T121: =IFERROR(XLOOKUP(A121,'Source Ledger'!$B$5:$B$200,'Source Ledger'!$E$5:$E$200),"") | U121: =IFERROR(XLOOKUP(A121,'Source Ledger'!$B$5:$B$200,'Source Ledger'!$H$5:$H$200),"") | V121: =IFERROR(XLOOKUP(A121,'Source Ledger'!$B$5:$B$200,'Source Ledger'!$G$5:$G$200),"") | W121: =IF(OR(M121="",T121=""),"",T121-M121) | X121: =IF(V121="","No","Yes")
A122: MD-00118 | B122: =IFERROR(XLOOKUP(A122,'Source Inventory'!$A$5:$A$200,'Source Inventory'!$B$5:$B$200),"") | C122: =IFERROR(XLOOKUP(A122,'Source Inventory'!$A$5:$A$200,'Source Inventory'!$C$5:$C$200),"") | D122: =IFERROR(XLOOKUP(A122,'Source Inventory'!$A$5:$A$200,'Source Inventory'!$D$5:$D$200),"") | E122: =IFERROR(XLOOKUP(A122,'Source Inventory'!$A$5:$A$200,'Source Inventory'!$E$5:$E$200),"") | F122: =IFERROR(XLOOKUP(A122,'Source Inventory'!$A$5:$A$200,'Source Inventory'!$F$5:$F$200),"") | G122: =IFERROR(XLOOKUP(A122,'Source Inventory'!$A$5:$A$200,'Source Inventory'!$G$5:$G$200),"") | H122: Certified Recycler | I122: Disposed (certificate missing) | J122: Retired/Pending Disposal | K122: Files reviewed for MD-00118: Microsoft Surface Laptop 5, basis $790, operating site Disposed (certificate missing), status Retired/Pending Disposal. Source Ledger FA-000118; net book value $0. PO PO-2024-0024 documents the buy for MD-00118. offboarding ticket RET-00118 referenced. equipment_transfer_log TR-00118 posted Jun 03, 2026; inbound 2026-06-04 approval APR-00118. no verified disposal certificate located. | L122: 2026-05-24 | M122: =IFERROR(XLOOKUP(A122,'Source Inventory'!$A$5:$A$200,'Source Inventory'!$H$5:$H$200),"") | N122: 0 | O122: =IFERROR(XLOOKUP(A122,'Source Ledger'!$B$5:$B$200,'Source Ledger'!$A$5:$A$200),"") | P122: =IFERROR(XLOOKUP(A122,'Source Ledger'!$B$5:$B$200,'Source Ledger'!$D$5:$D$200),"") | Q122: Low | R122: EX-0151, EX-0152 | S122: =IF(OR(R122="",R122=0),"No","Yes") | T122: =IFERROR(XLOOKUP(A122,'Source Ledger'!$B$5:$B$200,'Source Ledger'!$E$5:$E$200),"") | U122: =IFERROR(XLOOKUP(A122,'Source Ledger'!$B$5:$B$200,'Source Ledger'!$H$5:$H$200),"") | V122: =IFERROR(XLOOKUP(A122,'Source Ledger'!$B$5:$B$200,'Source Ledger'!$G$5:$G$200),"") | W122: =IF(OR(M122="",T122=""),"",T122-M122) | X122: =IF(V122="","No","Yes")
A123: MD-00119 | B123: =IFERROR(XLOOKUP(A123,'Source Inventory'!$A$5:$A$200,'Source Inventory'!$B$5:$B$200),"") | C123: =IFERROR(XLOOKUP(A123,'Source Inventory'!$A$5:$A$200,'Source Inventory'!$C$5:$C$200),"") | D123: =IFERROR(XLOOKUP(A123,'Source Inventory'!$A$5:$A$200,'Source Inventory'!$D$5:$D$200),"") | E123: =IFERROR(XLOOKUP(A123,'Source Inventory'!$A$5:$A$200,'Source Inventory'!$E$5:$E$200),"") | F123: =IFERROR(XLOOKUP(A123,'Source Inventory'!$A$5:$A$200,'Source Inventory'!$F$5:$F$200),"") | G123: =IFERROR(XLOOKUP(A123,'Source Inventory'!$A$5:$A$200,'Source Inventory'!$G$5:$G$200),"") | H123: Certified Recycler | I123: Disposed | J123: Disposed | K123: Files reviewed for MD-00119: Lenovo ThinkPad X1 Carbon, basis $950, operating site Disposed, status Disposed. Source Ledger FA-000119; net book value $0. buy path for MD-00119 references PO-2024-0024. equipment_transfer_log TR-00119 posted Jul 08, 2026; inbound 2026-07-09 approval APR-00119. | L123: 2026-07-20 | M123: =IFERROR(XLOOKUP(A123,'Source Inventory'!$A$5:$A$200,'Source Inventory'!$H$5:$H$200),"") | N123: 0 | O123: =IFERROR(XLOOKUP(A123,'Source Ledger'!$B$5:$B$200,'Source Ledger'!$A$5:$A$200),"") | P123: =IFERROR(XLOOKUP(A123,'Source Ledger'!$B$5:$B$200,'Source Ledger'!$D$5:$D$200),"") | Q123: High | R123: EX-0153 | S123: =IF(OR(R123="",R123=0),"No","Yes") | T123: =IFERROR(XLOOKUP(A123,'Source Ledger'!$B$5:$B$200,'Source Ledger'!$E$5:$E$200),"") | U123: =IFERROR(XLOOKUP(A123,'Source Ledger'!$B$5:$B$200,'Source Ledger'!$H$5:$H$200),"") | V123: =IFERROR(XLOOKUP(A123,'Source Ledger'!$B$5:$B$200,'Source Ledger'!$G$5:$G$200),"") | W123: =IF(OR(M123="",T123=""),"",T123-M123) | X123: =IF(V123="","No","Yes")
A124: MD-00120 | B124: =IFERROR(XLOOKUP(A124,'Source Inventory'!$A$5:$A$200,'Source Inventory'!$B$5:$B$200),"") | C124: =IFERROR(XLOOKUP(A124,'Source Inventory'!$A$5:$A$200,'Source Inventory'!$C$5:$C$200),"") | D124: =IFERROR(XLOOKUP(A124,'Source Inventory'!$A$5:$A$200,'Source Inventory'!$D$5:$D$200),"") | E124: =IFERROR(XLOOKUP(A124,'Source Inventory'!$A$5:$A$200,'Source Inventory'!$E$5:$E$200),"") | F124: =IFERROR(XLOOKUP(A124,'Source Inventory'!$A$5:$A$200,'Source Inventory'!$F$5:$F$200),"") | G124: =IFERROR(XLOOKUP(A124,'Source Inventory'!$A$5:$A$200,'Source Inventory'!$G$5:$G$200),"") | H124: Certified Recycler | I124: Disposed | J124: Disposed | K124: Files reviewed for MD-00120: MacBook Pro 14, basis $6245, operating site Disposed, status Disposed. acquisition recorded on PO-2025-0025. equipment_transfer_log TR-00120 posted Jan 18, 2026; inbound 2026-01-20 approval APR-00120. Source Ledger FA-000120; net book value $0. | L124: 2026-07-20 | M124: =IFERROR(XLOOKUP(A124,'Source Inventory'!$A$5:$A$200,'Source Inventory'!$H$5:$H$200),"") | N124: 0 | O124: =IFERROR(XLOOKUP(A124,'Source Ledger'!$B$5:$B$200,'Source Ledger'!$A$5:$A$200),"") | P124: =IFERROR(XLOOKUP(A124,'Source Ledger'!$B$5:$B$200,'Source Ledger'!$D$5:$D$200),"") | Q124: High | S124: =IF(OR(R124="",R124=0),"No","Yes") | T124: =IFERROR(XLOOKUP(A124,'Source Ledger'!$B$5:$B$200,'Source Ledger'!$E$5:$E$200),"") | U124: =IFERROR(XLOOKUP(A124,'Source Ledger'!$B$5:$B$200,'Source Ledger'!$H$5:$H$200),"") | V124: =IFERROR(XLOOKUP(A124,'Source Ledger'!$B$5:$B$200,'Source Ledger'!$G$5:$G$200),"") | W124: =IF(OR(M124="",T124=""),"",T124-M124) | X124: =IF(V124="","No","Yes")
A125: MD-00121 | B125: =IFERROR(XLOOKUP(A125,'Source Inventory'!$A$5:$A$200,'Source Inventory'!$B$5:$B$200),"") | C125: =IFERROR(XLOOKUP(A125,'Source Inventory'!$A$5:$A$200,'Source Inventory'!$C$5:$C$200),"") | D125: =IFERROR(XLOOKUP(A125,'Source Inventory'!$A$5:$A$200,'Source Inventory'!$D$5:$D$200),"") | E125: =IFERROR(XLOOKUP(A125,'Source Inventory'!$A$5:$A$200,'Source Inventory'!$E$5:$E$200),"") | F125: =IFERROR(XLOOKUP(A125,'Source Inventory'!$A$5:$A$200,'Source Inventory'!$F$5:$F$200),"") | G125: =IFERROR(XLOOKUP(A125,'Source Inventory'!$A$5:$A$200,'Source Inventory'!$G$5:$G$200),"") | H125: IT Stock | I125: Chicago | J125: Available | K125: Asset MD-00121 — Dell Latitude 7440 — reconciled to Available in Chicago on $1940 acquisition. equipment_transfer_log TR-00121 posted Jan 21, 2026; inbound 2026-01-21 approval APR-00121. Source Ledger FA-000121; net book value $0. order PO-2025-0025 appears in the purchasing extract. | L125: 2026-02-03 | M125: =IFERROR(XLOOKUP(A125,'Source Inventory'!$A$5:$A$200,'Source Inventory'!$H$5:$H$200),"") | N125: 0 | O125: =IFERROR(XLOOKUP(A125,'Source Ledger'!$B$5:$B$200,'Source Ledger'!$A$5:$A$200),"") | P125: =IFERROR(XLOOKUP(A125,'Source Ledger'!$B$5:$B$200,'Source Ledger'!$D$5:$D$200),"") | Q125: High | R125: EX-0154 | S125: =IF(OR(R125="",R125=0),"No","Yes") | T125: =IFERROR(XLOOKUP(A125,'Source Ledger'!$B$5:$B$200,'Source Ledger'!$E$5:$E$200),"") | U125: =IFERROR(XLOOKUP(A125,'Source Ledger'!$B$5:$B$200,'Source Ledger'!$H$5:$H$200),"") | V125: =IFERROR(XLOOKUP(A125,'Source Ledger'!$B$5:$B$200,'Source Ledger'!$G$5:$G$200),"") | W125: =IF(OR(M125="",T125=""),"",T125-M125) | X125: =IF(V125="","No","Yes")
A126: MD-00122 | B126: =IFERROR(XLOOKUP(A126,'Source Inventory'!$A$5:$A$200,'Source Inventory'!$B$5:$B$200),"") | C126: =IFERROR(XLOOKUP(A126,'Source Inventory'!$A$5:$A$200,'Source Inventory'!$C$5:$C$200),"") | D126: =IFERROR(XLOOKUP(A126,'Source Inventory'!$A$5:$A$200,'Source Inventory'!$D$5:$D$200),"") | E126: =IFERROR(XLOOKUP(A126,'Source Inventory'!$A$5:$A$200,'Source Inventory'!$E$5:$E$200),"") | F126: =IFERROR(XLOOKUP(A126,'Source Inventory'!$A$5:$A$200,'Source Inventory'!$F$5:$F$200),"") | G126: =IFERROR(XLOOKUP(A126,'Source Inventory'!$A$5:$A$200,'Source Inventory'!$G$5:$G$200),"") | H126: IT Stock | I126: Dallas | J126: Available | K126: Files reviewed for MD-00122: HP EliteBook 840 G10, basis $655, operating site Dallas, status Available. acquisition recorded on PO-2025-0025. equipment_transfer_log TR-00122 posted Feb 23, 2026; inbound 2026-02-25 approval APR-00122. Source Ledger FA-000122; net book value $336.15. | L126: 2026-03-04 | M126: =IFERROR(XLOOKUP(A126,'Source Inventory'!$A$5:$A$200,'Source Inventory'!$H$5:$H$200),"") | N126: 336.15 | O126: =IFERROR(XLOOKUP(A126,'Source Ledger'!$B$5:$B$200,'Source Ledger'!$A$5:$A$200),"") | P126: =IFERROR(XLOOKUP(A126,'Source Ledger'!$B$5:$B$200,'Source Ledger'!$D$5:$D$200),"") | Q126: High | R126: EX-0155 | S126: =IF(OR(R126="",R126=0),"No","Yes") | T126: =IFERROR(XLOOKUP(A126,'Source Ledger'!$B$5:$B$200,'Source Ledger'!$E$5:$E$200),"") | U126: =IFERROR(XLOOKUP(A126,'Source Ledger'!$B$5:$B$200,'Source Ledger'!$H$5:$H$200),"") | V126: =IFERROR(XLOOKUP(A126,'Source Ledger'!$B$5:$B$200,'Source Ledger'!$G$5:$G$200),"") | W126: =IF(OR(M126="",T126=""),"",T126-M126) | X126: =IF(V126="","No","Yes")
A127: MD-00123 | B127: =IFERROR(XLOOKUP(A127,'Source Inventory'!$A$5:$A$200,'Source Inventory'!$B$5:$B$200),"") | C127: =IFERROR(XLOOKUP(A127,'Source Inventory'!$A$5:$A$200,'Source Inventory'!$C$5:$C$200),"") | D127: =IFERROR(XLOOKUP(A127,'Source Inventory'!$A$5:$A$200,'Source Inventory'!$D$5:$D$200),"") | E127: =IFERROR(XLOOKUP(A127,'Source Inventory'!$A$5:$A$200,'Source Inventory'!$E$5:$E$200),"") | F127: =IFERROR(XLOOKUP(A127,'Source Inventory'!$A$5:$A$200,'Source Inventory'!$F$5:$F$200),"") | G127: =IFERROR(XLOOKUP(A127,'Source Inventory'!$A$5:$A$200,'Source Inventory'!$G$5:$G$200),"") | H127: IT Stock | I127: Denver | J127: Available | K127: Files reviewed for MD-00123: Microsoft Surface Laptop 5, basis $1130, operating site Denver, status Available. order PO-2025-0025 appears in the purchasing extract. equipment_transfer_log TR-00123 posted Mar 31, 2026; inbound 2026-04-03 approval APR-00123. Source Ledger FA-000123; net book value $622.62. | L127: 2026-04-05 | M127: =IFERROR(XLOOKUP(A127,'Source Inventory'!$A$5:$A$200,'Source Inventory'!$H$5:$H$200),"") | N127: 622.62 | O127: =IFERROR(XLOOKUP(A127,'Source Ledger'!$B$5:$B$200,'Source Ledger'!$A$5:$A$200),"") | P127: =IFERROR(XLOOKUP(A127,'Source Ledger'!$B$5:$B$200,'Source Ledger'!$D$5:$D$200),"") | Q127: High | R127: EX-0156 | S127: =IF(OR(R127="",R127=0),"No","Yes") | T127: =IFERROR(XLOOKUP(A127,'Source Ledger'!$B$5:$B$200,'Source Ledger'!$E$5:$E$200),"") | U127: =IFERROR(XLOOKUP(A127,'Source Ledger'!$B$5:$B$200,'Source Ledger'!$H$5:$H$200),"") | V127: =IFERROR(XLOOKUP(A127,'Source Ledger'!$B$5:$B$200,'Source Ledger'!$G$5:$G$200),"") | W127: =IF(OR(M127="",T127=""),"",T127-M127) | X127: =IF(V127="","No","Yes")
A128: MD-00124 | B128: =IFERROR(XLOOKUP(A128,'Source Inventory'!$A$5:$A$200,'Source Inventory'!$B$5:$B$200),"") | C128: =IFERROR(XLOOKUP(A128,'Source Inventory'!$A$5:$A$200,'Source Inventory'!$C$5:$C$200),"") | D128: =IFERROR(XLOOKUP(A128,'Source Inventory'!$A$5:$A$200,'Source Inventory'!$D$5:$D$200),"") | E128: =IFERROR(XLOOKUP(A128,'Source Inventory'!$A$5:$A$200,'Source Inventory'!$E$5:$E$200),"") | F128: =IFERROR(XLOOKUP(A128,'Source Inventory'!$A$5:$A$200,'Source Inventory'!$F$5:$F$200),"") | G128: =IFERROR(XLOOKUP(A128,'Source Inventory'!$A$5:$A$200,'Source Inventory'!$G$5:$G$200),"") | H128: IT Stock | I128: New York | J128: Available | K128: Files reviewed for MD-00124: Lenovo ThinkPad X1 Carbon, basis $6425, operating site New York, status Available. acquisition recorded on PO-2022-0026. equipment_transfer_log TR-00124 posted May 01, 2026; inbound 2026-05-01 approval APR-00124. Source Ledger FA-000124; net book value $947.26. | L128: 2026-05-06 | M128: =IFERROR(XLOOKUP(A128,'Source Inventory'!$A$5:$A$200,'Source Inventory'!$H$5:$H$200),"") | N128: 947.26 | O128: =IFERROR(XLOOKUP(A128,'Source Ledger'!$B$5:$B$200,'Source Ledger'!$A$5:$A$200),"") | P128: =IFERROR(XLOOKUP(A128,'Source Ledger'!$B$5:$B$200,'Source Ledger'!$D$5:$D$200),"") | Q128: High | R128: EX-0157 | S128: =IF(OR(R128="",R128=0),"No","Yes") | T128: =IFERROR(XLOOKUP(A128,'Source Ledger'!$B$5:$B$200,'Source Ledger'!$E$5:$E$200),"") | U128: =IFERROR(XLOOKUP(A128,'Source Ledger'!$B$5:$B$200,'Source Ledger'!$H$5:$H$200),"") | V128: =IFERROR(XLOOKUP(A128,'Source Ledger'!$B$5:$B$200,'Source Ledger'!$G$5:$G$200),"") | W128: =IF(OR(M128="",T128=""),"",T128-M128) | X128: =IF(V128="","No","Yes")
A129: MD-00125 | B129: =IFERROR(XLOOKUP(A129,'Source Inventory'!$A$5:$A$200,'Source Inventory'!$B$5:$B$200),"") | C129: =IFERROR(XLOOKUP(A129,'Source Inventory'!$A$5:$A$200,'Source Inventory'!$C$5:$C$200),"") | D129: =IFERROR(XLOOKUP(A129,'Source Inventory'!$A$5:$A$200,'Source Inventory'!$D$5:$D$200),"") | E129: =IFERROR(XLOOKUP(A129,'Source Inventory'!$A$5:$A$200,'Source Inventory'!$E$5:$E$200),"") | F129: =IFERROR(XLOOKUP(A129,'Source Inventory'!$A$5:$A$200,'Source Inventory'!$F$5:$F$200),"") | G129: =IFERROR(XLOOKUP(A129,'Source Inventory'!$A$5:$A$200,'Source Inventory'!$G$5:$G$200),"") | H129: IT Stock | I129: Seattle | J129: Available | K129: Reconciliation packet cites MD-00125 with acquisition $2120 and custody Available at Seattle. equipment_transfer_log TR-00125 posted Jun 05, 2026; inbound 2026-06-08 approval APR-00125. Source Ledger FA-000125; net book value $0. order PO-2022-0026 appears in the purchasing extract. | L129: 2026-06-07 | M129: =IFERROR(XLOOKUP(A129,'Source Inventory'!$A$5:$A$200,'Source Inventory'!$H$5:$H$200),"") | N129: 0 | O129: =IFERROR(XLOOKUP(A129,'Source Ledger'!$B$5:$B$200,'Source Ledger'!$A$5:$A$200),"") | P129: =IFERROR(XLOOKUP(A129,'Source Ledger'!$B$5:$B$200,'Source Ledger'!$D$5:$D$200),"") | Q129: High | R129: EX-0158 | S129: =IF(OR(R129="",R129=0),"No","Yes") | T129: =IFERROR(XLOOKUP(A129,'Source Ledger'!$B$5:$B$200,'Source Ledger'!$E$5:$E$200),"") | U129: =IFERROR(XLOOKUP(A129,'Source Ledger'!$B$5:$B$200,'Source Ledger'!$H$5:$H$200),"") | V129: =IFERROR(XLOOKUP(A129,'Source Ledger'!$B$5:$B$200,'Source Ledger'!$G$5:$G$200),"") | W129: =IF(OR(M129="",T129=""),"",T129-M129) | X129: =IF(V129="","No","Yes")
A130: MD-00126 | B130: =IFERROR(XLOOKUP(A130,'Source Inventory'!$A$5:$A$200,'Source Inventory'!$B$5:$B$200),"") | C130: =IFERROR(XLOOKUP(A130,'Source Inventory'!$A$5:$A$200,'Source Inventory'!$C$5:$C$200),"") | D130: =IFERROR(XLOOKUP(A130,'Source Inventory'!$A$5:$A$200,'Source Inventory'!$D$5:$D$200),"") | E130: =IFERROR(XLOOKUP(A130,'Source Inventory'!$A$5:$A$200,'Source Inventory'!$E$5:$E$200),"") | F130: =IFERROR(XLOOKUP(A130,'Source Inventory'!$A$5:$A$200,'Source Inventory'!$F$5:$F$200),"") | G130: =IFERROR(XLOOKUP(A130,'Source Inventory'!$A$5:$A$200,'Source Inventory'!$G$5:$G$200),"") | H130: IT Stock | I130: Atlanta | J130: Available | K130: Reconciliation packet cites MD-00126 with acquisition $520 and custody Available at Atlanta. equipment_transfer_log TR-00126 posted Jan 10, 2026; inbound 2026-01-12 approval APR-00126. Source Ledger FA-000126; net book value $302.75. PO PO-2022-0026 documents the buy for MD-00126. | L130: 2026-01-08 | M130: =IFERROR(XLOOKUP(A130,'Source Inventory'!$A$5:$A$200,'Source Inventory'!$H$5:$H$200),"") | N130: 302.75 | O130: =IFERROR(XLOOKUP(A130,'Source Ledger'!$B$5:$B$200,'Source Ledger'!$A$5:$A$200),"") | P130: =IFERROR(XLOOKUP(A130,'Source Ledger'!$B$5:$B$200,'Source Ledger'!$D$5:$D$200),"") | Q130: High | R130: EX-0159 | S130: =IF(OR(R130="",R130=0),"No","Yes") | T130: =IFERROR(XLOOKUP(A130,'Source Ledger'!$B$5:$B$200,'Source Ledger'!$E$5:$E$200),"") | U130: =IFERROR(XLOOKUP(A130,'Source Ledger'!$B$5:$B$200,'Source Ledger'!$H$5:$H$200),"") | V130: =IFERROR(XLOOKUP(A130,'Source Ledger'!$B$5:$B$200,'Source Ledger'!$G$5:$G$200),"") | W130: =IF(OR(M130="",T130=""),"",T130-M130) | X130: =IF(V130="","No","Yes")
A131: MD-00127 | B131: =IFERROR(XLOOKUP(A131,'Source Inventory'!$A$5:$A$200,'Source Inventory'!$B$5:$B$200),"") | C131: =IFERROR(XLOOKUP(A131,'Source Inventory'!$A$5:$A$200,'Source Inventory'!$C$5:$C$200),"") | D131: =IFERROR(XLOOKUP(A131,'Source Inventory'!$A$5:$A$200,'Source Inventory'!$D$5:$D$200),"") | E131: =IFERROR(XLOOKUP(A131,'Source Inventory'!$A$5:$A$200,'Source Inventory'!$E$5:$E$200),"") | F131: =IFERROR(XLOOKUP(A131,'Source Inventory'!$A$5:$A$200,'Source Inventory'!$F$5:$F$200),"") | G131: =IFERROR(XLOOKUP(A131,'Source Inventory'!$A$5:$A$200,'Source Inventory'!$G$5:$G$200),"") | H131: E0061 | I131: Denver | J131: In Use | K131: Reconciliation packet cites MD-00127 with acquisition $995 and custody In Use at Denver. hr_employee_status lists Liam Keane (E0061) as Transferred. equipment_transfer_log TR-00127 posted Feb 11, 2026; inbound 2026-02-17 blank approval field. Source Ledger FA-000127; net book value $662.65. buy path for MD-00127 references PO-2022-0026. | L131: 2026-08-05 | M131: =IFERROR(XLOOKUP(A131,'Source Inventory'!$A$5:$A$200,'Source Inventory'!$H$5:$H$200),"") | N131: 662.65 | O131: =IFERROR(XLOOKUP(A131,'Source Ledger'!$B$5:$B$200,'Source Ledger'!$A$5:$A$200),"") | P131: =IFERROR(XLOOKUP(A131,'Source Ledger'!$B$5:$B$200,'Source Ledger'!$D$5:$D$200),"") | Q131: Medium | R131: EX-0160 | S131: =IF(OR(R131="",R131=0),"No","Yes") | T131: =IFERROR(XLOOKUP(A131,'Source Ledger'!$B$5:$B$200,'Source Ledger'!$E$5:$E$200),"") | U131: =IFERROR(XLOOKUP(A131,'Source Ledger'!$B$5:$B$200,'Source Ledger'!$H$5:$H$200),"") | V131: =IFERROR(XLOOKUP(A131,'Source Ledger'!$B$5:$B$200,'Source Ledger'!$G$5:$G$200),"") | W131: =IF(OR(M131="",T131=""),"",T131-M131) | X131: =IF(V131="","No","Yes")
A132: MD-00128 | B132: =IFERROR(XLOOKUP(A132,'Source Inventory'!$A$5:$A$200,'Source Inventory'!$B$5:$B$200),"") | C132: =IFERROR(XLOOKUP(A132,'Source Inventory'!$A$5:$A$200,'Source Inventory'!$C$5:$C$200),"") | D132: =IFERROR(XLOOKUP(A132,'Source Inventory'!$A$5:$A$200,'Source Inventory'!$D$5:$D$200),"") | E132: =IFERROR(XLOOKUP(A132,'Source Inventory'!$A$5:$A$200,'Source Inventory'!$E$5:$E$200),"") | F132: =IFERROR(XLOOKUP(A132,'Source Inventory'!$A$5:$A$200,'Source Inventory'!$F$5:$F$200),"") | G132: =IFERROR(XLOOKUP(A132,'Source Inventory'!$A$5:$A$200,'Source Inventory'!$G$5:$G$200),"") | H132: E0062 | I132: New York | J132: In Use | K132: Reconciliation packet cites MD-00128 with acquisition $6290 and custody In Use at New York. hr_employee_status lists Bianca Silva (E0062) as Transferred. equipment_transfer_log TR-00128 posted Mar 16, 2026; inbound 2026-03-19 approval APR-00128. Source Ledger FA-000128; net book value $1364.77. PO PO-2022-0026 documents the buy for MD-00128. | L132: 2026-08-05 | M132: =IFERROR(XLOOKUP(A132,'Source Inventory'!$A$5:$A$200,'Source Inventory'!$H$5:$H$200),"") | N132: 1364.77 | O132: =IFERROR(XLOOKUP(A132,'Source Ledger'!$B$5:$B$200,'Source Ledger'!$A$5:$A$200),"") | P132: =IFERROR(XLOOKUP(A132,'Source Ledger'!$B$5:$B$200,'Source Ledger'!$D$5:$D$200),"") | Q132: High | S132: =IF(OR(R132="",R132=0),"No","Yes") | T132: =IFERROR(XLOOKUP(A132,'Source Ledger'!$B$5:$B$200,'Source Ledger'!$E$5:$E$200),"") | U132: =IFERROR(XLOOKUP(A132,'Source Ledger'!$B$5:$B$200,'Source Ledger'!$H$5:$H$200),"") | V132: =IFERROR(XLOOKUP(A132,'Source Ledger'!$B$5:$B$200,'Source Ledger'!$G$5:$G$200),"") | W132: =IF(OR(M132="",T132=""),"",T132-M132) | X132: =IF(V132="","No","Yes")
A133: MD-00129 | B133: =IFERROR(XLOOKUP(A133,'Source Inventory'!$A$5:$A$200,'Source Inventory'!$B$5:$B$200),"") | C133: =IFERROR(XLOOKUP(A133,'Source Inventory'!$A$5:$A$200,'Source Inventory'!$C$5:$C$200),"") | D133: =IFERROR(XLOOKUP(A133,'Source Inventory'!$A$5:$A$200,'Source Inventory'!$D$5:$D$200),"") | E133: =IFERROR(XLOOKUP(A133,'Source Inventory'!$A$5:$A$200,'Source Inventory'!$E$5:$E$200),"") | F133: =IFERROR(XLOOKUP(A133,'Source Inventory'!$A$5:$A$200,'Source Inventory'!$F$5:$F$200),"") | G133: =IFERROR(XLOOKUP(A133,'Source Inventory'!$A$5:$A$200,'Source Inventory'!$G$5:$G$200),"") | H133: E0063 | I133: Seattle | J133: In Use | K133: Reconciliation packet cites MD-00129 with acquisition $1985 and custody In Use at Seattle. hr_employee_status lists Greg Hollis (E0063) as Transferred. equipment_transfer_log TR-00129 posted Apr 20, 2026; inbound 2026-04-21 approval APR-00129. Source Ledger FA-000129; net book value $111.86. buy path for MD-00129 references PO-2022-0026. | L133: 2026-08-05 | M133: =IFERROR(XLOOKUP(A133,'Source Inventory'!$A$5:$A$200,'Source Inventory'!$H$5:$H$200),"") | N133: 111.86 | O133: =IFERROR(XLOOKUP(A133,'Source Ledger'!$B$5:$B$200,'Source Ledger'!$A$5:$A$200),"") | P133: =IFERROR(XLOOKUP(A133,'Source Ledger'!$B$5:$B$200,'Source Ledger'!$D$5:$D$200),"") | Q133: High | S133: =IF(OR(R133="",R133=0),"No","Yes") | T133: =IFERROR(XLOOKUP(A133,'Source Ledger'!$B$5:$B$200,'Source Ledger'!$E$5:$E$200),"") | U133: =IFERROR(XLOOKUP(A133,'Source Ledger'!$B$5:$B$200,'Source Ledger'!$H$5:$H$200),"") | V133: =IFERROR(XLOOKUP(A133,'Source Ledger'!$B$5:$B$200,'Source Ledger'!$G$5:$G$200),"") | W133: =IF(OR(M133="",T133=""),"",T133-M133) | X133: =IF(V133="","No","Yes")
A134: MD-00130 | B134: =IFERROR(XLOOKUP(A134,'Source Inventory'!$A$5:$A$200,'Source Inventory'!$B$5:$B$200),"") | C134: =IFERROR(XLOOKUP(A134,'Source Inventory'!$A$5:$A$200,'Source Inventory'!$C$5:$C$200),"") | D134: =IFERROR(XLOOKUP(A134,'Source Inventory'!$A$5:$A$200,'Source Inventory'!$D$5:$D$200),"") | E134: =IFERROR(XLOOKUP(A134,'Source Inventory'!$A$5:$A$200,'Source Inventory'!$E$5:$E$200),"") | F134: =IFERROR(XLOOKUP(A134,'Source Inventory'!$A$5:$A$200,'Source Inventory'!$F$5:$F$200),"") | G134: =IFERROR(XLOOKUP(A134,'Source Inventory'!$A$5:$A$200,'Source Inventory'!$G$5:$G$200),"") | H134: E0064 | I134: Atlanta | J134: In Use | K134: Files reviewed for MD-00130: Lenovo ThinkPad T14, basis $700, operating site Atlanta, status In Use. equipment_transfer_log TR-00130 posted May 22, 2026; inbound 2026-05-28 approval APR-00130. hr_employee_status lists Naomi Berger (E0064) as Transferred. PO-2023-0023 covers under-threshold MD-00130; no FAR row expected under ITAM-001 §7. | L134: 2026-08-05 | M134: =IFERROR(XLOOKUP(A134,'Source Inventory'!$A$5:$A$200,'Source Inventory'!$H$5:$H$200),"") | N134: =IF(V134="","",V134) | O134: =IFERROR(XLOOKUP(A134,'Source Ledger'!$B$5:$B$200,'Source Ledger'!$A$5:$A$200),"") | P134: =IFERROR(XLOOKUP(A134,'Source Ledger'!$B$5:$B$200,'Source Ledger'!$D$5:$D$200),"") | Q134: High | R134: EX-0161 | S134: =IF(OR(R134="",R134=0),"No","Yes") | T134: =IFERROR(XLOOKUP(A134,'Source Ledger'!$B$5:$B$200,'Source Ledger'!$E$5:$E$200),"") | U134: =IFERROR(XLOOKUP(A134,'Source Ledger'!$B$5:$B$200,'Source Ledger'!$H$5:$H$200),"") | V134: =IFERROR(XLOOKUP(A134,'Source Ledger'!$B$5:$B$200,'Source Ledger'!$G$5:$G$200),"") | W134: =IF(OR(M134="",T134=""),"",T134-M134) | X134: =IF(V134="","No","Yes")
A135: MD-00131 | B135: =IFERROR(XLOOKUP(A135,'Source Inventory'!$A$5:$A$200,'Source Inventory'!$B$5:$B$200),"") | C135: =IFERROR(XLOOKUP(A135,'Source Inventory'!$A$5:$A$200,'Source Inventory'!$C$5:$C$200),"") | D135: =IFERROR(XLOOKUP(A135,'Source Inventory'!$A$5:$A$200,'Source Inventory'!$D$5:$D$200),"") | E135: =IFERROR(XLOOKUP(A135,'Source Inventory'!$A$5:$A$200,'Source Inventory'!$E$5:$E$200),"") | F135: =IFERROR(XLOOKUP(A135,'Source Inventory'!$A$5:$A$200,'Source Inventory'!$F$5:$F$200),"") | G135: =IFERROR(XLOOKUP(A135,'Source Inventory'!$A$5:$A$200,'Source Inventory'!$G$5:$G$200),"") | H135: E0065 | I135: Chicago | J135: In Use | K135: Files reviewed for MD-00131: MacBook Pro 14, basis $1175, operating site Chicago, status In Use. equipment_transfer_log TR-00131 posted Jun 26, 2026; inbound 2026-06-28 approval APR-00131. hr_employee_status lists Felix Moreno (E0065) as Transferred. PO-2023-0023 covers under-threshold MD-00131; no FAR row expected under ITAM-001 §7. | L135: 2026-08-05 | M135: =IFERROR(XLOOKUP(A135,'Source Inventory'!$A$5:$A$200,'Source Inventory'!$H$5:$H$200),"") | N135: =IF(V135="","",V135) | O135: =IFERROR(XLOOKUP(A135,'Source Ledger'!$B$5:$B$200,'Source Ledger'!$A$5:$A$200),"") | P135: =IFERROR(XLOOKUP(A135,'Source Ledger'!$B$5:$B$200,'Source Ledger'!$D$5:$D$200),"") | Q135: High | R135: EX-0162 | S135: =IF(OR(R135="",R135=0),"No","Yes") | T135: =IFERROR(XLOOKUP(A135,'Source Ledger'!$B$5:$B$200,'Source Ledger'!$E$5:$E$200),"") | U135: =IFERROR(XLOOKUP(A135,'Source Ledger'!$B$5:$B$200,'Source Ledger'!$H$5:$H$200),"") | V135: =IFERROR(XLOOKUP(A135,'Source Ledger'!$B$5:$B$200,'Source Ledger'!$G$5:$G$200),"") | W135: =IF(OR(M135="",T135=""),"",T135-M135) | X135: =IF(V135="","No","Yes")
A136: MD-00132 | B136: =IFERROR(XLOOKUP(A136,'Source Inventory'!$A$5:$A$200,'Source Inventory'!$B$5:$B$200),"") | C136: =IFERROR(XLOOKUP(A136,'Source Inventory'!$A$5:$A$200,'Source Inventory'!$C$5:$C$200),"") | D136: =IFERROR(XLOOKUP(A136,'Source Inventory'!$A$5:$A$200,'Source Inventory'!$D$5:$D$200),"") | E136: =IFERROR(XLOOKUP(A136,'Source Inventory'!$A$5:$A$200,'Source Inventory'!$E$5:$E$200),"") | F136: =IFERROR(XLOOKUP(A136,'Source Inventory'!$A$5:$A$200,'Source Inventory'!$F$5:$F$200),"") | G136: =IFERROR(XLOOKUP(A136,'Source Inventory'!$A$5:$A$200,'Source Inventory'!$G$5:$G$200),"") | H136: E0066 | I136: Dallas | J136: In Use | K136: Files reviewed for MD-00132: Dell Latitude 7440, basis $6470, operating site Dallas, status In Use. equipment_transfer_log TR-00132 posted Jan 30, 2026; inbound 2026-01-31 approval APR-00132. hr_employee_status lists Sharon Quinlan (E0066) as Transferred. RN-0132 under-threshold claim rejected; $6,470 exceeds gate with no FA row. | L136: 2026-08-05 | M136: =IFERROR(XLOOKUP(A136,'Source Inventory'!$A$5:$A$200,'Source Inventory'!$H$5:$H$200),"") | N136: =IF(V136="","",V136) | O136: =IFERROR(XLOOKUP(A136,'Source Ledger'!$B$5:$B$200,'Source Ledger'!$A$5:$A$200),"") | P136: =IFERROR(XLOOKUP(A136,'Source Ledger'!$B$5:$B$200,'Source Ledger'!$D$5:$D$200),"") | Q136: High | R136: EX-0163 | S136: =IF(OR(R136="",R136=0),"No","Yes") | T136: =IFERROR(XLOOKUP(A136,'Source Ledger'!$B$5:$B$200,'Source Ledger'!$E$5:$E$200),"") | U136: =IFERROR(XLOOKUP(A136,'Source Ledger'!$B$5:$B$200,'Source Ledger'!$H$5:$H$200),"") | V136: =IFERROR(XLOOKUP(A136,'Source Ledger'!$B$5:$B$200,'Source Ledger'!$G$5:$G$200),"") | W136: =IF(OR(M136="",T136=""),"",T136-M136) | X136: =IF(V136="","No","Yes")

Sheet Exception Register
A1: Exception Register
A2: Each exception cites exact related records. Image leads are labeled as leads, not clearance. Flags duplicate serial MD-LA-050021 across MD-00021 and MD-00025, and duplicate serial MD-NE-050088 across MD-00088 and MD-00092.
A4: Exception ID | B4: Type | C4: Severity | D4: Asset Tag | E4: Serial Number | F4: Related Record(s) | G4: Financial Exposure | H4: Required Action | I4: Owner by Role | J4: Resolution Deadline | K4: Status | L4: Evidence Assessment | M4: Certification Impact
A5: EX-0001 | B5: Inventory-to-Ledger Difference | C5: High | D5: MD-00017 | E5: MD-LA-050017 | F5: Ledger:FA-000017; PO:PO-2025-0004; RegisterCost:1985.0; LedgerCost:2070.0; OverDepreciation:90.0 | G5: 85 | H5: Finance Controller: clear FA-000017 over-depreciation and cost basis on MD-00017 before relying on NBV. | I5: Finance Controller | J5: 2026-08-21 | K5: Open | L5: Pulled PO-2025-0004 and FA-000017 for MD-00017: register $1985.0 vs ledger $2070.0. FA-000017 accumulated depreciation $2160 exceeds acquisition $2070 by $90. | M5: Requires remediation
A6: EX-0002 | B6: Duplicate Serial Number | C6: High | D6: MD-00021 | E6: MD-LA-050021 | F6: Duplicate serial MD-LA-050021 across MD-00021 and MD-00025; Serial:MD-LA-050021; AlsoTagged:MD-00021,MD-00025 | G6: 124.52 | H6: Bench-validate and retag duplicate serial MD-LA-050021 involving MD-00021 (EX-0002). | I6: IT Asset Specialist | J6: 2026-08-18 | K6: Open | L6: Serial MD-LA-050021 appears on MD-00021 and MD-00021,MD-00025; bench validation required (EX-0002). | M6: Requires remediation
A7: EX-0003 | B7: Closed Location Assignment | C7: Medium | D7: MD-00025 | E7: MD-LA-050021 | F7: RegisterLocation:Denver - Closed; Transfer:TR-00025; HRLocation:Chicago | G7: 0 | H7: Retire the closed-office code on MD-00025 and post Chicago as the working site; cite TR-00025 in the update (EX-0003) | I7: IT Asset Specialist | J7: 2026-08-19 | K7: Open | L7: Site code Denver - Closed on MD-00025 was retired during consolidation but remains on the asset row. equipment_transfer_log TR-00025 points to Chicago. operating footprint for MD-00025 is Chicago, not Denver - Closed. finding EX-0003. | M7: Requires remediation
A8: EX-0004 | B8: Duplicate Serial Number | C8: High | D8: MD-00025 | E8: MD-LA-050021 | F8: Duplicate serial MD-LA-050021 across MD-00021 and MD-00025; Serial:MD-LA-050021; AlsoTagged:MD-00021,MD-00025 | G8: 0 | H8: Bench-validate and retag duplicate serial MD-LA-050021 involving MD-00025 (EX-0004). | I8: IT Asset Specialist | J8: 2026-08-18 | K8: Open | L8: Serial MD-LA-050021 appears on MD-00025 and MD-00021,MD-00025; bench validation required (EX-0004). | M8: Requires remediation
A9: EX-0005 | B9: Closed Location Assignment | C9: Medium | D9: MD-00026 | E9: MD-MO-050026 | F9: RegisterLocation:Chicago - Closed; Transfer:TR-00026; HRLocation:Dallas | G9: 382.34 | H9: Replace shuttered site Chicago - Closed on MD-00026 with Dallas on the register; cite TR-00026 in the update (EX-0005) | I9: IT Asset Specialist | J9: 2026-08-19 | K9: Open | L9: equipment_transfer_log TR-00026 points to Dallas. operating footprint for MD-00026 is Dallas, not Chicago - Closed. finding EX-0005. Site code Chicago - Closed on MD-00026 was retired during consolidation but remains on the asset row. | M9: Requires remediation
A10: EX-0006 | B10: Closed Location Assignment | C10: Medium | D10: MD-00027 | E10: MD-MO-050027 | F10: RegisterLocation:Denver - Closed; Transfer:TR-00027; HRLocation:Denver | G10: 672.21 | H10: Correct the stale location on MD-00027 (Denver - Closed → Denver); cite TR-00027 in the update (EX-0006) | I10: IT Asset Specialist | J10: 2026-08-19 | K10: Open | L10: The register extract for MD-00027 carries location Denver - Closed after that floor was vacated. operating footprint for MD-00027 is Denver, not Denver - Closed. equipment_transfer_log TR-00027 points to Denver. finding EX-0006. | M10: Requires remediation
A11: EX-0007 | B11: Closed Location Assignment | C11: Medium | D11: MD-00028 | E11: MD-NE-050028 | F11: RegisterLocation:Chicago - Closed; Transfer:TR-00028; HRLocation:New York | G11: 914.09 | H11: Replace shuttered site Chicago - Closed on MD-00028 with New York on the register; cite TR-00028 in the update (EX-0007) | I11: IT Asset Specialist | J11: 2026-08-19 | K11: Open | L11: equipment_transfer_log TR-00028 points to New York. finding EX-0007. operating footprint for MD-00028 is New York, not Chicago - Closed. Inventory row MD-00028 (serial MD-NE-050028) still lists site Chicago - Closed. | M11: Requires remediation
A12: EX-0008 | B12: Closed Location Assignment | C12: Medium | D12: MD-00029 | E12: MD-LA-050029 | F12: RegisterLocation:Denver - Closed; Transfer:TR-00029; HRLocation:Seattle | G12: 0 | H12: Correct the stale location on MD-00029 (Denver - Closed → Seattle); cite TR-00029 in the update (EX-0008) | I12: IT Asset Specialist | J12: 2026-08-19 | K12: Open | L12: finding EX-0008. Site code Denver - Closed on MD-00029 was retired during consolidation but remains on the asset row. equipment_transfer_log TR-00029 points to Seattle. operating footprint for MD-00029 is Seattle, not Denver - Closed. | M12: Requires remediation
A13: EX-0009 | B13: Closed Location Assignment | C13: Medium | D13: MD-00030 | E13: MD-MO-050030 | F13: RegisterLocation:Chicago - Closed; Transfer:TR-00030; HRLocation:Atlanta | G13: 355.14 | H13: Retire the closed-office code on MD-00030 and post Atlanta as the working site; cite TR-00030 in the update (EX-0009) | I13: IT Asset Specialist | J13: 2026-08-19 | K13: Open | L13: equipment_transfer_log TR-00030 points to Atlanta. operating footprint for MD-00030 is Atlanta, not Chicago - Closed. finding EX-0009. Site code Chicago - Closed on MD-00030 was retired during consolidation but remains on the asset row. | M13: Requires remediation
A14: EX-0010 | B14: Closed Location Assignment | C14: Medium | D14: MD-00031 | E14: MD-MO-050031 | F14: RegisterLocation:Denver - Closed; Transfer:TR-00031; HRLocation:Chicago | G14: 722.59 | H14: Replace shuttered site Denver - Closed on MD-00031 with Chicago on the register; cite TR-00031 in the update (EX-0010) | I14: IT Asset Specialist | J14: 2026-08-19 | K14: Open | L14: Site code Denver - Closed on MD-00031 was retired during consolidation but remains on the asset row. operating footprint for MD-00031 is Chicago, not Denver - Closed. finding EX-0010. equipment_transfer_log TR-00031 points to Chicago. | M14: Requires remediation
A15: EX-0011 | B15: Closed Location Assignment | C15: Medium | D15: MD-00032 | E15: MD-NE-050032 | F15: RegisterLocation:Chicago - Closed; Transfer:TR-00032; HRLocation:Dallas | G15: 1384.3 | H15: Correct the stale location on MD-00032 (Chicago - Closed → Dallas); cite TR-00032 in the update (EX-0011) | I15: IT Asset Specialist | J15: 2026-08-19 | K15: Open | L15: The register extract for MD-00032 carries location Chicago - Closed after that floor was vacated. equipment_transfer_log TR-00032 points to Dallas. operating footprint for MD-00032 is Dallas, not Chicago - Closed. finding EX-0011. | M15: Requires remediation
A16: EX-0012 | B16: Closed Location Assignment | C16: Medium | D16: MD-00033 | E16: MD-LA-050033 | F16: RegisterLocation:Denver - Closed; Transfer:TR-00033; HRLocation:Denver | G16: 116.93 | H16: Replace shuttered site Denver - Closed on MD-00033 with Denver on the register; cite TR-00033 in the update (EX-0012) | I16: IT Asset Specialist | J16: 2026-08-19 | K16: Open | L16: operating footprint for MD-00033 is Denver, not Denver - Closed. equipment_transfer_log TR-00033 points to Denver. Inventory row MD-00033 (serial MD-LA-050033) still lists site Denver - Closed. finding EX-0012. | M16: Requires remediation
... A167: EX-0163 | B167: Inventory-to-Ledger Difference | C167: Critical | D167: MD-00132 | E167: MD-NE-050132 | F167: PO:PO-2023-0022; RegisterCost:6470.0; Policy:ITAM-001 §7 threshold $2500; capitalization_approved on PO does not excuse missing FA row for qualifying asset; regional note RN-0132 is non-authoritative | G167: 6470 | H167: Capitalize MD-00132 or obtain approved write-off; reject RN-0132 claim (EX-0163). | I167: Finance Controller | J167: 2026-08-15 | K167: Open | L167: MD-00132 acquisition $6470.0 exceeds the $2,500 capitalization gate with no FA row; RN-0132 under-threshold claim rejected (EX-0163). | M167: Blocks certification
A169: Total Financial Exposure | G169: 0 | H169: IT Asset Specialist: remediate Total Financial Exposure on None per cited records. | L169: Reviewed cited records for None under Total Financial Exposure: .

Sheet Custody Chain
A1: Custody Chain - High-Risk and Unresolved Assets
A2: Confirmed Fact vs Technician Claim vs Unresolved Assumption. Includes policy figure and dock image leads where applicable.
A4: Asset Tag | B4: Event Date | C4: Event Type | D4: From Party | E4: To Party | F4: Location | G4: Record Reference | H4: Fact Type | I4: Detail
A5: MD-00017 | B5: 2023-06-18 | C5: Purchase | D5: Vendor | E5: Central Receiving | F5: Atlanta Warehouse | G5: PO:PO-2025-0004 | H5: Confirmed Fact | I5: Acquisition MD-00017: Samsung ViewFinity S8, $1985, PO PO-2025-0004.
A6: MD-00017 | B6: 2026-08-09 | C6: Policy Control Figure | D6: ITAM-001 | G6: ITAM_control_matrix.png; IT_asset_management_policy.pdf | H6: Confirmed Fact | I6: Matrix return criteria applied to MD-00017; figure is reference, not inbound proof for chain row 6.
A7: MD-00017 | B7: 2026-06-18 | C7: Assignment/Transfer | D7: Central Receiving | E7: E0017 | F7: Seattle | G7: Transfer:TR-00017; Approval:APR-00017 | H7: Confirmed Fact | I7: Transfer TR-00017 for MD-00017: posted 06/17/2026, inbound Jun 19, 2026, APR APR-00017.
A8: MD-00017 | B8: 2026-08-09 | C8: Reconciliation Conclusion | D8: Evidence review | E8: E0017 | F8: Seattle | G8: HR:E0017:Active; Transfer:TR-00017; Approval:APR-00017; PO:PO-2025-0004; Ledger:FA-000017; PolicyFigure:ITAM_control_matrix.png | H8: Confirmed Fact | I8: Verified outcome MD-00017: In Use / Seattle (High). EX-0001.
A9: MD-00021 | B9: 2023-10-22 | C9: Purchase | D9: Vendor | E9: Central Receiving | F9: Atlanta Warehouse | G9: PO:PO-2022-0005 | H9: Confirmed Fact | I9: Acquisition MD-00021: Samsung ViewFinity S8, $1850, PO PO-2022-0005.
A10: MD-00021 | B10: 2026-04-22 | C10: Assignment/Transfer | D10: Central Receiving | E10: E0021 | F10: Denver | G10: Transfer:TR-00021; Approval:APR-00021 | H10: Confirmed Fact | I10: Transfer TR-00021 for MD-00021: posted 2026-05-02, inbound 05/03/2026, APR APR-00021.
A11: MD-00021 | B11: 2026-08-09 | C11: Policy Control Figure | D11: ITAM-001 | G11: ITAM_control_matrix.png; IT_asset_management_policy.pdf | H11: Confirmed Fact | I11: Policy figure sets transfer evidence expectations for MD-00021; chain row 11 remains the audit trail.
A12: MD-00021 | B12: 2026-08-09 | C12: Reconciliation Conclusion | D12: Evidence review | E12: E0021 | F12: Denver | G12: HR:E0021:Active; Transfer:TR-00021; Approval:APR-00021; PO:PO-2022-0005; Ledger:FA-000021; PolicyFigure:ITAM_control_matrix.png | H12: Confirmed Fact | I12: Verified outcome MD-00021: In Use / Denver (Medium). EX-0002.
A13: MD-00025 | B13: 2023-02-02 | C13: Purchase | D13: Vendor | E13: Central Receiving | F13: Atlanta Warehouse | G13: PO:PO-2022-0005 | H13: Confirmed Fact | I13: Vendor shipment for MD-00025 (LG UltraFine 27MD5KL) recorded at $2030 on PO-2022-0005.
A14: MD-00025 | B14: 2026-02-02 | C14: Assignment/Transfer | D14: Central Receiving | E14: E0025 | F14: Chicago | G14: Transfer:TR-00025; Approval:APR-00025 | H14: Confirmed Fact | I14: Transfer TR-00025 for MD-00025: posted 01/21/2026, inbound Jan 22, 2026, APR APR-00025.
A15: MD-00025 | B15: 2026-08-05 | C15: Regional IT Note Lead | D15: Regional IT | F15: Denver - Closed | G15: regional_IT_notes.docx | H15: Technician Claim | I15: regional_IT_notes.docx checked for MD-00025; no corroborated RN entry found.
A16: MD-00025 | B16: 2026-08-09 | C16: Policy Control Figure | D16: ITAM-001 | G16: ITAM_control_matrix.png; IT_asset_management_policy.pdf | H16: Confirmed Fact | I16: Policy figure sets assignment evidence expectations for MD-00025; chain row 16 remains the audit trail.
A17: MD-00025 | B17: 2026-08-09 | C17: Reconciliation Conclusion | D17: Evidence review | E17: E0025 | F17: Chicago | G17: HR:E0025:Active; Transfer:TR-00025; Approval:APR-00025; PO:PO-2022-0005; Ledger:FA-000025; PolicyFigure:ITAM_control_matrix.png | H17: Confirmed Fact | I17: Final status on MD-00025 — In Use, site Chicago, Medium. EX-0003, EX-0004.
A18: MD-00034 | B18: 2024-11-11 | C18: Purchase | D18: Vendor | E18: Central Receiving | F18: Atlanta Warehouse | G18: PO:PO-2024-0007 | H18: Confirmed Fact | I18: Acquisition MD-00034: LG UltraFine 27MD5KL, $790, PO PO-2024-0007.
A19: MD-00034 | B19: 2026-05-11 | C19: Assignment/Transfer | D19: Central Receiving | E19: E0034 | F19: New York | G19: Transfer:TR-00034; Approval:APR-00034 | H19: Confirmed Fact | I19: Transfer TR-00034 for MD-00034: posted May 22, 2026, inbound 2026-05-22, APR APR-00034.
A20: MD-00034 | B20: 2026-08-05 | C20: Regional IT Note Lead | D20: Regional IT | F20: Chicago - Closed | G20: regional_IT_notes.docx | H20: Technician Claim | I20: regional_IT_notes.docx checked for MD-00034; no corroborated RN entry found.
A21: MD-00034 | B21: 2026-08-09 | C21: Policy Control Figure | D21: ITAM-001 | G21: ITAM_control_matrix.png; IT_asset_management_policy.pdf | H21: Confirmed Fact | I21: ITAM_control_matrix.png Appendix A transfer row consulted while tracing MD-00034; transactional proof stays with chain row 21.
A22: MD-00034 | B22: 2026-08-09 | C22: Reconciliation Conclusion | D22: Evidence review | E22: E0034 | F22: New York | G22: HR:E0034:Active; Transfer:TR-00034; Approval:APR-00034; PO:PO-2024-0007; Ledger:FA-000034; PolicyFigure:ITAM_control_matrix.png | H22: Confirmed Fact | I22: Verified outcome MD-00034: In Use / New York (High). EX-0013, EX-0014.
A23: MD-00051 | B23: 2025-04-04 | C23: Purchase | D23: Vendor | E23: Central Receiving | F23: Atlanta Warehouse | G23: PO:PO-2023-0010 | H23: Confirmed Fact | I23: PO PO-2023-0010 covers MD-00051 (Samsung Galaxy S24) for $1040.
A24: MD-00051 | B24: 2026-04-04 | C24: Assignment/Transfer | D24: Central Receiving | E24: IT Stock | F24: Denver | G24: Transfer:TR-00051; Approval:APR-00051 | H24: Confirmed Fact | I24: Transfer TR-00051 for MD-00051: posted 03/31/2026, inbound Mar 31, 2026, APR APR-00051.
A25: MD-00051 | B25: 2026-08-05 | C25: Regional IT Note Lead | D25: Regional IT | F25: Denver - Closed | G25: regional_IT_notes.docx | H25: Technician Claim | I25: regional_IT_notes.docx checked for MD-00051; no corroborated RN entry found.
A26: MD-00051 | B26: 2026-08-09 | C26: Policy Control Figure | D26: ITAM-001 | G26: ITAM_control_matrix.png; IT_asset_management_policy.pdf | H26: Confirmed Fact | I26: Read IT_asset_management_policy.pdf §4–§9 with the matrix assignment line for MD-00051; cite chain row 26.
A27: MD-00051 | B27: 2026-08-09 | C27: Reconciliation Conclusion | D27: Evidence review | E27: IT Stock | F27: Denver | G27: Transfer:TR-00051; Approval:APR-00051; Received:2026-04-05; PO:PO-2023-0010; Ledger:FA-000051; PolicyFigure:ITAM_control_matrix.png | H27: Confirmed Fact | I27: Verified outcome MD-00051: Available / Denver (High). EX-0031, EX-0032.
A28: MD-00058 | B28: 2024-11-11 | C28: Purchase | D28: Vendor | E28: Central Receiving | F28: Atlanta Warehouse | G28: PO:PO-2024-0011 | H28: Confirmed Fact | I28: Acquisition MD-00058: Google Pixel 8, $610, PO PO-2024-0011.
A29: MD-00058 | B29: 2026-05-11 | C29: Assignment/Transfer | D29: Central Receiving | E29: Regional IT | F29: New York | G29: Transfer:TR-00058; Approval:missing | H29: Confirmed Fact | I29: Transfer TR-00058 for MD-00058: posted 05/22/2026, inbound May 23, 2026, APR missing.
A30: MD-00058 | B30: 2026-05-24 | C30: Offboarding Ticket | D30: E0071 | E30: IT Service Desk | G30: Ticket:OFF-00058; Status:Closed | H30: Confirmed Fact | I30: Service desk OFF-00058: Closed; return required Yes; due 2026-07-15. Ticket alone does not dock MD-00058.
A31: MD-00058 | B31: 2026-05-24 | C31: Technician Comment | D31: Service Desk | G31: Ticket:OFF-00058 | H31: Technician Claim | I31: Opened return kit after HR closeout. Label printed, waiting on the person. Ref MD-00058.
A32: MD-00058 | B32: 2026-08-05 | C32: Regional IT Note Lead | D32: Regional IT | F32: Chicago - Closed | G32: regional_IT_notes.docx | H32: Technician Claim | I32: regional_IT_notes.docx checked for MD-00058; no corroborated RN entry found.
A33: MD-00058 | B33: 2026-08-09 | C33: Policy Control Figure | D33: ITAM-001 | G33: ITAM_control_matrix.png; IT_asset_management_policy.pdf | H33: Confirmed Fact | I33: Policy figure sets assignment evidence expectations for MD-00058; chain row 33 remains the audit trail.
A34: MD-00058 | B34: 2026-08-09 | C34: Reconciliation Conclusion | D34: Evidence review | E34: Regional IT | F34: New York | G34: Transfer:TR-00058; Received:2026-05-12; Ticket:OFF-00058; PO:PO-2024-0011; Ledger:FA-000058; PolicyFigure:ITAM_control_matrix.png | H34: Confirmed Fact | I34: Custody conclusion for MD-00058: Pending Redeployment at New York (Medium). EX-0039, EX-0040, EX-0041.
A35: MD-00059 | B35: 2025-12-12 | C35: Purchase | D35: Vendor | E35: Central Receiving | F35: Atlanta Warehouse | G35: PO:PO-2024-0011 | H35: Confirmed Fact | I35: Acquisition MD-00059: Samsung Galaxy S23 FE, $1085, PO PO-2024-0011.
A36: MD-00059 | B36: 2026-06-12 | C36: Assignment/Transfer | D36: Central Receiving | E36: Regional IT | F36: Seattle | G36: Transfer:TR-00059; Approval:missing | H36: Confirmed Fact | I36: Transfer TR-00059 for MD-00059: posted Jun 26, 2026, inbound 2026-06-26, APR missing.
A37: MD-00059 | B37: 2026-06-01 | C37: Offboarding Ticket | D37: E0072 | E37: IT Service Desk | G37: Ticket:OFF-00059; Status:Closed | H37: Confirmed Fact | I37: Service desk OFF-00059: Closed; return required Yes; due Jul 15, 2026. Ticket alone does not dock MD-00059.
A38: MD-00059 | B38: 2026-06-01 | C38: Technician Comment | D38: Service Desk | G38: Ticket:OFF-00059 | H38: Technician Claim | I38: Mailed prepaid pouch 6/25. No SCAN-86 yet. Ref MD-00059.
A39: MD-00059 | B39: 2026-08-05 | C39: Regional IT Note Lead | D39: Regional IT | F39: Denver - Closed | G39: regional_IT_notes.docx | H39: Technician Claim | I39: regional_IT_notes.docx checked for MD-00059; no corroborated RN entry found.
A40: MD-00059 | B40: 2026-08-09 | C40: Policy Control Figure | D40: ITAM-001 | G40: ITAM_control_matrix.png; IT_asset_management_policy.pdf | H40: Confirmed Fact | I40: Read IT_asset_management_policy.pdf §4–§9 with the matrix financial line for MD-00059; cite chain row 40.
A41: MD-00059 | B41: 2026-08-09 | C41: Reconciliation Conclusion | D41: Evidence review | E41: Regional IT | F41: Seattle | G41: Transfer:TR-00059; Received:2026-06-13; Ticket:OFF-00059; PO:PO-2024-0011; Ledger:FA-000059; PolicyFigure:ITAM_control_matrix.png | H41: Confirmed Fact | I41: Custody conclusion for MD-00059: Pending Redeployment at Seattle (Medium). EX-0042, EX-0043, EX-0044.
A42: MD-00060 | B42: 2022-01-13 | C42: Purchase | D42: Vendor | E42: Central Receiving | F42: Atlanta Warehouse | G42: PO:PO-2024-0011 | H42: Confirmed Fact | I42: Vendor shipment for MD-00060 (Samsung Galaxy S24) recorded at $6380 on PO-2024-0011.
A43: MD-00060 | B43: 2026-01-13 | C43: Assignment/Transfer | D43: Central Receiving | E43: Regional IT | F43: Atlanta | G43: Transfer:TR-00060; Approval:APR-00060 | H43: Confirmed Fact | I43: Transfer TR-00060 for MD-00060: posted 2026-01-30, inbound 02/02/2026, APR APR-00060.
A44: MD-00060 | B44: 2026-05-02 | C44: Offboarding Ticket | D44: E0073 | E44: IT Service Desk | G44: Ticket:OFF-00060; Status:Closed | H44: Confirmed Fact | I44: Service desk OFF-00060: Closed; return required Yes; due 07/15/2026. Ticket alone does not dock MD-00060.
A45: MD-00060 | B45: 2026-05-02 | C45: Technician Comment | D45: Service Desk | G45: Ticket:OFF-00060 | H45: Technician Claim | I45: User said they'd drop at UPS on the way out. Ticket remains open until dock confirms. Ref MD-00060.
A46: MD-00060 | B46: 2026-08-05 | C46: Regional IT Note Lead | D46: Regional IT | F46: Chicago - Closed | G46: regional_IT_notes.docx | H46: Technician Claim | I46: regional_IT_notes.docx checked for MD-00060; no corroborated RN entry found.
A47: MD-00060 | B47: 2026-08-09 | C47: Policy Control Figure | D47: ITAM-001 | G47: ITAM_control_matrix.png; IT_asset_management_policy.pdf | H47: Confirmed Fact | I47: Read IT_asset_management_policy.pdf §4–§9 with the matrix disposal line for MD-00060; cite chain row 47.
A48: MD-00060 | B48: 2026-08-09 | C48: Reconciliation Conclusion | D48: Evidence review | E48: Regional IT | F48: Atlanta | G48: Transfer:TR-00060; Approval:APR-00060; Received:2026-01-14; Ticket:OFF-00060; PO:PO-2024-0011; Ledger:FA-000060; PolicyFigure:ITAM_control_matrix.png | H48: Confirmed Fact | I48: Chain ends with MD-00060 as Pending Redeployment in Atlanta; confidence High. EX-0045, EX-0046.
A49: MD-00061 | B49: 2023-02-14 | C49: Purchase | D49: Vendor | E49: Central Receiving | F49: Atlanta Warehouse | G49: PO:PO-2025-0012 | H49: Confirmed Fact | I49: Acquisition MD-00061: iPhone 15, $2075, PO PO-2025-0012.
A50: MD-00061 | B50: 2026-02-14 | C50: Assignment/Transfer | D50: Central Receiving | E50: Regional IT | F50: Chicago | G50: Transfer:TR-00061; Approval:APR-00061 | H50: Confirmed Fact | I50: Transfer TR-00061 for MD-00061: posted 02/02/2026, inbound Feb 03, 2026, APR APR-00061.
A51: MD-00061 | B51: 2026-06-03 | C51: Offboarding Ticket | D51: E0074 | E51: IT Service Desk | G51: Ticket:OFF-00061; Status:Closed | H51: Confirmed Fact | I51: Service desk OFF-00061: Closed; return required Yes; due 2026-07-15. Ticket alone does not dock MD-00061.
A52: MD-00061 | B52: 2026-06-03 | C52: Technician Comment | D52: Service Desk | G52: Ticket:OFF-00061 | H52: Technician Claim | I52: Looping with site ops — laptop still showing assigned post-term. Ref MD-00061.
A53: MD-00061 | B53: 2026-08-05 | C53: Regional IT Note Lead | D53: Regional IT | F53: Denver - Closed | G53: regional_IT_notes.docx | H53: Technician Claim | I53: regional_IT_notes.docx checked for MD-00061; no corroborated RN entry found.
A54: MD-00061 | B54: 2026-08-09 | C54: Policy Control Figure | D54: ITAM-001 | G54: ITAM_control_matrix.png; IT_asset_management_policy.pdf | H54: Confirmed Fact | I54: Policy figure sets return evidence expectations for MD-00061; chain row 54 remains the audit trail.
A55: MD-00061 | B55: 2026-08-09 | C55: Reconciliation Conclusion | D55: Evidence review | E55: Regional IT | F55: Chicago | G55: Transfer:TR-00061; Approval:APR-00061; Received:2026-02-15; Ticket:OFF-00061; PO:PO-2025-0012; Ledger:FA-000061; PolicyFigure:ITAM_control_matrix.png | H55: Confirmed Fact | I55: Chain ends with MD-00061 as Pending Redeployment in Chicago; confidence High. EX-0047, EX-0048.
A56: MD-00062 | B56: 2024-03-15 | C56: Purchase | D56: Vendor | E56: Central Receiving | F56: Atlanta Warehouse | G56: PO:PO-2025-0012 | H56: Confirmed Fact | I56: PO PO-2025-0012 covers MD-00062 (Google Pixel 8) for $790.
A57: MD-00062 | B57: 2026-03-15 | C57: Assignment/Transfer | D57: Central Receiving | E57: Regional IT | F57: Dallas | G57: Transfer:TR-00062; Approval:APR-00062 | H57: Confirmed Fact | I57: Transfer TR-00062 for MD-00062: posted Mar 07, 2026, inbound 2026-03-07, APR APR-00062.
A58: MD-00062 | B58: 2026-05-04 | C58: Offboarding Ticket | D58: E0075 | E58: IT Service Desk | G58: Ticket:OFF-00062; Status:Closed | H58: Confirmed Fact | I58: Service desk OFF-00062: Closed; return required Yes; due Jul 15, 2026. Ticket alone does not dock MD-00062.
A59: MD-00062 | B59: 2026-05-04 | C59: Technician Comment | D59: Service Desk | G59: Ticket:OFF-00062 | H59: Technician Claim | I59: Return SLA missed; reminder sent to personal email on file. Ref MD-00062.
A60: MD-00062 | B60: 2026-08-05 | C60: Regional IT Note Lead | D60: Regional IT | F60: Chicago - Closed | G60: regional_IT_notes.docx | H60: Technician Claim | I60: regional_IT_notes.docx checked for MD-00062; no corroborated RN entry found.
A61: MD-00062 | B61: 2026-08-09 | C61: Policy Control Figure | D61: ITAM-001 | G61: ITAM_control_matrix.png; IT_asset_management_policy.pdf | H61: Confirmed Fact | I61: ITAM_control_matrix.png Appendix A transfer row consulted while tracing MD-00062; transactional proof stays with chain row 61.
A62: MD-00062 | B62: 2026-08-09 | C62: Reconciliation Conclusion | D62: Evidence review | E62: Regional IT | F62: Dallas | G62: Transfer:TR-00062; Approval:APR-00062; Received:2026-03-16; Ticket:OFF-00062; PO:PO-2025-0012; Ledger:FA-000062; PolicyFigure:ITAM_control_matrix.png | H62: Confirmed Fact | I62: Verified outcome MD-00062: Pending Redeployment / Dallas (High). EX-0049, EX-0050.
A63: MD-00063 | B63: 2025-04-16 | C63: Purchase | D63: Vendor | E63: Central Receiving | F63: Atlanta Warehouse | G63: PO:PO-2025-0012 | H63: Confirmed Fact | I63: Vendor shipment for MD-00063 (Samsung Galaxy S23 FE) recorded at $950 on PO-2025-0012.
A64: MD-00063 | B64: 2026-04-16 | C64: Assignment/Transfer | D64: Central Receiving | E64: Regional IT | F64: Denver | G64: Transfer:TR-00063; Approval:APR-00063 | H64: Confirmed Fact | I64: Transfer TR-00063 for MD-00063: posted 2026-04-12, inbound 04/16/2026, APR APR-00063.
A65: MD-00063 | B65: 2026-06-05 | C65: Offboarding Ticket | D65: E0076 | E65: IT Service Desk | G65: Ticket:OFF-00063; Status:Closed | H65: Confirmed Fact | I65: Service desk OFF-00063: Closed; return required Yes; due 07/15/2026. Ticket alone does not dock MD-00063.
A66: MD-00063 | B66: 2026-06-05 | C66: Technician Comment | D66: Service Desk | G66: Ticket:OFF-00063 | H66: Technician Claim | I66: Created 1Z label. Box not in Atlanta inbound as of last check. Ref MD-00063.
A67: MD-00063 | B67: 2026-08-05 | C67: Regional IT Note Lead | D67: Regional IT | F67: Denver - Closed | G67: regional_IT_notes.docx | H67: Technician Claim | I67: regional_IT_notes.docx checked for MD-00063; no corroborated RN entry found.
A68: MD-00063 | B68: 2026-08-09 | C68: Policy Control Figure | D68: ITAM-001 | G68: ITAM_control_matrix.png; IT_asset_management_policy.pdf | H68: Confirmed Fact | I68: Policy figure sets financial evidence expectations for MD-00063; chain row 68 remains the audit trail.
A69: MD-00063 | B69: 2026-08-09 | C69: Reconciliation Conclusion | D69: Evidence review | E69: Regional IT | F69: Denver | G69: Transfer:TR-00063; Approval:APR-00063; Received:2026-04-17; Ticket:OFF-00063; PO:PO-2025-0012; Ledger:FA-000063; PolicyFigure:ITAM_control_matrix.png | H69: Confirmed Fact | I69: Final status on MD-00063 — Pending Redeployment, site Denver, High. EX-0051, EX-0052.
A70: MD-00064 | B70: 2022-05-17 | C70: Purchase | D70: Vendor | E70: Central Receiving | F70: Atlanta Warehouse | G70: PO:PO-2025-0012 | H70: Confirmed Fact | I70: Vendor shipment for MD-00064 (iPhone 14) recorded at $6245 on PO-2025-0012.
A71: MD-00064 | B71: 2026-05-17 | C71: Assignment/Transfer | D71: Central Receiving | E71: Regional IT | F71: New York | G71: Transfer:TR-00064; Approval:missing | H71: Confirmed Fact | I71: Transfer TR-00064 for MD-00064: posted 05/13/2026, inbound May 14, 2026, APR missing.
A72: MD-00064 | B72: 2026-05-06 | C72: Offboarding Ticket | D72: E0077 | E72: IT Service Desk | G72: Ticket:OFF-00064; Status:Closed | H72: Confirmed Fact | I72: Service desk OFF-00064: Closed; return required Yes; due 2026-07-15. Ticket alone does not dock MD-00064.
A73: MD-00064 | B73: 2026-05-06 | C73: Technician Comment | D73: Service Desk | G73: Ticket:OFF-00064 | H73: Technician Claim | I73: Desk copy of the offboarding packet marked 'ship later.' Ref MD-00064.
A74: MD-00064 | B74: 2026-08-05 | C74: Regional IT Note Lead | D74: Regional IT | F74: Chicago - Closed | G74: regional_IT_notes.docx | H74: Technician Claim | I74: regional_IT_notes.docx checked for MD-00064; no corroborated RN entry found.
A75: MD-00064 | B75: 2026-08-09 | C75: Policy Control Figure | D75: ITAM-001 | G75: ITAM_control_matrix.png; IT_asset_management_policy.pdf | H75: Confirmed Fact | I75: ITAM_control_matrix.png Appendix A disposal row consulted while tracing MD-00064; transactional proof stays with chain row 75.
A76: MD-00064 | B76: 2026-08-09 | C76: Reconciliation Conclusion | D76: Evidence review | E76: Regional IT | F76: New York | G76: Transfer:TR-00064; Received:2026-05-18; Ticket:OFF-00064; PO:PO-2025-0012; Ledger:FA-000064; PolicyFigure:ITAM_control_matrix.png | H76: Confirmed Fact | I76: Verified outcome MD-00064: Pending Redeployment / New York (Medium). EX-0053, EX-0054, EX-0055.
A77: MD-00065 | B77: 2023-06-18 | C77: Purchase | D77: Vendor | E77: Central Receiving | F77: Atlanta Warehouse | G77: PO:PO-2022-0013 | H77: Confirmed Fact | I77: Vendor shipment for MD-00065 (Samsung Galaxy S24) recorded at $1940 on PO-2022-0013.
A78: MD-00065 | B78: 2026-06-18 | C78: Assignment/Transfer | D78: Central Receiving | E78: Regional IT | F78: Seattle | G78: Transfer:TR-00065; Approval:missing | H78: Confirmed Fact | I78: Transfer TR-00065 for MD-00065: posted Jun 17, 2026, inbound 2026-06-23, APR missing.
A79: MD-00065 | B79: 2026-06-07 | C79: Offboarding Ticket | D79: E0078 | E79: IT Service Desk | G79: Ticket:OFF-00065; Status:Closed | H79: Confirmed Fact | I79: Service desk OFF-00065: Closed; return required Yes; due Jul 15, 2026. Ticket alone does not dock MD-00065.
A80: MD-00065 | B80: 2026-06-07 | C80: Technician Comment | D80: Service Desk | G80: Ticket:OFF-00065 | H80: Technician Claim | I80: Manager thought IT already had it. We don't. Ref MD-00065.
A81: MD-00065 | B81: 2026-08-05 | C81: Regional IT Note Lead | D81: Regional IT | F81: Denver - Closed | G81: regional_IT_notes.docx | H81: Technician Claim | I81: regional_IT_notes.docx checked for MD-00065; no corroborated RN entry found.
A82: MD-00065 | B82: 2026-08-09 | C82: Policy Control Figure | D82: ITAM-001 | G82: ITAM_control_matrix.png; IT_asset_management_policy.pdf | H82: Confirmed Fact | I82: Matrix return criteria applied to MD-00065; figure is reference, not inbound proof for chain row 82.
A83: MD-00065 | B83: 2026-08-09 | C83: Reconciliation Conclusion | D83: Evidence review | E83: Regional IT | F83: Seattle | G83: Transfer:TR-00065; Received:2026-06-19; Ticket:OFF-00065; PO:PO-2022-0013; Ledger:FA-000065; PolicyFigure:ITAM_control_matrix.png | H83: Confirmed Fact | I83: Verified outcome MD-00065: Pending Redeployment / Seattle (Medium). EX-0056, EX-0057, EX-0058.
A84: MD-00066 | B84: 2024-07-19 | C84: Purchase | D84: Vendor | E84: Central Receiving | F84: Atlanta Warehouse | G84: PO:PO-2022-0013 | H84: Confirmed Fact | I84: Acquisition MD-00066: iPhone 15, $655, PO PO-2022-0013.
A85: MD-00066 | B85: 2026-01-19 | C85: Assignment/Transfer | D85: Central Receiving | E85: Regional IT | F85: Atlanta | G85: Transfer:TR-00066; Approval:APR-00066 | H85: Confirmed Fact | I85: Transfer TR-00066 for MD-00066: posted 2026-01-22, inbound 01/25/2026, APR APR-00066.
A86: MD-00066 | B86: 2026-05-08 | C86: Offboarding Ticket | D86: E0079 | E86: IT Service Desk | G86: Ticket:OFF-00066; Status:Closed | H86: Confirmed Fact | I86: Service desk OFF-00066: Closed; return required Yes; due 07/15/2026. Ticket alone does not dock MD-00066.
A87: MD-00066 | B87: 2026-05-08 | C87: Technician Comment | D87: Service Desk | G87: Ticket:OFF-00066 | H87: Technician Claim | I87: Pushed a second reminder. Carrier still has no acceptance. Ref MD-00066.
A88: MD-00066 | B88: 2026-08-05 | C88: Regional IT Note Lead | D88: Regional IT | F88: Chicago - Closed | G88: regional_IT_notes.docx | H88: Technician Claim | I88: regional_IT_notes.docx checked for MD-00066; no corroborated RN entry found.
A89: MD-00066 | B89: 2026-08-09 | C89: Policy Control Figure | D89: ITAM-001 | G89: ITAM_control_matrix.png; IT_asset_management_policy.pdf | H89: Confirmed Fact | I89: Policy figure sets assignment evidence expectations for MD-00066; chain row 89 remains the audit trail.
A90: MD-00066 | B90: 2026-08-09 | C90: Reconciliation Conclusion | D90: Evidence review | E90: Regional IT | F90: Atlanta | G90: Transfer:TR-00066; Approval:APR-00066; Received:2026-01-20; Ticket:OFF-00066; PO:PO-2022-0013; Ledger:FA-000066; PolicyFigure:ITAM_control_matrix.png | H90: Confirmed Fact | I90: Custody conclusion for MD-00066: Pending Redeployment at Atlanta (High). EX-0059, EX-0060.
A91: MD-00067 | B91: 2025-08-20 | C91: Purchase | D91: Vendor | E91: Central Receiving | F91: Atlanta Warehouse | G91: PO:PO-2022-0013 | H91: Confirmed Fact | I91: PO PO-2022-0013 covers MD-00067 (Google Pixel 8) for $1130.
A92: MD-00067 | B92: 2026-02-20 | C92: Assignment/Transfer | D92: Central Receiving | E92: Regional IT | F92: Chicago | G92: Transfer:TR-00067; Approval:APR-00067 | H92: Confirmed Fact | I92: Transfer TR-00067 for MD-00067: posted 02/23/2026, inbound Feb 23, 2026, APR APR-00067.
A93: MD-00067 | B93: 2026-06-09 | C93: Offboarding Ticket | D93: E0080 | E93: IT Service Desk | G93: Ticket:OFF-00067; Status:Closed | H93: Confirmed Fact | I93: Service desk OFF-00067: Closed; return required Yes; due 2026-07-15. Ticket alone does not dock MD-00067.
A94: MD-00067 | B94: 2026-06-09 | C94: Technician Comment | D94: Service Desk | G94: Ticket:OFF-00067 | H94: Technician Claim | I94: WFH return; waiting on tracking to leave 'label created.' Ref MD-00067.
A95: MD-00067 | B95: 2026-08-05 | C95: Regional IT Note Lead | D95: Regional IT | F95: Denver - Closed | G95: regional_IT_notes.docx | H95: Technician Claim | I95: regional_IT_notes.docx checked for MD-00067; no corroborated RN entry found.
A96: MD-00067 | B96: 2026-08-09 | C96: Policy Control Figure | D96: ITAM-001 | G96: ITAM_control_matrix.png; IT_asset_management_policy.pdf | H96: Confirmed Fact | I96: Matrix financial criteria applied to MD-00067; figure is reference, not inbound proof for chain row 96.
A97: MD-00067 | B97: 2026-08-09 | C97: Reconciliation Conclusion | D97: Evidence review | E97: Regional IT | F97: Chicago | G97: Transfer:TR-00067; Approval:APR-00067; Received:2026-02-21; Ticket:OFF-00067; PO:PO-2022-0013; Ledger:FA-000067; PolicyFigure:ITAM_control_matrix.png | H97: Confirmed Fact | I97: Custody conclusion for MD-00067: Pending Redeployment at Chicago (High). EX-0061, EX-0062.
A98: MD-00068 | B98: 2022-09-21 | C98: Purchase | D98: Vendor | E98: Central Receiving | F98: Atlanta Warehouse | G98: PO:PO-2022-0013 | H98: Confirmed Fact | I98: PO PO-2022-0013 covers MD-00068 (Samsung Galaxy S23 FE) for $6425.
A99: MD-00068 | B99: 2026-03-21 | C99: Assignment/Transfer | D99: Central Receiving | E99: E0071 | F99: Remote - Former Employee | G99: Transfer:TR-00068; Approval:APR-00068 | H99: Confirmed Fact | I99: Transfer TR-00068 for MD-00068: posted Mar 28, 2026, inbound 2026-04-03, APR APR-00068.
A100: MD-00068 | B100: 2026-05-10 | C100: Offboarding Ticket | D100: E0081 | E100: IT Service Desk | G100: Ticket:OFF-00068; Status:Past Due | H100: Confirmed Fact | I100: Service desk OFF-00068: Past Due; return required Yes; due Jul 15, 2026. Ticket alone does not dock MD-00068.
A101: MD-00068 | B101: 2026-05-10 | C101: Technician Comment | D101: Service Desk | G101: Ticket:OFF-00068 | H101: Technician Claim | I101: Coordinator asked if we can close on the label. No. Ref MD-00068.
...

Sheet Ledger Reconciliation
A1: Inventory-to-Ledger Reconciliation
A2: Book value from fixed-asset ledger when present. No invented balances.
A4: Control Total | B4: Amount
A5: Corrected register - sum of acquisition cost (132 assets) | B5: 332115
A6: Fixed-asset ledger - sum of acquisition cost (129 assets) | B6: 324740
A7: Acquisition cost difference (register − ledger) | B7: 7375
A8: Corrected register - remaining book value (ledger NBV where present; blank if missing) | B8: 61526.6
A9: Ledger - net book value, Active status only | B9: 61526.6
A10: Ledger - net book value, all statuses including Disposed | B10: 61526.6
A11: Assets with matching acquisition cost (register vs ledger) | B11: 123
A12: Assets with acquisition cost mismatch | B12: 6
A13: Assets on inventory missing from ledger | B13: 3
A16: Explanation of remaining differences
A17: 1) Three assets (MD-00130, MD-00131, MD-00132) appear on the operational register and purchase orders but have no fixed-asset ledger row. Combined register acquisition cost = $8,345. MD-00130 ($700) and MD-00131 ($1,175) sit on PO-2023-0023 (capitalization_approved=No) under the $2,500 gate - expected FA absence. MD-00132 ($6,470) is on PO-2023-0022 and is capital-qualifying - Critical gap.
A18: 2) Seven assets have ledger-over-register acquisition cost variances (MD-00017 $85, MD-00034 $140, MD-00051 $210, MD-00068 $55, MD-00085 $195, MD-00102 $120, MD-00119 $165). Combined ledger cost excess = $970. PO approved amounts tie to the inventory lines; Finance should align the FAR. Per section 9 these are High remediation items, not sole Critical blockers. Separately, FA-000017 shows accumulated depreciation $2,160 against acquisition cost $2,070 (over-depreciation $90) with NBV reported as $0.
A19: 3) Eight disposal certificates clear operational status to Disposed with $0 NBV on ledger. Two recycler transfers (MD-00114, MD-00118) lack verified certificates; ledger already shows Disposed/$0 while operational status remains Retired/Pending Disposal. Active ledger NBV otherwise ties to corrected register remaining book value for assets present on both files.
A20: 4) FA-000034 (MD-00034) NBV is $479.88 (acquisition $930.00 minus accumulated depreciation $450.12). Aggregate Active ledger NBV control total is $61,526.60.
A22: Asset-level differences requiring Finance action
A23: Asset Tag | B23: Issue | C23: Register Acquisition Cost | D23: Ledger Acquisition Cost | E23: Cost Difference | F23: Register/Reconciled NBV | G23: Ledger NBV | H23: Explanation
A24: MD-00017 | B24: Acquisition cost mismatch | C24: =IFERROR(XLOOKUP(A24,'Corrected Register'!$A$5:$A$200,'Corrected Register'!$M$5:$M$200),"") | D24: =IFERROR(XLOOKUP(A24,'Corrected Register'!$A$5:$A$200,'Corrected Register'!$T$5:$T$200),"") | E24: =IF(OR(C24="",D24=""),"",D24-C24) | F24: =IFERROR(XLOOKUP(A24,'Corrected Register'!$A$5:$A$200,'Corrected Register'!$N$5:$N$200),"") | G24: =IFERROR(XLOOKUP(A24,'Source Ledger'!$B$5:$B$200,'Source Ledger'!$G$5:$G$200),"") | H24: Ledger FA-000017 cost exceeds register by $85 (validate PO-2025-0004). Accumulated depreciation $2,160 exceeds acquisition cost $2,070 by $90.
A25: MD-00034 | B25: Acquisition cost mismatch; FA-000034 NBV $479.88 (acq $930 − accum dep $450.12) | C25: =IFERROR(XLOOKUP(A25,'Corrected Register'!$A$5:$A$200,'Corrected Register'!$M$5:$M$200),"") | D25: =IFERROR(XLOOKUP(A25,'Corrected Register'!$A$5:$A$200,'Corrected Register'!$T$5:$T$200),"") | E25: =IF(OR(C25="",D25=""),"",D25-C25) | F25: =IFERROR(XLOOKUP(A25,'Corrected Register'!$A$5:$A$200,'Corrected Register'!$N$5:$N$200),"") | G25: =IFERROR(XLOOKUP(A25,'Source Ledger'!$B$5:$B$200,'Source Ledger'!$G$5:$G$200),"") | H25: Ledger FA-000034 cost exceeds register by $140. Validate against PO-2024-0007.
A26: MD-00051 | B26: Acquisition cost mismatch | C26: =IFERROR(XLOOKUP(A26,'Corrected Register'!$A$5:$A$200,'Corrected Register'!$M$5:$M$200),"") | D26: =IFERROR(XLOOKUP(A26,'Corrected Register'!$A$5:$A$200,'Corrected Register'!$T$5:$T$200),"") | E26: =IF(OR(C26="",D26=""),"",D26-C26) | F26: =IFERROR(XLOOKUP(A26,'Corrected Register'!$A$5:$A$200,'Corrected Register'!$N$5:$N$200),"") | G26: =IFERROR(XLOOKUP(A26,'Source Ledger'!$B$5:$B$200,'Source Ledger'!$G$5:$G$200),"") | H26: Ledger FA-000051 cost exceeds register by $210. Validate against PO-2023-0010.
A27: MD-00068 | B27: Acquisition cost mismatch | C27: =IFERROR(XLOOKUP(A27,'Corrected Register'!$A$5:$A$200,'Corrected Register'!$M$5:$M$200),"") | D27: =IFERROR(XLOOKUP(A27,'Corrected Register'!$A$5:$A$200,'Corrected Register'!$T$5:$T$200),"") | E27: =IF(OR(C27="",D27=""),"",D27-C27) | F27: =IFERROR(XLOOKUP(A27,'Corrected Register'!$A$5:$A$200,'Corrected Register'!$N$5:$N$200),"") | G27: =IFERROR(XLOOKUP(A27,'Source Ledger'!$B$5:$B$200,'Source Ledger'!$G$5:$G$200),"") | H27: Ledger FA-000068 cost exceeds register by $55. Validate against PO-2022-0013.
A28: MD-00085 | B28: Acquisition cost mismatch | C28: =IFERROR(XLOOKUP(A28,'Corrected Register'!$A$5:$A$200,'Corrected Register'!$M$5:$M$200),"") | D28: =IFERROR(XLOOKUP(A28,'Corrected Register'!$A$5:$A$200,'Corrected Register'!$T$5:$T$200),"") | E28: =IF(OR(C28="",D28=""),"",D28-C28) | F28: =IFERROR(XLOOKUP(A28,'Corrected Register'!$A$5:$A$200,'Corrected Register'!$N$5:$N$200),"") | G28: =IFERROR(XLOOKUP(A28,'Source Ledger'!$B$5:$B$200,'Source Ledger'!$G$5:$G$200),"") | H28: Ledger FA-000085 cost exceeds register by $195. Validate against PO-2025-0016.
A29: MD-00102 | B29: Acquisition cost mismatch | C29: =IFERROR(XLOOKUP(A29,'Corrected Register'!$A$5:$A$200,'Corrected Register'!$M$5:$M$200),"") | D29: =IFERROR(XLOOKUP(A29,'Corrected Register'!$A$5:$A$200,'Corrected Register'!$T$5:$T$200),"") | E29: =IF(OR(C29="",D29=""),"",D29-C29) | F29: =IFERROR(XLOOKUP(A29,'Corrected Register'!$A$5:$A$200,'Corrected Register'!$N$5:$N$200),"") | G29: =IFERROR(XLOOKUP(A29,'Source Ledger'!$B$5:$B$200,'Source Ledger'!$G$5:$G$200),"") | H29: Ledger FA-000102 cost exceeds register by $120. Validate against PO-2024-0019.
A30: MD-00114 | B30: Ledger disposed without operational disposal evidence | C30: =IFERROR(XLOOKUP(A30,'Corrected Register'!$A$5:$A$200,'Corrected Register'!$M$5:$M$200),"") | D30: =IFERROR(XLOOKUP(A30,'Corrected Register'!$A$5:$A$200,'Corrected Register'!$T$5:$T$200),"") | E30: =IF(OR(C30="",D30=""),"",D30-C30) | F30: =IFERROR(XLOOKUP(A30,'Corrected Register'!$A$5:$A$200,'Corrected Register'!$N$5:$N$200),"") | G30: =IFERROR(XLOOKUP(A30,'Source Ledger'!$B$5:$B$200,'Source Ledger'!$G$5:$G$200),"") | H30: Ledger status Disposed but verified status is Retired/Pending Disposal; certificate evidence incomplete.
A31: MD-00118 | B31: Ledger disposed without operational disposal evidence | C31: =IFERROR(XLOOKUP(A31,'Corrected Register'!$A$5:$A$200,'Corrected Register'!$M$5:$M$200),"") | D31: =IFERROR(XLOOKUP(A31,'Corrected Register'!$A$5:$A$200,'Corrected Register'!$T$5:$T$200),"") | E31: =IF(OR(C31="",D31=""),"",D31-C31) | F31: =IFERROR(XLOOKUP(A31,'Corrected Register'!$A$5:$A$200,'Corrected Register'!$N$5:$N$200),"") | G31: =IFERROR(XLOOKUP(A31,'Source Ledger'!$B$5:$B$200,'Source Ledger'!$G$5:$G$200),"") | H31: Ledger status Disposed but verified status is Retired/Pending Disposal; certificate evidence incomplete.
A32: MD-00119 | B32: Acquisition cost mismatch | C32: =IFERROR(XLOOKUP(A32,'Corrected Register'!$A$5:$A$200,'Corrected Register'!$M$5:$M$200),"") | D32: =IFERROR(XLOOKUP(A32,'Corrected Register'!$A$5:$A$200,'Corrected Register'!$T$5:$T$200),"") | E32: =IF(OR(C32="",D32=""),"",D32-C32) | F32: =IFERROR(XLOOKUP(A32,'Corrected Register'!$A$5:$A$200,'Corrected Register'!$N$5:$N$200),"") | G32: =IFERROR(XLOOKUP(A32,'Source Ledger'!$B$5:$B$200,'Source Ledger'!$G$5:$G$200),"") | H32: Ledger FA-000119 cost exceeds register by $165. Validate against PO-2024-0024.
A33: MD-00130 | B33: On inventory, missing from ledger (under-threshold) | C33: =IFERROR(XLOOKUP(A33,'Corrected Register'!$A$5:$A$200,'Corrected Register'!$M$5:$M$200),"") | D33: =IFERROR(XLOOKUP(A33,'Corrected Register'!$A$5:$A$200,'Corrected Register'!$T$5:$T$200),"") | E33: =IF(OR(C33="",D33=""),"",D33-C33) | F33: =IFERROR(XLOOKUP(A33,'Corrected Register'!$A$5:$A$200,'Corrected Register'!$N$5:$N$200),"") | G33: =IFERROR(XLOOKUP(A33,'Source Ledger'!$B$5:$B$200,'Source Ledger'!$G$5:$G$200),"") | H33: Register cost below $2,500. PO-2023-0023 capitalization_approved=No; FAR absence expected under ITAM-001 section 7. Informational only.
A34: MD-00131 | B34: On inventory, missing from ledger (under-threshold) | C34: =IFERROR(XLOOKUP(A34,'Corrected Register'!$A$5:$A$200,'Corrected Register'!$M$5:$M$200),"") | D34: =IFERROR(XLOOKUP(A34,'Corrected Register'!$A$5:$A$200,'Corrected Register'!$T$5:$T$200),"") | E34: =IF(OR(C34="",D34=""),"",D34-C34) | F34: =IFERROR(XLOOKUP(A34,'Corrected Register'!$A$5:$A$200,'Corrected Register'!$N$5:$N$200),"") | G34: =IFERROR(XLOOKUP(A34,'Source Ledger'!$B$5:$B$200,'Source Ledger'!$G$5:$G$200),"") | H34: Register cost below $2,500. PO-2023-0023 capitalization_approved=No; FAR absence expected under ITAM-001 section 7. Informational only.
A35: MD-00132 | B35: On inventory, missing from ledger (capital-qualifying) | C35: =IFERROR(XLOOKUP(A35,'Corrected Register'!$A$5:$A$200,'Corrected Register'!$M$5:$M$200),"") | D35: =IFERROR(XLOOKUP(A35,'Corrected Register'!$A$5:$A$200,'Corrected Register'!$T$5:$T$200),"") | E35: =IF(OR(C35="",D35=""),"",D35-C35) | F35: =IFERROR(XLOOKUP(A35,'Corrected Register'!$A$5:$A$200,'Corrected Register'!$N$5:$N$200),"") | G35: =IFERROR(XLOOKUP(A35,'Source Ledger'!$B$5:$B$200,'Source Ledger'!$G$5:$G$200),"") | H35: Capital-qualifying asset on PO-2023-0022 with no FA row. RN-0132 rejected. Critical certification blocker.

Sheet Certification
A1: Quarterly Inventory Certification Statement
A2: Yanou & Partners IT Services | As of 2026-08-09 | Policy ITAM-001 §9 | Multimodal leads do not replace transaction proof
A4: Section | B4: Determination | C4: Scope / Count | D4: Evidence Basis | E4: Owner | F4: Status
A5: A. Records accepted for certification draft | B5: Operational conclusions accepted subject to listed non-blocking remediation | C5: 101 assets | D5: HR + transfer/return/disposal transaction evidence; multimodal figure/image used as control lead only | E5: IT Asset Specialist | F5: Conditional
A6: B. Assets requiring escalation before approval | B6: Cannot certify while Critical exceptions remain open | C6: 31 assets / 43 blocking exceptions | D6: Missing, overdue without receiving proof, shipment serial mismatches (incl. dock image lead for 1ZMD00000082), missing capital ledger rows (≥$2,500), missing disposal certificates | E6: IT Operations Manager | F6: BLOCKED
A7: C. HR validation required | B7: Separated employee assignments and offboarding ticket custodians | C7: 43 exceptions | D7: hr_employee_status.csv vs register/tickets | E7: HR Operations Lead | F7: Open
A8: D. Finance validation required | B8: Capital-qualifying ledger gap (MD-00132) and cost-basis variances | C8: 10 exceptions | D8: fixed_asset_ledger.xlsx + hardware_purchase_orders.csv + register costs | E8: Finance Controller | F8: Open
A9: E. Internal Audit testing recommended | B9: Sample custody chains for Missing, Overdue, Disposal gaps, and duplicate serials (MD-LA-050021 across MD-00021 and MD-00025; MD-NE-050088 across MD-00088 and MD-00092) | C9: 65 high-risk chains | D9: Custody Chain worksheet + source IDs + ITAM_control_matrix.png | E9: Internal Auditor | F9: Recommended
A11: Must be completed before the quarterly asset report is approved
A12: 1. Clear or formally risk-accept all exceptions with Certification Impact = Blocks certification.
A13: 2. Recover or loss-investigate all Verified Status = Missing assets (MD-00089-MD-00100).
A14: 3. Complete returns with carrier acceptance + delivery + receiving scan for Return Overdue assets.
A15: 4. Resolve shipment serial mismatches (MD-00074, MD-00076, MD-00082, MD-00084). Dock image for 1ZMD00000082 is a lead only.
A16: 5. Obtain disposal certificates for MD-00114 and MD-00118 (and complete pending-disposal evidence for MD-00101-MD-00110) or restore to stock.
A17: 6. Finance: add a ledger row (or approved write-off) for capital-qualifying MD-00132 only; MD-00130 and MD-00131 are under the $2,500 threshold so FA absence is expected; resolve seven acquisition-cost variances (amounts differ by asset).
A18: 7. Update the operational register to verified custodians/locations.
A19: 8. Obtain retrospective approvals for transfers TR-00058, TR-00059, TR-00064, TR-00065, TR-00127.
A20: 9. Flags duplicate serial MD-LA-050021 across MD-00021 and MD-00025, and duplicate serial MD-NE-050088 across MD-00088 and MD-00092. Physical validation and retag required.
A21: Sign-off
A22: Role | B22: Name | C22: Signature | D22: Date | E22: Determination
A23: IT Asset Specialist (preparer)
A24: IT Operations Manager
A25: Finance Controller
A26: HR Operations Lead
A27: Internal Auditor (optional review)
A29: CERTIFICATION STATUS: NOT APPROVED as of 2026-08-09. Critical exceptions remain.
A30: Critical certification blockers (must clear before sign-off)
A31: Asset Tag | B31: Blocker basis | C31: Verified status / location | D31: Exception IDs
A32: MD-00074 | B32: Critical certification blocker — Unresolved shipment serial mismatch (1ZMD00000074) | C32: In Transit - Exception / Carrier Network | D32: EX-0076
A33: MD-00076 | B33: Critical certification blocker — Unresolved shipment serial mismatch (1ZMD00000076) | C33: In Transit - Exception / Carrier Network | D33: EX-0081
A34: MD-00082 | B34: Critical certification blocker — Unresolved shipment serial mismatch (1ZMD00000082) | C34: In Transit - Exception / Carrier Network | D34: EX-0092
A35: MD-00084 | B35: Critical certification blocker — Unresolved shipment serial mismatch (1ZMD00000084) | C35: In Transit - Exception / Carrier Network | D35: EX-0095
A36: MD-00114 | B36: Critical certification blocker — Retired/Pending Disposal without verified disposal certificate | C36: Retired/Pending Disposal / Disposed (certificate missing) | D36: EX-0149, EX-0150
A37: MD-00118 | B37: Critical certification blocker — Retired/Pending Disposal without verified disposal certificate | C37: Retired/Pending Disposal / Disposed (certificate missing) | D37: EX-0151, EX-0152
A38: MD-00132 | B38: Critical certification blocker — Capital-qualifying asset missing from fixed-asset ledger | C38: Pending Redeployment / Atlanta Warehouse | D38: EX-0163

Sheet Evidence Index
A1: Evidence Index - Source Systems of Record
A3: Source File | B3: Role | C3: Key Fields Used | D3: Evidentiary Weight
A4: it_asset_inventory.xlsx | B4: Operational asset register (pre-reconciliation) | C4: Asset tag, serial, model, assigned employee, location, cost, warranty, lifecycle status | D4: Not assumed current
A5: hr_employee_status.csv | B5: HR employment status (authoritative) | C5: Active / Transferred / Separated; locations; termination and transfer dates | D5: Authoritative for employment
A6: equipment_transfer_log.csv | B6: Approved/unapproved movements | C6: Transfer ID, custodians, locations, approval ID, received date | D6: Authoritative for movement when approved + received
A7: service_desk_offboarding.csv | B7: Offboarding and retirement tickets | C7: Ticket number, employee, assets, return due, ticket status, comments | D7: Ticket status authoritative; comments are claims
A8: device_return_shipments.csv | B8: Return shipping activity | C8: Tracking, dates, receiving scan, shipment status, serial on shipment | D8: Label ≠ return; need acceptance+delivery+scan
A9: hardware_purchase_orders.csv | B9: Acquisition / procurement | C9: PO, vendor, asset tags, approved amount, capitalization flag | D9: Validates acquisition
A10: fixed_asset_ledger.xlsx | B10: Accounting book value | C10: FA ID, capitalized flag, cost, accum. dep., NBV, ledger status | D10: Authoritative for NBV
A11: asset_disposal_records.csv | B11: Disposal certificates | C11: Certificate ID, tag, serial, method, vendor, verified flag | D11: Required for Disposed status
A12: IT_asset_management_policy.pdf | B12: Policy ITAM-001 v3.2 (includes embedded control-matrix figure) | C12: Assignment, transfer, return, loss, disposal, financial, certification rules | D12: Control criteria
A13: ITAM_control_matrix.png | B13: Policy Appendix A control-matrix figure | C13: Required evidence by control; failure classification; owner | D13: Visual policy exhibit; use with PDF
A14: receiving_exception_scan_1ZMD00000082.png | B14: Atlanta warehouse dock exception photo lead | C14: Tracking 1ZMD00000082; MISMATCH serial HOLD tag | D14: Image lead only; NOT receiving clearance
A15: regional_IT_notes.docx | B15: Informal technician notes | C15: Leads on closed offices, disposals, approvals, mismatches | D15: Non-authoritative leads only

Sheet Methodology
A1: Reconciliation Methodology
A3: Step | B3: Description
A4: 1. Population | B4: Loaded 132 register assets; matched to HR, transfers, tickets, shipments, POs, ledger (129), disposal certificates (8), plus multimodal policy figure and dock image lead.
A5: 2. Custodian verification | B5: Did not trust register owner/status. Applied HR employment status and latest transfer to_custodian / to_location.
A6: 3. Return verification | B6: Required carrier acceptance + delivery + receiving scan with serial match. Label-created and Past Due remain Return Overdue. Dock image is lead only.
A7: 4. Disposal verification | B7: Required certificate_verified=Yes matching tag/serial. Recycler transfers without certificates stay Retired/Pending Disposal.
A8: 5. Exceptions | B8: Raised discrete exceptions with exact IDs; shipment mismatch for MD-00082 cites receiving_exception_scan_1ZMD00000082.png as lead.
A9: 6. Financials | B9: Acquisition cost from register; remaining book value from ledger NBV. Missing ledger assets show blank NBV.
A10: 7. Custody chains | B10: Built for high-risk / unresolved / Critical-exception assets; separated Confirmed Fact vs Technician Claim vs Unresolved Assumption.
A11: 8. Non-invention rule | B11: No synthetic transfers, returns, approvals, or disposal certificates were created. Image leads do not invent clearance.
A12: 9
A14: Capitalization gate | B14: Applied ITAM-001 §7 per-asset $2,500 threshold. Did not treat PO capitalization_approved as forcing FA rows for under-threshold lines (MD-00130/MD-00131). Flagged only MD-00132 as Critical missing capital row. Rejected RN-0132.
A15: Evidence precedence | B15: Applied §3 order: ledger/certificates/carrier scans > approved transfers > HR > ticket status > notes/images.
A16: Duplicate serials | B16: Flags duplicate serial MD-LA-050021 across MD-00021 and MD-00025, and duplicate serial MD-NE-050088 across MD-00088 and MD-00092.
